Workbook

Sheet Вводные
D3: Год | J3: =F10 -> 2024 | K3: =J3+1 -> 2025 | L3: =K3+1 -> 2026 | M3: =L3+1 -> 2027 | N3: =M3+1 -> 2028 | O3: =N3+1 -> 2029 | P3: =O3+1 -> 2030 | Q3: =P3+1 -> 2031 | R3: =Q3+1 -> 2032 | ... BJ3: =BI3+1 -> 2076
D4: Возраст | J4: =J3 - $F$11 -> 31 | K4: =K3 - $F$11 -> 32 | L4: =L3 - $F$11 -> 33 | M4: =M3 - $F$11 -> 34 | N4: =N3 - $F$11 -> 35 | O4: =O3 - $F$11 -> 36 | P4: =P3 - $F$11 -> 37 | Q4: =Q3 - $F$11 -> 38 | ... BJ4: =BJ3 - $F$11 -> 83
D5: № периода | J5: =IF( J$3 = $F$10, 1, H$5 + 1 ) -> 1 | K5: =IF( K$3 = $F$10, 0, J$5 + 1 ) -> 2 | L5: =IF( L$3 = $F$10, 0, K$5 + 1 ) -> 3 | M5: =IF( M$3 = $F$10, 0, L$5 + 1 ) -> 4 | N5: =IF( N$3 = $F$10, 0, M$5 + 1 ) -> 5 | O5: =IF( O$3 = $F$10, 0, N$5 + 1 ) -> 6 | P5: =IF( P$3 = $F$10, 0, O$5 + 1 ) -> 7 | Q5: =IF( Q$3 = $F$10, 0, P$5 + 1 ) -> 8 | R5: =IF( R$3 = $F$10, 0, Q$5 + 1 ) -> 9 | ... BJ5: =IF( BJ$3 = $F$10, 0, BI$5 + 1 ) -> 53
B8: =MAX( $B$7:B7 ) + 1 -> 1 | D8: Технические
D10: Дата начала | E10: год | F10: 2024
D11: Год рождения | E11: год | F11: 1993
D12: Месяцев в году | E12: x | F12: 12
D14: Инфляция | E14: % | J14: 0.05 | K14: 0.03 | L14: 0.03 | M14: 0.03 | N14: 0.03 | O14: 0.03 | P14: 0.03 | Q14: 0.03 | R14: 0.03 | S14: 0.03 | T14: 0.03 | U14: 0.03 | V14: 0.03 | W14: 0.03 | X14: 0.03 | Y14: 0.03 | Z14: 0.03 | AA14: 0.03 | AB14: 0.03 | AC14: 0.03 | AD14: 0.03 | AE14: 0.03 | AF14: 0.03 | AG14: 0.03 | AH14: 0.03 | AI14: 0.03 | AJ14: 0.03 | AK14: 0.03 | AL14: 0.03 | AM14: 0.03 | AN14: 0.03 | AO14: 0.03 | AP14: 0.03 | AQ14: 0.03 | AR14: 0.03 | AS14: 0.03 | AT14: 0.03 | AU14: 0.03 | AV14: 0.03 | AW14: 0.03 | AX14: 0.03 | AY14: 0.03 | AZ14: 0.03 | BA14: 0.03 | BB14: 0.03 | BC14: 0.03 | BD14: 0.03 | BE14: 0.03 | BF14: 0.03 | BG14: 0.03 | BH14: 0.03 | BI14: 0.03 | BJ14: 0.03
D15: Доходность на инвестированный капитал | E15: % | F15: 0.06
B17: =MAX( $B$7:B16 ) + 1 -> 2 | D17: Доходы
C19: =MAX( $B$7:C18 ) + 0.1 -> 2.1 | D19: Ежемесячные доходы
D21: Ежемесячные доходы | F21: =SUM(F22:F26) -> 13000
D22: Income 1 | E22: USD / мес. | F22: 10000
D23: Income 2 | E23: USD / мес. | F23: 2000
D24: Income 3 | E24: USD / мес. | F24: 1000
D25: Ежемесячный доход 4 | E25: USD / мес. | F25: 0
D26: Ежемесячный доход 5 | E26: USD / мес. | F26: 0
D28: Период получения доходов
D29: =$D$22 -> Income 1 | E29: год | F29: 2024 | G29: 2076
D30: =$D$23 -> Income 2 | E30: год | F30: 2024 | G30: 2024
D31: =$D$24 -> Income 3 | E31: год | F31: 2024 | G31: 2076
D32: =$D$25 -> Ежемесячный доход 4 | E32: год | F32: 2025 | G32: 2076
D33: =$D$26 -> Ежемесячный доход 5 | E33: год | F33: 2024 | G33: 2076
D35: Темп роста ежемесячных доходов
D36: ="Темп роста " & D22 -> Темп роста Income 1 | E36: % | J36: 0 | K36: 0.5 | L36: =L$14 -> 0.03 | M36: =M$14 -> 0.03 | N36: =N$14 -> 0.03 | O36: =O$14 -> 0.03 | P36: =P$14 -> 0.03 | Q36: =Q$14 -> 0.03 | R36: =R$14 -> 0.03 | S36: =S$14 -> 0.03 | ... BJ36: =BJ$14 -> 0.03
D37: ="Темп роста " & D23 -> Темп роста Income 2 | E37: % | J37: 0 | K37: 0 | L37: 0 | M37: 0 | N37: 0 | O37: 0 | P37: 0 | Q37: 0 | R37: 0 | S37: 0 | T37: 0 | U37: 0 | V37: 0 | W37: 0 | X37: 0 | Y37: 0 | Z37: 0 | AA37: 0 | AB37: 0 | AC37: 0 | AD37: 0 | AE37: 0 | AF37: 0 | AG37: 0 | AH37: 0 | AI37: 0 | AJ37: 0 | AK37: 0 | AL37: 0 | AM37: 0 | AN37: 0 | AO37: 0 | AP37: 0 | AQ37: 0 | AR37: 0 | AS37: 0 | AT37: 0 | AU37: 0 | AV37: 0 | AW37: 0 | AX37: 0 | AY37: 0 | AZ37: 0 | BA37: 0 | BB37: 0 | BC37: 0 | BD37: 0 | BE37: 0 | BF37: 0 | BG37: 0 | BH37: 0 | BI37: 0 | BJ37: 0
D38: ="Темп роста " & D24 -> Темп роста Income 3 | E38: % | J38: 0 | K38: =K$14 -> 0.03 | L38: =L$14 -> 0.03 | M38: =M$14 -> 0.03 | N38: =N$14 -> 0.03 | O38: =O$14 -> 0.03 | P38: =P$14 -> 0.03 | Q38: =Q$14 -> 0.03 | R38: =R$14 -> 0.03 | ... BJ38: =BJ$14 -> 0.03
D39: ="Темп роста " & D25 -> Темп роста Ежемесячный доход 4 | E39: % | J39: 0 | K39: =K$14 -> 0.03 | L39: =L$14 -> 0.03 | M39: =M$14 -> 0.03 | N39: =N$14 -> 0.03 | O39: =O$14 -> 0.03 | P39: =P$14 -> 0.03 | Q39: =Q$14 -> 0.03 | R39: =R$14 -> 0.03 | ... BJ39: =BJ$14 -> 0.03
D40: ="Темп роста " & D26 -> Темп роста Ежемесячный доход 5 | E40: % | J40: 0 | K40: =K$14 -> 0.03 | L40: =L$14 -> 0.03 | M40: =M$14 -> 0.03 | N40: =N$14 -> 0.03 | O40: =O$14 -> 0.03 | P40: =P$14 -> 0.03 | Q40: =Q$14 -> 0.03 | R40: =R$14 -> 0.03 | ... BJ40: =BJ$14 -> 0.03
C42: =MAX( $B$7:C41 ) + 0.1 -> 2.2 | D42: Ежегодные доходы
D44: Ежегодные доходы | F44: =SUM(F45:F49) -> 0
D45: Ежегодный доход 1 | E45: USD / год | F45: 0
D46: Ежегодный доход 2 | E46: USD / год | F46: 0
D47: Ежегодный доход 3 | E47: USD / год | F47: 0
D48: Ежегодный доход 4 | E48: USD / год | F48: 0
D49: Ежегодный доход 5 | E49: USD / год | F49: 0
D51: Ежегодные доходы
D52: =Вводные!$D$45 -> Ежегодный доход 1 | E52: год | F52: 2024 | G52: 2076
D53: =Вводные!$D$46 -> Ежегодный доход 2 | E53: год | F53: 2024 | G53: 2076
D54: =Вводные!$D$47 -> Ежегодный доход 3 | E54: год | F54: 2024 | G54: 2076
D55: =Вводные!$D$48 -> Ежегодный доход 4 | E55: год | F55: 2024 | G55: 2076
D56: =Вводные!$D$49 -> Ежегодный доход 5 | E56: год | F56: 2024 | G56: 2076
D58: Темп роста ежегодных доходов
D59: ="Темп роста " & D45 -> Темп роста Ежегодный доход 1 | E59: % | J59: 0 | K59: =K$14 -> 0.03 | L59: =L$14 -> 0.03 | M59: =M$14 -> 0.03 | N59: =N$14 -> 0.03 | O59: =O$14 -> 0.03 | P59: =P$14 -> 0.03 | Q59: =Q$14 -> 0.03 | R59: =R$14 -> 0.03 | ... BJ59: =BJ$14 -> 0.03
D60: ="Темп роста " & D46 -> Темп роста Ежегодный доход 2 | E60: % | J60: 0 | K60: =K$14 -> 0.03 | L60: =L$14 -> 0.03 | M60: =M$14 -> 0.03 | N60: =N$14 -> 0.03 | O60: =O$14 -> 0.03 | P60: =P$14 -> 0.03 | Q60: =Q$14 -> 0.03 | R60: =R$14 -> 0.03 | ... BJ60: =BJ$14 -> 0.03
D61: ="Темп роста " & D47 -> Темп роста Ежегодный доход 3 | E61: % | J61: 0 | K61: =K$14 -> 0.03 | L61: =L$14 -> 0.03 | M61: =M$14 -> 0.03 | N61: =N$14 -> 0.03 | O61: =O$14 -> 0.03 | P61: =P$14 -> 0.03 | Q61: =Q$14 -> 0.03 | R61: =R$14 -> 0.03 | ... BJ61: =BJ$14 -> 0.03
D62: ="Темп роста " & D48 -> Темп роста Ежегодный доход 4 | E62: % | J62: 0 | K62: =K$14 -> 0.03 | L62: =L$14 -> 0.03 | M62: =M$14 -> 0.03 | N62: =N$14 -> 0.03 | O62: =O$14 -> 0.03 | P62: =P$14 -> 0.03 | Q62: =Q$14 -> 0.03 | R62: =R$14 -> 0.03 | ... BJ62: =BJ$14 -> 0.03
D63: ="Темп роста " & D49 -> Темп роста Ежегодный доход 5 | E63: % | J63: 0 | K63: =K$14 -> 0.03 | L63: =L$14 -> 0.03 | M63: =M$14 -> 0.03 | N63: =N$14 -> 0.03 | O63: =O$14 -> 0.03 | P63: =P$14 -> 0.03 | Q63: =Q$14 -> 0.03 | R63: =R$14 -> 0.03 | ... BJ63: =BJ$14 -> 0.03
B65: =MAX( $B$7:B64 ) + 1 -> 3 | D65: Расходы
C67: =MAX( $B$7:C66 ) + 0.1 -> 3.1 | D67: Ежемесячные расходы
D69: Ежемесячные расходы | F69: =SUM(F70:F89) -> -8000
D70: Еда | E70: USD / мес. | F70: -1000
D71: Садик | E71: USD / мес. | F71: -1000
D72: Няня | E72: USD / мес. | F72: -1000
D73: Ипотека | E73: USD / мес. | F73: -1000
D74: Аренда квартиры + коммуналка | E74: USD / мес. | F74: -1000
D75: Связь + интернет | E75: USD / мес. | F75: -1000
D76: Командировки | E76: USD / мес. | F76: -1000
D77: Прочее | E77: USD / мес. | F77: -1000
D78: Ежемесячный расход 9 | E78: USD / мес. | F78: 0
D79: Ежемесячный расход 10 | E79: USD / мес. | F79: 0
D80: Ежемесячный расход 11 | E80: USD / мес. | F80: 0
D81: Ежемесячный расход 12 | E81: USD / мес. | F81: 0
... D89: Ежемесячный расход 20 | E89: USD / мес. | F89: 0
D91: Темп роста ежемесячных расходов
D92: ="Темп роста " & D70 -> Темп роста Еда | E92: % | J92: 0 | K92: =K$14 -> 0.03 | L92: =L$14 -> 0.03 | M92: =M$14 -> 0.03 | N92: =N$14 -> 0.03 | O92: =O$14 -> 0.03 | P92: =P$14 -> 0.03 | Q92: =Q$14 -> 0.03 | R92: =R$14 -> 0.03 | ... BJ92: =BJ$14 -> 0.03
D93: ="Темп роста " & D71 -> Темп роста Садик | E93: % | J93: 0 | K93: =K$14 -> 0.03 | L93: =L$14 -> 0.03 | M93: =M$14 -> 0.03 | N93: =N$14 -> 0.03 | O93: =O$14 -> 0.03 | P93: =P$14 -> 0.03 | Q93: =Q$14 -> 0.03 | R93: =R$14 -> 0.03 | ... BJ93: =BJ$14 -> 0.03
D94: ="Темп роста " & D72 -> Темп роста Няня | E94: % | J94: 0 | K94: =K$14 -> 0.03 | L94: =L$14 -> 0.03 | M94: =M$14 -> 0.03 | N94: =N$14 -> 0.03 | O94: =O$14 -> 0.03 | P94: =P$14 -> 0.03 | Q94: =Q$14 -> 0.03 | R94: =R$14 -> 0.03 | ... BJ94: =BJ$14 -> 0.03
D95: ="Темп роста " & D73 -> Темп роста Ипотека | E95: % | J95: 0 | K95: 0 | L95: 0 | M95: 0 | N95: 0 | O95: 0 | P95: 0 | Q95: 0 | R95: 0 | S95: 0 | T95: 0 | U95: 0 | V95: 0 | W95: 0 | X95: 0 | Y95: 0 | Z95: 0 | AA95: 0 | AB95: 0 | AC95: 0 | AD95: 0 | AE95: 0 | AF95: 0 | AG95: 0 | AH95: 0 | AI95: 0 | AJ95: 0 | AK95: 0 | AL95: 0 | AM95: 0 | AN95: 0 | AO95: 0 | AP95: 0 | AQ95: 0 | AR95: 0 | AS95: 0 | AT95: 0 | AU95: 0 | AV95: 0 | AW95: 0 | AX95: 0 | AY95: 0 | AZ95: 0 | BA95: 0 | BB95: 0 | BC95: 0 | BD95: 0 | BE95: 0 | BF95: 0 | BG95: 0 | BH95: 0 | BI95: 0 | BJ95: 0
D96: ="Темп роста " & D74 -> Темп роста Аренда квартиры + коммуналка | E96: % | J96: 0 | K96: =K$14 -> 0.03 | L96: =L$14 -> 0.03 | M96: =M$14 -> 0.03 | N96: =N$14 -> 0.03 | O96: =O$14 -> 0.03 | P96: =P$14 -> 0.03 | Q96: =Q$14 -> 0.03 | R96: =R$14 -> 0.03 | ... BJ96: =BJ$14 -> 0.03
D97: ="Темп роста " & D75 -> Темп роста Связь + интернет | E97: % | J97: 0 | K97: =K$14 -> 0.03 | L97: =L$14 -> 0.03 | M97: =M$14 -> 0.03 | N97: =N$14 -> 0.03 | O97: =O$14 -> 0.03 | P97: =P$14 -> 0.03 | Q97: =Q$14 -> 0.03 | R97: =R$14 -> 0.03 | ... BJ97: =BJ$14 -> 0.03
D98: ="Темп роста " & D76 -> Темп роста Командировки | E98: % | J98: 0 | K98: =K$14 -> 0.03 | L98: =L$14 -> 0.03 | M98: =M$14 -> 0.03 | N98: =N$14 -> 0.03 | O98: =O$14 -> 0.03 | P98: =P$14 -> 0.03 | Q98: =Q$14 -> 0.03 | R98: =R$14 -> 0.03 | ... BJ98: =BJ$14 -> 0.03
D99: ="Темп роста " & D77 -> Темп роста Прочее | E99: % | J99: 0 | K99: =K$14 -> 0.03 | L99: =L$14 -> 0.03 | M99: =M$14 -> 0.03 | N99: =N$14 -> 0.03 | O99: =O$14 -> 0.03 | P99: =P$14 -> 0.03 | Q99: =Q$14 -> 0.03 | R99: =R$14 -> 0.03 | ... BJ99: =BJ$14 -> 0.03
D100: ="Темп роста " & D78 -> Темп роста Ежемесячный расход 9 | E100: % | J100: 0 | K100: =K$14 -> 0.03 | L100: =L$14 -> 0.03 | M100: =M$14 -> 0.03 | N100: =N$14 -> 0.03 | O100: =O$14 -> 0.03 | P100: =P$14 -> 0.03 | Q100: =Q$14 -> 0.03 | R100: =R$14 -> 0.03 | ... BJ100: =BJ$14 -> 0.03
D101: ="Темп роста " & D79 -> Темп роста Ежемесячный расход 10 | E101: % | J101: 0 | K101: =K$14 -> 0.03 | L101: =L$14 -> 0.03 | M101: =M$14 -> 0.03 | N101: =N$14 -> 0.03 | O101: =O$14 -> 0.03 | P101: =P$14 -> 0.03 | Q101: =Q$14 -> 0.03 | R101: =R$14 -> 0.03 | ... BJ101: =BJ$14 -> 0.03
D102: ="Темп роста " & D80 -> Темп роста Ежемесячный расход 11 | E102: % | J102: 0 | K102: =K$14 -> 0.03 | L102: =L$14 -> 0.03 | M102: =M$14 -> 0.03 | N102: =N$14 -> 0.03 | O102: =O$14 -> 0.03 | P102: =P$14 -> 0.03 | Q102: =Q$14 -> 0.03 | R102: =R$14 -> 0.03 | ... BJ102: =BJ$14 -> 0.03
D103: ="Темп роста " & D81 -> Темп роста Ежемесячный расход 12 | E103: % | J103: 0 | K103: =K$14 -> 0.03 | L103: =L$14 -> 0.03 | M103: =M$14 -> 0.03 | N103: =N$14 -> 0.03 | O103: =O$14 -> 0.03 | P103: =P$14 -> 0.03 | Q103: =Q$14 -> 0.03 | R103: =R$14 -> 0.03 | ... BJ103: =BJ$14 -> 0.03
D104: ="Темп роста " & D82 -> Темп роста Ежемесячный расход 13 | E104: % | J104: 0 | K104: =K$14 -> 0.03 | L104: =L$14 -> 0.03 | M104: =M$14 -> 0.03 | N104: =N$14 -> 0.03 | O104: =O$14 -> 0.03 | P104: =P$14 -> 0.03 | Q104: =Q$14 -> 0.03 | R104: =R$14 -> 0.03 | ... BJ104: =BJ$14 -> 0.03
D105: ="Темп роста " & D83 -> Темп роста Ежемесячный расход 14 | E105: % | J105: 0 | K105: =K$14 -> 0.03 | L105: =L$14 -> 0.03 | M105: =M$14 -> 0.03 | N105: =N$14 -> 0.03 | O105: =O$14 -> 0.03 | P105: =P$14 -> 0.03 | Q105: =Q$14 -> 0.03 | R105: =R$14 -> 0.03 | ... BJ105: =BJ$14 -> 0.03
D106: ="Темп роста " & D84 -> Темп роста Ежемесячный расход 15 | E106: % | J106: 0 | K106: =K$14 -> 0.03 | L106: =L$14 -> 0.03 | M106: =M$14 -> 0.03 | N106: =N$14 -> 0.03 | O106: =O$14 -> 0.03 | P106: =P$14 -> 0.03 | Q106: =Q$14 -> 0.03 | R106: =R$14 -> 0.03 | ... BJ106: =BJ$14 -> 0.03
D107: ="Темп роста " & D85 -> Темп роста Ежемесячный расход 16 | E107: % | J107: 0 | K107: =K$14 -> 0.03 | L107: =L$14 -> 0.03 | M107: =M$14 -> 0.03 | N107: =N$14 -> 0.03 | O107: =O$14 -> 0.03 | P107: =P$14 -> 0.03 | Q107: =Q$14 -> 0.03 | R107: =R$14 -> 0.03 | ... BJ107: =BJ$14 -> 0.03
... D111: ="Темп роста " & D89 -> Темп роста Ежемесячный расход 20 | E111: % | J111: 0 | K111: =K$14 -> 0.03 | L111: =L$14 -> 0.03 | M111: =M$14 -> 0.03 | N111: =N$14 -> 0.03 | O111: =O$14 -> 0.03 | P111: =P$14 -> 0.03 | Q111: =Q$14 -> 0.03 | R111: =R$14 -> 0.03 | ... BJ111: =BJ$14 -> 0.03
C113: =MAX( $B$7:C112 ) + 0.1 -> 3.2 | D113: Ежегодные расходы
D115: Ежегодные расходы | F115: =SUM(F116:F125) -> -21000
D116: Страховка | E116: USD / год | F116: -3000
D117: Детский сад / школа | E117: USD / год | F117: -3000
D118: Страховка по ипотеке | E118: USD / год | F118: -3000
D119: Отпуск | E119: USD / год | F119: -3000
D120: Долг 2 млн | E120: USD / год | F120: -3000
D121: Долг за квартиру | E121: USD / год | F121: -3000
D122: Подарки | E122: USD / год | F122: -3000
D123: Ежегодный расход 8 | E123: USD / год | F123: 0
D124: Ежегодный расход 9 | E124: USD / год | F124: 0
D125: Ежегодный расход 10 | E125: USD / год | F125: 0
D127: Темп роста ежегодных расходов
D128: ="Темп роста " & D116 -> Темп роста Страховка | E128: % | J128: 0 | K128: =K$14 -> 0.03 | L128: =L$14 -> 0.03 | M128: =M$14 -> 0.03 | N128: =N$14 -> 0.03 | O128: =O$14 -> 0.03 | P128: =P$14 -> 0.03 | Q128: =Q$14 -> 0.03 | R128: =R$14 -> 0.03 | ... BJ128: =BJ$14 -> 0.03
D129: ="Темп роста " & D117 -> Темп роста Детский сад / школа | E129: % | J129: 0 | K129: =K$14 -> 0.03 | L129: =L$14 -> 0.03 | M129: =M$14 -> 0.03 | N129: =N$14 -> 0.03 | O129: =O$14 -> 0.03 | P129: =P$14 -> 0.03 | Q129: =Q$14 -> 0.03 | R129: =R$14 -> 0.03 | ... BJ129: =BJ$14 -> 0.03
D130: ="Темп роста " & D118 -> Темп роста Страховка по ипотеке | E130: % | J130: 0 | K130: 0 | L130: 0 | M130: 0 | N130: 0 | O130: 0 | P130: 0 | Q130: 0 | R130: 0 | S130: 0 | T130: 0 | U130: 0 | V130: 0 | W130: 0 | X130: 0 | Y130: 0 | Z130: 0 | AA130: 0 | AB130: 0 | AC130: 0 | AD130: 0 | AE130: 0 | AF130: 0 | AG130: 0 | AH130: 0 | AI130: 0 | AJ130: 0 | AK130: 0 | AL130: 0 | AM130: 0 | AN130: 0 | AO130: 0 | AP130: 0 | AQ130: 0 | AR130: 0 | AS130: 0 | AT130: 0 | AU130: 0 | AV130: 0 | AW130: 0 | AX130: 0 | AY130: 0 | AZ130: 0 | BA130: 0 | BB130: 0 | BC130: 0 | BD130: 0 | BE130: 0 | BF130: 0 | BG130: 0 | BH130: 0 | BI130: 0 | BJ130: 0
D131: ="Темп роста " & D119 -> Темп роста Отпуск | E131: % | J131: 0 | K131: =K$14 -> 0.03 | L131: =L$14 -> 0.03 | M131: =M$14 -> 0.03 | N131: =N$14 -> 0.03 | O131: =O$14 -> 0.03 | P131: =P$14 -> 0.03 | Q131: =Q$14 -> 0.03 | R131: =R$14 -> 0.03 | ... BJ131: =BJ$14 -> 0.03
D132: ="Темп роста " & D120 -> Темп роста Долг 2 млн | E132: % | J132: 0 | K132: 0 | L132: 0 | M132: 0 | N132: 0 | O132: 0 | P132: 0 | Q132: 0 | R132: 0 | S132: 0 | T132: 0 | U132: 0 | V132: 0 | W132: 0 | X132: 0 | Y132: 0 | Z132: 0 | AA132: 0 | AB132: 0 | AC132: 0 | AD132: 0 | AE132: 0 | AF132: 0 | AG132: 0 | AH132: 0 | AI132: 0 | AJ132: 0 | AK132: 0 | AL132: 0 | AM132: 0 | AN132: 0 | AO132: 0 | AP132: 0 | AQ132: 0 | AR132: 0 | AS132: 0 | AT132: 0 | AU132: 0 | AV132: 0 | AW132: 0 | AX132: 0 | AY132: 0 | AZ132: 0 | BA132: 0 | BB132: 0 | BC132: 0 | BD132: 0 | BE132: 0 | BF132: 0 | BG132: 0 | BH132: 0 | BI132: 0 | BJ132: 0
...

Sheet Доходы
D3: =Вводные!D3 -> Год | J3: =Вводные!J3 -> 2024 | K3: =Вводные!K3 -> 2025 | L3: =Вводные!L3 -> 2026 | M3: =Вводные!M3 -> 2027 | N3: =Вводные!N3 -> 2028 | O3: =Вводные!O3 -> 2029 | P3: =Вводные!P3 -> 2030 | Q3: =Вводные!Q3 -> 2031 | ... BJ3: =Вводные!BJ3 -> 2076
D4: =Вводные!D4 -> Возраст | J4: =Вводные!J4 -> 31 | K4: =Вводные!K4 -> 32 | L4: =Вводные!L4 -> 33 | M4: =Вводные!M4 -> 34 | N4: =Вводные!N4 -> 35 | O4: =Вводные!O4 -> 36 | P4: =Вводные!P4 -> 37 | Q4: =Вводные!Q4 -> 38 | ... BJ4: =Вводные!BJ4 -> 83
D5: =Вводные!D5 -> № периода | J5: =Вводные!J5 -> 1 | K5: =Вводные!K5 -> 2 | L5: =Вводные!L5 -> 3 | M5: =Вводные!M5 -> 4 | N5: =Вводные!N5 -> 5 | O5: =Вводные!O5 -> 6 | P5: =Вводные!P5 -> 7 | Q5: =Вводные!Q5 -> 8 | ... BJ5: =Вводные!BJ5 -> 53
B8: =MAX( $B5:B$7 ) + 1 -> 1 | D8: Флаги
C10: =MAX( $B$7:C9 ) + 0.1 -> 1.1 | D10: Флаги получения дохода
D12: Ежемесячные доходы
D13: =Вводные!$D$22 -> Income 1 | E13: флаг | J13: =IF( AND(J$3 >= Вводные!$F29, J$3 <= Вводные!$G29), 1, 0) -> 1 | K13: =IF( AND(K$3 >= Вводные!$F29, K$3 <= Вводные!$G29), 1, 0) -> 1 | L13: =IF( AND(L$3 >= Вводные!$F29, L$3 <= Вводные!$G29), 1, 0) -> 1 | M13: =IF( AND(M$3 >= Вводные!$F29, M$3 <= Вводные!$G29), 1, 0) -> 1 | N13: =IF( AND(N$3 >= Вводные!$F29, N$3 <= Вводные!$G29), 1, 0) -> 1 | O13: =IF( AND(O$3 >= Вводные!$F29, O$3 <= Вводные!$G29), 1, 0) -> 1 | P13: =IF( AND(P$3 >= Вводные!$F29, P$3 <= Вводные!$G29), 1, 0) -> 1 | Q13: =IF( AND(Q$3 >= Вводные!$F29, Q$3 <= Вводные!$G29), 1, 0) -> 1 | ... BJ13: =IF( AND(BJ$3 >= Вводные!$F29, BJ$3 <= Вводные!$G29), 1, 0) -> 1
D14: =Вводные!$D$23 -> Income 2 | E14: флаг | J14: =IF( AND(J$3 >= Вводные!$F30, J$3 <= Вводные!$G30), 1, 0) -> 1 | K14: =IF( AND(K$3 >= Вводные!$F30, K$3 <= Вводные!$G30), 1, 0) -> 0 | L14: =IF( AND(L$3 >= Вводные!$F30, L$3 <= Вводные!$G30), 1, 0) -> 0 | M14: =IF( AND(M$3 >= Вводные!$F30, M$3 <= Вводные!$G30), 1, 0) -> 0 | N14: =IF( AND(N$3 >= Вводные!$F30, N$3 <= Вводные!$G30), 1, 0) -> 0 | O14: =IF( AND(O$3 >= Вводные!$F30, O$3 <= Вводные!$G30), 1, 0) -> 0 | P14: =IF( AND(P$3 >= Вводные!$F30, P$3 <= Вводные!$G30), 1, 0) -> 0 | Q14: =IF( AND(Q$3 >= Вводные!$F30, Q$3 <= Вводные!$G30), 1, 0) -> 0 | ... BJ14: =IF( AND(BJ$3 >= Вводные!$F30, BJ$3 <= Вводные!$G30), 1, 0) -> 0
D15: =Вводные!$D$24 -> Income 3 | E15: флаг | J15: =IF( AND(J$3 >= Вводные!$F31, J$3 <= Вводные!$G31), 1, 0) -> 1 | K15: =IF( AND(K$3 >= Вводные!$F31, K$3 <= Вводные!$G31), 1, 0) -> 1 | L15: =IF( AND(L$3 >= Вводные!$F31, L$3 <= Вводные!$G31), 1, 0) -> 1 | M15: =IF( AND(M$3 >= Вводные!$F31, M$3 <= Вводные!$G31), 1, 0) -> 1 | N15: =IF( AND(N$3 >= Вводные!$F31, N$3 <= Вводные!$G31), 1, 0) -> 1 | O15: =IF( AND(O$3 >= Вводные!$F31, O$3 <= Вводные!$G31), 1, 0) -> 1 | P15: =IF( AND(P$3 >= Вводные!$F31, P$3 <= Вводные!$G31), 1, 0) -> 1 | Q15: =IF( AND(Q$3 >= Вводные!$F31, Q$3 <= Вводные!$G31), 1, 0) -> 1 | ... BJ15: =IF( AND(BJ$3 >= Вводные!$F31, BJ$3 <= Вводные!$G31), 1, 0) -> 1
D16: =Вводные!$D$25 -> Ежемесячный доход 4 | E16: флаг | J16: =IF( AND(J$3 >= Вводные!$F32, J$3 <= Вводные!$G32), 1, 0) -> 0 | K16: =IF( AND(K$3 >= Вводные!$F32, K$3 <= Вводные!$G32), 1, 0) -> 1 | L16: =IF( AND(L$3 >= Вводные!$F32, L$3 <= Вводные!$G32), 1, 0) -> 1 | M16: =IF( AND(M$3 >= Вводные!$F32, M$3 <= Вводные!$G32), 1, 0) -> 1 | N16: =IF( AND(N$3 >= Вводные!$F32, N$3 <= Вводные!$G32), 1, 0) -> 1 | O16: =IF( AND(O$3 >= Вводные!$F32, O$3 <= Вводные!$G32), 1, 0) -> 1 | P16: =IF( AND(P$3 >= Вводные!$F32, P$3 <= Вводные!$G32), 1, 0) -> 1 | Q16: =IF( AND(Q$3 >= Вводные!$F32, Q$3 <= Вводные!$G32), 1, 0) -> 1 | ... BJ16: =IF( AND(BJ$3 >= Вводные!$F32, BJ$3 <= Вводные!$G32), 1, 0) -> 1
D17: =Вводные!$D$26 -> Ежемесячный доход 5 | E17: флаг | J17: =IF( AND(J$3 >= Вводные!$F33, J$3 <= Вводные!$G33), 1, 0) -> 1 | K17: =IF( AND(K$3 >= Вводные!$F33, K$3 <= Вводные!$G33), 1, 0) -> 1 | L17: =IF( AND(L$3 >= Вводные!$F33, L$3 <= Вводные!$G33), 1, 0) -> 1 | M17: =IF( AND(M$3 >= Вводные!$F33, M$3 <= Вводные!$G33), 1, 0) -> 1 | N17: =IF( AND(N$3 >= Вводные!$F33, N$3 <= Вводные!$G33), 1, 0) -> 1 | O17: =IF( AND(O$3 >= Вводные!$F33, O$3 <= Вводные!$G33), 1, 0) -> 1 | P17: =IF( AND(P$3 >= Вводные!$F33, P$3 <= Вводные!$G33), 1, 0) -> 1 | Q17: =IF( AND(Q$3 >= Вводные!$F33, Q$3 <= Вводные!$G33), 1, 0) -> 1 | ... BJ17: =IF( AND(BJ$3 >= Вводные!$F33, BJ$3 <= Вводные!$G33), 1, 0) -> 1
D19: Ежегодные доходы
D20: =Вводные!$D$45 -> Ежегодный доход 1 | E20: флаг | J20: =IF( AND(J$3 >= Вводные!$F52, J$3 <= Вводные!$G52), 1, 0) -> 1 | K20: =IF( AND(K$3 >= Вводные!$F52, K$3 <= Вводные!$G52), 1, 0) -> 1 | L20: =IF( AND(L$3 >= Вводные!$F52, L$3 <= Вводные!$G52), 1, 0) -> 1 | M20: =IF( AND(M$3 >= Вводные!$F52, M$3 <= Вводные!$G52), 1, 0) -> 1 | N20: =IF( AND(N$3 >= Вводные!$F52, N$3 <= Вводные!$G52), 1, 0) -> 1 | O20: =IF( AND(O$3 >= Вводные!$F52, O$3 <= Вводные!$G52), 1, 0) -> 1 | P20: =IF( AND(P$3 >= Вводные!$F52, P$3 <= Вводные!$G52), 1, 0) -> 1 | Q20: =IF( AND(Q$3 >= Вводные!$F52, Q$3 <= Вводные!$G52), 1, 0) -> 1 | ... BJ20: =IF( AND(BJ$3 >= Вводные!$F52, BJ$3 <= Вводные!$G52), 1, 0) -> 1
D21: =Вводные!$D$46 -> Ежегодный доход 2 | E21: флаг | J21: =IF( AND(J$3 >= Вводные!$F53, J$3 <= Вводные!$G53), 1, 0) -> 1 | K21: =IF( AND(K$3 >= Вводные!$F53, K$3 <= Вводные!$G53), 1, 0) -> 1 | L21: =IF( AND(L$3 >= Вводные!$F53, L$3 <= Вводные!$G53), 1, 0) -> 1 | M21: =IF( AND(M$3 >= Вводные!$F53, M$3 <= Вводные!$G53), 1, 0) -> 1 | N21: =IF( AND(N$3 >= Вводные!$F53, N$3 <= Вводные!$G53), 1, 0) -> 1 | O21: =IF( AND(O$3 >= Вводные!$F53, O$3 <= Вводные!$G53), 1, 0) -> 1 | P21: =IF( AND(P$3 >= Вводные!$F53, P$3 <= Вводные!$G53), 1, 0) -> 1 | Q21: =IF( AND(Q$3 >= Вводные!$F53, Q$3 <= Вводные!$G53), 1, 0) -> 1 | ... BJ21: =IF( AND(BJ$3 >= Вводные!$F53, BJ$3 <= Вводные!$G53), 1, 0) -> 1
D22: =Вводные!$D$47 -> Ежегодный доход 3 | E22: флаг | J22: =IF( AND(J$3 >= Вводные!$F54, J$3 <= Вводные!$G54), 1, 0) -> 1 | K22: =IF( AND(K$3 >= Вводные!$F54, K$3 <= Вводные!$G54), 1, 0) -> 1 | L22: =IF( AND(L$3 >= Вводные!$F54, L$3 <= Вводные!$G54), 1, 0) -> 1 | M22: =IF( AND(M$3 >= Вводные!$F54, M$3 <= Вводные!$G54), 1, 0) -> 1 | N22: =IF( AND(N$3 >= Вводные!$F54, N$3 <= Вводные!$G54), 1, 0) -> 1 | O22: =IF( AND(O$3 >= Вводные!$F54, O$3 <= Вводные!$G54), 1, 0) -> 1 | P22: =IF( AND(P$3 >= Вводные!$F54, P$3 <= Вводные!$G54), 1, 0) -> 1 | Q22: =IF( AND(Q$3 >= Вводные!$F54, Q$3 <= Вводные!$G54), 1, 0) -> 1 | ... BJ22: =IF( AND(BJ$3 >= Вводные!$F54, BJ$3 <= Вводные!$G54), 1, 0) -> 1
D23: =Вводные!$D$48 -> Ежегодный доход 4 | E23: флаг | J23: =IF( AND(J$3 >= Вводные!$F55, J$3 <= Вводные!$G55), 1, 0) -> 1 | K23: =IF( AND(K$3 >= Вводные!$F55, K$3 <= Вводные!$G55), 1, 0) -> 1 | L23: =IF( AND(L$3 >= Вводные!$F55, L$3 <= Вводные!$G55), 1, 0) -> 1 | M23: =IF( AND(M$3 >= Вводные!$F55, M$3 <= Вводные!$G55), 1, 0) -> 1 | N23: =IF( AND(N$3 >= Вводные!$F55, N$3 <= Вводные!$G55), 1, 0) -> 1 | O23: =IF( AND(O$3 >= Вводные!$F55, O$3 <= Вводные!$G55), 1, 0) -> 1 | P23: =IF( AND(P$3 >= Вводные!$F55, P$3 <= Вводные!$G55), 1, 0) -> 1 | Q23: =IF( AND(Q$3 >= Вводные!$F55, Q$3 <= Вводные!$G55), 1, 0) -> 1 | ... BJ23: =IF( AND(BJ$3 >= Вводные!$F55, BJ$3 <= Вводные!$G55), 1, 0) -> 1
D24: =Вводные!$D$49 -> Ежегодный доход 5 | E24: флаг | J24: =IF( AND(J$3 >= Вводные!$F56, J$3 <= Вводные!$G56), 1, 0) -> 1 | K24: =IF( AND(K$3 >= Вводные!$F56, K$3 <= Вводные!$G56), 1, 0) -> 1 | L24: =IF( AND(L$3 >= Вводные!$F56, L$3 <= Вводные!$G56), 1, 0) -> 1 | M24: =IF( AND(M$3 >= Вводные!$F56, M$3 <= Вводные!$G56), 1, 0) -> 1 | N24: =IF( AND(N$3 >= Вводные!$F56, N$3 <= Вводные!$G56), 1, 0) -> 1 | O24: =IF( AND(O$3 >= Вводные!$F56, O$3 <= Вводные!$G56), 1, 0) -> 1 | P24: =IF( AND(P$3 >= Вводные!$F56, P$3 <= Вводные!$G56), 1, 0) -> 1 | Q24: =IF( AND(Q$3 >= Вводные!$F56, Q$3 <= Вводные!$G56), 1, 0) -> 1 | ... BJ24: =IF( AND(BJ$3 >= Вводные!$F56, BJ$3 <= Вводные!$G56), 1, 0) -> 1
B26: =MAX( $B$7:B9 ) + 1 -> 2 | D26: Доходы
D28: Всего доходы | E28: USD / год | I28: =SUM(I32,I48) -> 156000 | J28: =SUM(J32,J48) -> 156000 | K28: =SUM(K32,K48) -> 192360 | L28: =SUM(L32,L48) -> 198130.8 | M28: =SUM(M32,M48) -> 204074.72 | N28: =SUM(N32,N48) -> 210196.97 | O28: =SUM(O32,O48) -> 216502.87 | P28: =SUM(P32,P48) -> 222997.96 | ... BJ28: =SUM(BJ32,BJ48) -> 868586.81
C30: =MAX( $B$7:C27 ) + 0.1 -> 2.1 | D30: Ежемесячные доходы
D32: Ежемесячные доходы | E32: USD / год | I32: =SUM(I33:I37) -> 156000 | J32: =SUM(J33:J37) -> 156000 | K32: =SUM(K33:K37) -> 192360 | L32: =SUM(L33:L37) -> 198130.8 | M32: =SUM(M33:M37) -> 204074.72 | N32: =SUM(N33:N37) -> 210196.97 | O32: =SUM(O33:O37) -> 216502.87 | P32: =SUM(P33:P37) -> 222997.96 | ... BJ32: =SUM(BJ33:BJ37) -> 868586.81
D33: =Вводные!$D$22 -> Income 1 | E33: USD / год | I33: =Вводные!F22 * Вводные!$F$12 -> 120000 | J33: =$I33 * J40 * J13 -> 120000 | K33: =$I33 * K40 * K13 -> 180000 | L33: =$I33 * L40 * L13 -> 185400 | M33: =$I33 * M40 * M13 -> 190962 | N33: =$I33 * N40 * N13 -> 196690.86 | O33: =$I33 * O40 * O13 -> 202591.59 | P33: =$I33 * P40 * P13 -> 208669.33 | Q33: =$I33 * Q40 * Q13 -> 214929.41 | ... BJ33: =$I33 * BJ40 * BJ13 -> 812776.18
D34: =Вводные!$D$23 -> Income 2 | E34: USD / год | I34: =Вводные!F23 * Вводные!$F$12 -> 24000 | J34: =$I34 * J41 * J14 -> 24000 | K34: =$I34 * K41 * K14 -> 0 | L34: =$I34 * L41 * L14 -> 0 | M34: =$I34 * M41 * M14 -> 0 | N34: =$I34 * N41 * N14 -> 0 | O34: =$I34 * O41 * O14 -> 0 | P34: =$I34 * P41 * P14 -> 0 | Q34: =$I34 * Q41 * Q14 -> 0 | ... BJ34: =$I34 * BJ41 * BJ14 -> 0
D35: =Вводные!$D$24 -> Income 3 | E35: USD / год | I35: =Вводные!F24 * Вводные!$F$12 -> 12000 | J35: =$I35 * J42 * J15 -> 12000 | K35: =$I35 * K42 * K15 -> 12360 | L35: =$I35 * L42 * L15 -> 12730.8 | M35: =$I35 * M42 * M15 -> 13112.724 | N35: =$I35 * N42 * N15 -> 13506.106 | O35: =$I35 * O42 * O15 -> 13911.289 | P35: =$I35 * P42 * P15 -> 14328.628 | Q35: =$I35 * Q42 * Q15 -> 14758.486 | ... BJ35: =$I35 * BJ42 * BJ15 -> 55810.631
D36: =Вводные!$D$25 -> Ежемесячный доход 4 | E36: USD / год | I36: =Вводные!F25 * Вводные!$F$12 -> 0 | J36: =$I36 * J43 * J16 -> 0 | K36: =$I36 * K43 * K16 -> 0 | L36: =$I36 * L43 * L16 -> 0 | M36: =$I36 * M43 * M16 -> 0 | N36: =$I36 * N43 * N16 -> 0 | O36: =$I36 * O43 * O16 -> 0 | P36: =$I36 * P43 * P16 -> 0 | Q36: =$I36 * Q43 * Q16 -> 0 | ... BJ36: =$I36 * BJ43 * BJ16 -> 0
D37: =Вводные!$D$26 -> Ежемесячный доход 5 | E37: USD / год | I37: =Вводные!F26 * Вводные!$F$12 -> 0 | J37: =$I37 * J44 * J17 -> 0 | K37: =$I37 * K44 * K17 -> 0 | L37: =$I37 * L44 * L17 -> 0 | M37: =$I37 * M44 * M17 -> 0 | N37: =$I37 * N44 * N17 -> 0 | O37: =$I37 * O44 * O17 -> 0 | P37: =$I37 * P44 * P17 -> 0 | Q37: =$I37 * Q44 * Q17 -> 0 | ... BJ37: =$I37 * BJ44 * BJ17 -> 0
D39: Темп роста ежемесячных доходов
D40: =Вводные!$D$36 -> Темп роста Income 1 | E40: % | I40: 1 | J40: =I40 * (1+Вводные!J36) -> 1 | K40: =J40 * (1+Вводные!K36) -> 1.5 | L40: =K40 * (1+Вводные!L36) -> 1.545 | M40: =L40 * (1+Вводные!M36) -> 1.59135 | N40: =M40 * (1+Вводные!N36) -> 1.6390905 | O40: =N40 * (1+Вводные!O36) -> 1.6882632 | P40: =O40 * (1+Вводные!P36) -> 1.7389111 | Q40: =P40 * (1+Вводные!Q36) -> 1.7910784 | ... BJ40: =BI40 * (1+Вводные!BJ36) -> 6.7731348
D41: =Вводные!$D$37 -> Темп роста Income 2 | E41: % | I41: 1 | J41: =I41 * (1+Вводные!J37) -> 1 | K41: =J41 * (1+Вводные!K37) -> 1 | L41: =K41 * (1+Вводные!L37) -> 1 | M41: =L41 * (1+Вводные!M37) -> 1 | N41: =M41 * (1+Вводные!N37) -> 1 | O41: =N41 * (1+Вводные!O37) -> 1 | P41: =O41 * (1+Вводные!P37) -> 1 | Q41: =P41 * (1+Вводные!Q37) -> 1 | ... BJ41: =BI41 * (1+Вводные!BJ37) -> 1
D42: =Вводные!$D$38 -> Темп роста Income 3 | E42: % | I42: 1 | J42: =I42 * (1+Вводные!J38) -> 1 | K42: =J42 * (1+Вводные!K38) -> 1.03 | L42: =K42 * (1+Вводные!L38) -> 1.0609 | M42: =L42 * (1+Вводные!M38) -> 1.092727 | N42: =M42 * (1+Вводные!N38) -> 1.1255088 | O42: =N42 * (1+Вводные!O38) -> 1.1592741 | P42: =O42 * (1+Вводные!P38) -> 1.1940523 | Q42: =P42 * (1+Вводные!Q38) -> 1.2298739 | ... BJ42: =BI42 * (1+Вводные!BJ38) -> 4.6508859
D43: =Вводные!$D$39 -> Темп роста Ежемесячный доход 4 | E43: % | I43: 1 | J43: =I43 * (1+Вводные!J39) -> 1 | K43: =J43 * (1+Вводные!K39) -> 1.03 | L43: =K43 * (1+Вводные!L39) -> 1.0609 | M43: =L43 * (1+Вводные!M39) -> 1.092727 | N43: =M43 * (1+Вводные!N39) -> 1.1255088 | O43: =N43 * (1+Вводные!O39) -> 1.1592741 | P43: =O43 * (1+Вводные!P39) -> 1.1940523 | Q43: =P43 * (1+Вводные!Q39) -> 1.2298739 | ... BJ43: =BI43 * (1+Вводные!BJ39) -> 4.6508859
D44: =Вводные!$D$40 -> Темп роста Ежемесячный доход 5 | E44: % | I44: 1 | J44: =I44 * (1+Вводные!J40) -> 1 | K44: =J44 * (1+Вводные!K40) -> 1.03 | L44: =K44 * (1+Вводные!L40) -> 1.0609 | M44: =L44 * (1+Вводные!M40) -> 1.092727 | N44: =M44 * (1+Вводные!N40) -> 1.1255088 | O44: =N44 * (1+Вводные!O40) -> 1.1592741 | P44: =O44 * (1+Вводные!P40) -> 1.1940523 | Q44: =P44 * (1+Вводные!Q40) -> 1.2298739 | ... BJ44: =BI44 * (1+Вводные!BJ40) -> 4.6508859
C46: =MAX( $B$7:C45 ) + 0.1 -> 2.2 | D46: Ежегодные доходы
D48: Ежегодные доходы | E48: USD / год | I48: =SUM(I49:I53) -> 0 | J48: =SUM(J49:J53) -> 0 | K48: =SUM(K49:K53) -> 0 | L48: =SUM(L49:L53) -> 0 | M48: =SUM(M49:M53) -> 0 | N48: =SUM(N49:N53) -> 0 | O48: =SUM(O49:O53) -> 0 | P48: =SUM(P49:P53) -> 0 | ... BJ48: =SUM(BJ49:BJ53) -> 0
D49: =Вводные!$D$45 -> Ежегодный доход 1 | E49: USD / год | I49: =Вводные!F45 -> 0 | J49: =$I49 * J56 * J20 -> 0 | K49: =$I49 * K56 * K20 -> 0 | L49: =$I49 * L56 * L20 -> 0 | M49: =$I49 * M56 * M20 -> 0 | N49: =$I49 * N56 * N20 -> 0 | O49: =$I49 * O56 * O20 -> 0 | P49: =$I49 * P56 * P20 -> 0 | Q49: =$I49 * Q56 * Q20 -> 0 | ... BJ49: =$I49 * BJ56 * BJ20 -> 0
D50: =Вводные!$D$46 -> Ежегодный доход 2 | E50: USD / год | I50: =Вводные!F46 -> 0 | J50: =$I50 * J57 * J21 -> 0 | K50: =$I50 * K57 * K21 -> 0 | L50: =$I50 * L57 * L21 -> 0 | M50: =$I50 * M57 * M21 -> 0 | N50: =$I50 * N57 * N21 -> 0 | O50: =$I50 * O57 * O21 -> 0 | P50: =$I50 * P57 * P21 -> 0 | Q50: =$I50 * Q57 * Q21 -> 0 | ... BJ50: =$I50 * BJ57 * BJ21 -> 0
D51: =Вводные!$D$47 -> Ежегодный доход 3 | E51: USD / год | I51: =Вводные!F47 -> 0 | J51: =$I51 * J58 * J22 -> 0 | K51: =$I51 * K58 * K22 -> 0 | L51: =$I51 * L58 * L22 -> 0 | M51: =$I51 * M58 * M22 -> 0 | N51: =$I51 * N58 * N22 -> 0 | O51: =$I51 * O58 * O22 -> 0 | P51: =$I51 * P58 * P22 -> 0 | Q51: =$I51 * Q58 * Q22 -> 0 | ... BJ51: =$I51 * BJ58 * BJ22 -> 0
D52: =Вводные!$D$48 -> Ежегодный доход 4 | E52: USD / год | I52: =Вводные!F48 -> 0 | J52: =$I52 * J59 * J23 -> 0 | K52: =$I52 * K59 * K23 -> 0 | L52: =$I52 * L59 * L23 -> 0 | M52: =$I52 * M59 * M23 -> 0 | N52: =$I52 * N59 * N23 -> 0 | O52: =$I52 * O59 * O23 -> 0 | P52: =$I52 * P59 * P23 -> 0 | Q52: =$I52 * Q59 * Q23 -> 0 | ... BJ52: =$I52 * BJ59 * BJ23 -> 0
D53: =Вводные!$D$49 -> Ежегодный доход 5 | E53: USD / год | I53: =Вводные!F49 -> 0 | J53: =$I53 * J60 * J24 -> 0 | K53: =$I53 * K60 * K24 -> 0 | L53: =$I53 * L60 * L24 -> 0 | M53: =$I53 * M60 * M24 -> 0 | N53: =$I53 * N60 * N24 -> 0 | O53: =$I53 * O60 * O24 -> 0 | P53: =$I53 * P60 * P24 -> 0 | Q53: =$I53 * Q60 * Q24 -> 0 | ... BJ53: =$I53 * BJ60 * BJ24 -> 0
D55: Темп роста ежегодных доходов
D56: =Вводные!$D$59 -> Темп роста Ежегодный доход 1 | E56: % | I56: 1 | J56: =I56 * (1+Вводные!J59) -> 1 | K56: =J56 * (1+Вводные!K59) -> 1.03 | L56: =K56 * (1+Вводные!L59) -> 1.0609 | M56: =L56 * (1+Вводные!M59) -> 1.092727 | N56: =M56 * (1+Вводные!N59) -> 1.1255088 | O56: =N56 * (1+Вводные!O59) -> 1.1592741 | P56: =O56 * (1+Вводные!P59) -> 1.1940523 | Q56: =P56 * (1+Вводные!Q59) -> 1.2298739 | ... BJ56: =BI56 * (1+Вводные!BJ59) -> 4.6508859
D57: =Вводные!$D$60 -> Темп роста Ежегодный доход 2 | E57: % | I57: 1 | J57: =I57 * (1+Вводные!J60) -> 1 | K57: =J57 * (1+Вводные!K60) -> 1.03 | L57: =K57 * (1+Вводные!L60) -> 1.0609 | M57: =L57 * (1+Вводные!M60) -> 1.092727 | N57: =M57 * (1+Вводные!N60) -> 1.1255088 | O57: =N57 * (1+Вводные!O60) -> 1.1592741 | P57: =O57 * (1+Вводные!P60) -> 1.1940523 | Q57: =P57 * (1+Вводные!Q60) -> 1.2298739 | ... BJ57: =BI57 * (1+Вводные!BJ60) -> 4.6508859
D58: =Вводные!$D$61 -> Темп роста Ежегодный доход 3 | E58: % | I58: 1 | J58: =I58 * (1+Вводные!J61) -> 1 | K58: =J58 * (1+Вводные!K61) -> 1.03 | L58: =K58 * (1+Вводные!L61) -> 1.0609 | M58: =L58 * (1+Вводные!M61) -> 1.092727 | N58: =M58 * (1+Вводные!N61) -> 1.1255088 | O58: =N58 * (1+Вводные!O61) -> 1.1592741 | P58: =O58 * (1+Вводные!P61) -> 1.1940523 | Q58: =P58 * (1+Вводные!Q61) -> 1.2298739 | ... BJ58: =BI58 * (1+Вводные!BJ61) -> 4.6508859
D59: =Вводные!$D$62 -> Темп роста Ежегодный доход 4 | E59: % | I59: 1 | J59: =I59 * (1+Вводные!J62) -> 1 | K59: =J59 * (1+Вводные!K62) -> 1.03 | L59: =K59 * (1+Вводные!L62) -> 1.0609 | M59: =L59 * (1+Вводные!M62) -> 1.092727 | N59: =M59 * (1+Вводные!N62) -> 1.1255088 | O59: =N59 * (1+Вводные!O62) -> 1.1592741 | P59: =O59 * (1+Вводные!P62) -> 1.1940523 | Q59: =P59 * (1+Вводные!Q62) -> 1.2298739 | ... BJ59: =BI59 * (1+Вводные!BJ62) -> 4.6508859
D60: =Вводные!$D$63 -> Темп роста Ежегодный доход 5 | E60: % | I60: 1 | J60: =I60 * (1+Вводные!J63) -> 1 | K60: =J60 * (1+Вводные!K63) -> 1.03 | L60: =K60 * (1+Вводные!L63) -> 1.0609 | M60: =L60 * (1+Вводные!M63) -> 1.092727 | N60: =M60 * (1+Вводные!N63) -> 1.1255088 | O60: =N60 * (1+Вводные!O63) -> 1.1592741 | P60: =O60 * (1+Вводные!P63) -> 1.1940523 | Q60: =P60 * (1+Вводные!Q63) -> 1.2298739 | ... BJ60: =BI60 * (1+Вводные!BJ63) -> 4.6508859

Sheet Расходы
D3: =Вводные!D3 -> Год | J3: =Вводные!J3 -> 2024 | K3: =Вводные!K3 -> 2025 | L3: =Вводные!L3 -> 2026 | M3: =Вводные!M3 -> 2027 | N3: =Вводные!N3 -> 2028 | O3: =Вводные!O3 -> 2029 | P3: =Вводные!P3 -> 2030 | Q3: =Вводные!Q3 -> 2031 | ... BJ3: =Вводные!BJ3 -> 2076
D4: =Вводные!D4 -> Возраст | J4: =Вводные!J4 -> 31 | K4: =Вводные!K4 -> 32 | L4: =Вводные!L4 -> 33 | M4: =Вводные!M4 -> 34 | N4: =Вводные!N4 -> 35 | O4: =Вводные!O4 -> 36 | P4: =Вводные!P4 -> 37 | Q4: =Вводные!Q4 -> 38 | ... BJ4: =Вводные!BJ4 -> 83
D5: =Вводные!D5 -> № периода | J5: =Вводные!J5 -> 1 | K5: =Вводные!K5 -> 2 | L5: =Вводные!L5 -> 3 | M5: =Вводные!M5 -> 4 | N5: =Вводные!N5 -> 5 | O5: =Вводные!O5 -> 6 | P5: =Вводные!P5 -> 7 | Q5: =Вводные!Q5 -> 8 | ... BJ5: =Вводные!BJ5 -> 53
B8: =MAX( $B5:B$7 ) + 1 -> 1 | D8: Флаги
C10: =MAX( $B$7:C9 ) + 0.1 -> 1.1 | D10: Флаги понесения расходов
D12: Ежемесячные расходы
D13: =Вводные!$D$70 -> Еда | E13: флаг | J13: =IF( AND(J$3 >= Вводные!$F142, J$3 <= Вводные!$G142), 1, 0) -> 1 | K13: =IF( AND(K$3 >= Вводные!$F142, K$3 <= Вводные!$G142), 1, 0) -> 1 | L13: =IF( AND(L$3 >= Вводные!$F142, L$3 <= Вводные!$G142), 1, 0) -> 1 | M13: =IF( AND(M$3 >= Вводные!$F142, M$3 <= Вводные!$G142), 1, 0) -> 1 | N13: =IF( AND(N$3 >= Вводные!$F142, N$3 <= Вводные!$G142), 1, 0) -> 1 | O13: =IF( AND(O$3 >= Вводные!$F142, O$3 <= Вводные!$G142), 1, 0) -> 1 | P13: =IF( AND(P$3 >= Вводные!$F142, P$3 <= Вводные!$G142), 1, 0) -> 1 | Q13: =IF( AND(Q$3 >= Вводные!$F142, Q$3 <= Вводные!$G142), 1, 0) -> 1 | ... BJ13: =IF( AND(BJ$3 >= Вводные!$F142, BJ$3 <= Вводные!$G142), 1, 0) -> 1
D14: =Вводные!$D$71 -> Садик | E14: флаг | J14: =IF( AND(J$3 >= Вводные!$F143, J$3 <= Вводные!$G143), 1, 0) -> 1 | K14: =IF( AND(K$3 >= Вводные!$F143, K$3 <= Вводные!$G143), 1, 0) -> 1 | L14: =IF( AND(L$3 >= Вводные!$F143, L$3 <= Вводные!$G143), 1, 0) -> 1 | M14: =IF( AND(M$3 >= Вводные!$F143, M$3 <= Вводные!$G143), 1, 0) -> 1 | N14: =IF( AND(N$3 >= Вводные!$F143, N$3 <= Вводные!$G143), 1, 0) -> 1 | O14: =IF( AND(O$3 >= Вводные!$F143, O$3 <= Вводные!$G143), 1, 0) -> 1 | P14: =IF( AND(P$3 >= Вводные!$F143, P$3 <= Вводные!$G143), 1, 0) -> 1 | Q14: =IF( AND(Q$3 >= Вводные!$F143, Q$3 <= Вводные!$G143), 1, 0) -> 1 | ... BJ14: =IF( AND(BJ$3 >= Вводные!$F143, BJ$3 <= Вводные!$G143), 1, 0) -> 1
D15: =Вводные!$D$72 -> Няня | E15: флаг | J15: =IF( AND(J$3 >= Вводные!$F144, J$3 <= Вводные!$G144), 1, 0) -> 1 | K15: =IF( AND(K$3 >= Вводные!$F144, K$3 <= Вводные!$G144), 1, 0) -> 1 | L15: =IF( AND(L$3 >= Вводные!$F144, L$3 <= Вводные!$G144), 1, 0) -> 1 | M15: =IF( AND(M$3 >= Вводные!$F144, M$3 <= Вводные!$G144), 1, 0) -> 1 | N15: =IF( AND(N$3 >= Вводные!$F144, N$3 <= Вводные!$G144), 1, 0) -> 1 | O15: =IF( AND(O$3 >= Вводные!$F144, O$3 <= Вводные!$G144), 1, 0) -> 1 | P15: =IF( AND(P$3 >= Вводные!$F144, P$3 <= Вводные!$G144), 1, 0) -> 1 | Q15: =IF( AND(Q$3 >= Вводные!$F144, Q$3 <= Вводные!$G144), 1, 0) -> 1 | ... BJ15: =IF( AND(BJ$3 >= Вводные!$F144, BJ$3 <= Вводные!$G144), 1, 0) -> 1
D16: =Вводные!$D$73 -> Ипотека | E16: флаг | J16: =IF( AND(J$3 >= Вводные!$F145, J$3 <= Вводные!$G145), 1, 0) -> 1 | K16: =IF( AND(K$3 >= Вводные!$F145, K$3 <= Вводные!$G145), 1, 0) -> 1 | L16: =IF( AND(L$3 >= Вводные!$F145, L$3 <= Вводные!$G145), 1, 0) -> 1 | M16: =IF( AND(M$3 >= Вводные!$F145, M$3 <= Вводные!$G145), 1, 0) -> 1 | N16: =IF( AND(N$3 >= Вводные!$F145, N$3 <= Вводные!$G145), 1, 0) -> 1 | O16: =IF( AND(O$3 >= Вводные!$F145, O$3 <= Вводные!$G145), 1, 0) -> 1 | P16: =IF( AND(P$3 >= Вводные!$F145, P$3 <= Вводные!$G145), 1, 0) -> 1 | Q16: =IF( AND(Q$3 >= Вводные!$F145, Q$3 <= Вводные!$G145), 1, 0) -> 1 | ... BJ16: =IF( AND(BJ$3 >= Вводные!$F145, BJ$3 <= Вводные!$G145), 1, 0) -> 0
D17: =Вводные!$D$74 -> Аренда квартиры + коммуналка | E17: флаг | J17: =IF( AND(J$3 >= Вводные!$F146, J$3 <= Вводные!$G146), 1, 0) -> 1 | K17: =IF( AND(K$3 >= Вводные!$F146, K$3 <= Вводные!$G146), 1, 0) -> 1 | L17: =IF( AND(L$3 >= Вводные!$F146, L$3 <= Вводные!$G146), 1, 0) -> 1 | M17: =IF( AND(M$3 >= Вводные!$F146, M$3 <= Вводные!$G146), 1, 0) -> 1 | N17: =IF( AND(N$3 >= Вводные!$F146, N$3 <= Вводные!$G146), 1, 0) -> 1 | O17: =IF( AND(O$3 >= Вводные!$F146, O$3 <= Вводные!$G146), 1, 0) -> 1 | P17: =IF( AND(P$3 >= Вводные!$F146, P$3 <= Вводные!$G146), 1, 0) -> 1 | Q17: =IF( AND(Q$3 >= Вводные!$F146, Q$3 <= Вводные!$G146), 1, 0) -> 1 | ... BJ17: =IF( AND(BJ$3 >= Вводные!$F146, BJ$3 <= Вводные!$G146), 1, 0) -> 1
D18: =Вводные!$D$75 -> Связь + интернет | E18: флаг | J18: =IF( AND(J$3 >= Вводные!$F147, J$3 <= Вводные!$G147), 1, 0) -> 1 | K18: =IF( AND(K$3 >= Вводные!$F147, K$3 <= Вводные!$G147), 1, 0) -> 1 | L18: =IF( AND(L$3 >= Вводные!$F147, L$3 <= Вводные!$G147), 1, 0) -> 1 | M18: =IF( AND(M$3 >= Вводные!$F147, M$3 <= Вводные!$G147), 1, 0) -> 1 | N18: =IF( AND(N$3 >= Вводные!$F147, N$3 <= Вводные!$G147), 1, 0) -> 1 | O18: =IF( AND(O$3 >= Вводные!$F147, O$3 <= Вводные!$G147), 1, 0) -> 1 | P18: =IF( AND(P$3 >= Вводные!$F147, P$3 <= Вводные!$G147), 1, 0) -> 1 | Q18: =IF( AND(Q$3 >= Вводные!$F147, Q$3 <= Вводные!$G147), 1, 0) -> 1 | ... BJ18: =IF( AND(BJ$3 >= Вводные!$F147, BJ$3 <= Вводные!$G147), 1, 0) -> 1
D19: =Вводные!$D$76 -> Командировки | E19: флаг | J19: =IF( AND(J$3 >= Вводные!$F148, J$3 <= Вводные!$G148), 1, 0) -> 1 | K19: =IF( AND(K$3 >= Вводные!$F148, K$3 <= Вводные!$G148), 1, 0) -> 1 | L19: =IF( AND(L$3 >= Вводные!$F148, L$3 <= Вводные!$G148), 1, 0) -> 1 | M19: =IF( AND(M$3 >= Вводные!$F148, M$3 <= Вводные!$G148), 1, 0) -> 1 | N19: =IF( AND(N$3 >= Вводные!$F148, N$3 <= Вводные!$G148), 1, 0) -> 1 | O19: =IF( AND(O$3 >= Вводные!$F148, O$3 <= Вводные!$G148), 1, 0) -> 1 | P19: =IF( AND(P$3 >= Вводные!$F148, P$3 <= Вводные!$G148), 1, 0) -> 1 | Q19: =IF( AND(Q$3 >= Вводные!$F148, Q$3 <= Вводные!$G148), 1, 0) -> 1 | ... BJ19: =IF( AND(BJ$3 >= Вводные!$F148, BJ$3 <= Вводные!$G148), 1, 0) -> 1
D20: =Вводные!$D$77 -> Прочее | E20: флаг | J20: =IF( AND(J$3 >= Вводные!$F149, J$3 <= Вводные!$G149), 1, 0) -> 1 | K20: =IF( AND(K$3 >= Вводные!$F149, K$3 <= Вводные!$G149), 1, 0) -> 1 | L20: =IF( AND(L$3 >= Вводные!$F149, L$3 <= Вводные!$G149), 1, 0) -> 1 | M20: =IF( AND(M$3 >= Вводные!$F149, M$3 <= Вводные!$G149), 1, 0) -> 1 | N20: =IF( AND(N$3 >= Вводные!$F149, N$3 <= Вводные!$G149), 1, 0) -> 1 | O20: =IF( AND(O$3 >= Вводные!$F149, O$3 <= Вводные!$G149), 1, 0) -> 1 | P20: =IF( AND(P$3 >= Вводные!$F149, P$3 <= Вводные!$G149), 1, 0) -> 1 | Q20: =IF( AND(Q$3 >= Вводные!$F149, Q$3 <= Вводные!$G149), 1, 0) -> 1 | ... BJ20: =IF( AND(BJ$3 >= Вводные!$F149, BJ$3 <= Вводные!$G149), 1, 0) -> 1
D21: =Вводные!$D$78 -> Ежемесячный расход 9 | E21: флаг | J21: =IF( AND(J$3 >= Вводные!$F150, J$3 <= Вводные!$G150), 1, 0) -> 1 | K21: =IF( AND(K$3 >= Вводные!$F150, K$3 <= Вводные!$G150), 1, 0) -> 1 | L21: =IF( AND(L$3 >= Вводные!$F150, L$3 <= Вводные!$G150), 1, 0) -> 1 | M21: =IF( AND(M$3 >= Вводные!$F150, M$3 <= Вводные!$G150), 1, 0) -> 1 | N21: =IF( AND(N$3 >= Вводные!$F150, N$3 <= Вводные!$G150), 1, 0) -> 1 | O21: =IF( AND(O$3 >= Вводные!$F150, O$3 <= Вводные!$G150), 1, 0) -> 1 | P21: =IF( AND(P$3 >= Вводные!$F150, P$3 <= Вводные!$G150), 1, 0) -> 1 | Q21: =IF( AND(Q$3 >= Вводные!$F150, Q$3 <= Вводные!$G150), 1, 0) -> 1 | ... BJ21: =IF( AND(BJ$3 >= Вводные!$F150, BJ$3 <= Вводные!$G150), 1, 0) -> 1
D22: =Вводные!$D$79 -> Ежемесячный расход 10 | E22: флаг | J22: =IF( AND(J$3 >= Вводные!$F151, J$3 <= Вводные!$G151), 1, 0) -> 1 | K22: =IF( AND(K$3 >= Вводные!$F151, K$3 <= Вводные!$G151), 1, 0) -> 1 | L22: =IF( AND(L$3 >= Вводные!$F151, L$3 <= Вводные!$G151), 1, 0) -> 1 | M22: =IF( AND(M$3 >= Вводные!$F151, M$3 <= Вводные!$G151), 1, 0) -> 1 | N22: =IF( AND(N$3 >= Вводные!$F151, N$3 <= Вводные!$G151), 1, 0) -> 1 | O22: =IF( AND(O$3 >= Вводные!$F151, O$3 <= Вводные!$G151), 1, 0) -> 1 | P22: =IF( AND(P$3 >= Вводные!$F151, P$3 <= Вводные!$G151), 1, 0) -> 1 | Q22: =IF( AND(Q$3 >= Вводные!$F151, Q$3 <= Вводные!$G151), 1, 0) -> 1 | ... BJ22: =IF( AND(BJ$3 >= Вводные!$F151, BJ$3 <= Вводные!$G151), 1, 0) -> 1
D23: =Вводные!$D$80 -> Ежемесячный расход 11 | E23: флаг | J23: =IF( AND(J$3 >= Вводные!$F152, J$3 <= Вводные!$G152), 1, 0) -> 1 | K23: =IF( AND(K$3 >= Вводные!$F152, K$3 <= Вводные!$G152), 1, 0) -> 1 | L23: =IF( AND(L$3 >= Вводные!$F152, L$3 <= Вводные!$G152), 1, 0) -> 1 | M23: =IF( AND(M$3 >= Вводные!$F152, M$3 <= Вводные!$G152), 1, 0) -> 1 | N23: =IF( AND(N$3 >= Вводные!$F152, N$3 <= Вводные!$G152), 1, 0) -> 1 | O23: =IF( AND(O$3 >= Вводные!$F152, O$3 <= Вводные!$G152), 1, 0) -> 1 | P23: =IF( AND(P$3 >= Вводные!$F152, P$3 <= Вводные!$G152), 1, 0) -> 1 | Q23: =IF( AND(Q$3 >= Вводные!$F152, Q$3 <= Вводные!$G152), 1, 0) -> 1 | ... BJ23: =IF( AND(BJ$3 >= Вводные!$F152, BJ$3 <= Вводные!$G152), 1, 0) -> 1
D24: =Вводные!$D$81 -> Ежемесячный расход 12 | E24: флаг | J24: =IF( AND(J$3 >= Вводные!$F153, J$3 <= Вводные!$G153), 1, 0) -> 1 | K24: =IF( AND(K$3 >= Вводные!$F153, K$3 <= Вводные!$G153), 1, 0) -> 1 | L24: =IF( AND(L$3 >= Вводные!$F153, L$3 <= Вводные!$G153), 1, 0) -> 1 | M24: =IF( AND(M$3 >= Вводные!$F153, M$3 <= Вводные!$G153), 1, 0) -> 1 | N24: =IF( AND(N$3 >= Вводные!$F153, N$3 <= Вводные!$G153), 1, 0) -> 1 | O24: =IF( AND(O$3 >= Вводные!$F153, O$3 <= Вводные!$G153), 1, 0) -> 1 | P24: =IF( AND(P$3 >= Вводные!$F153, P$3 <= Вводные!$G153), 1, 0) -> 1 | Q24: =IF( AND(Q$3 >= Вводные!$F153, Q$3 <= Вводные!$G153), 1, 0) -> 1 | ... BJ24: =IF( AND(BJ$3 >= Вводные!$F153, BJ$3 <= Вводные!$G153), 1, 0) -> 1
D25: =Вводные!$D$82 -> Ежемесячный расход 13 | E25: флаг | J25: =IF( AND(J$3 >= Вводные!$F154, J$3 <= Вводные!$G154), 1, 0) -> 1 | K25: =IF( AND(K$3 >= Вводные!$F154, K$3 <= Вводные!$G154), 1, 0) -> 1 | L25: =IF( AND(L$3 >= Вводные!$F154, L$3 <= Вводные!$G154), 1, 0) -> 1 | M25: =IF( AND(M$3 >= Вводные!$F154, M$3 <= Вводные!$G154), 1, 0) -> 1 | N25: =IF( AND(N$3 >= Вводные!$F154, N$3 <= Вводные!$G154), 1, 0) -> 1 | O25: =IF( AND(O$3 >= Вводные!$F154, O$3 <= Вводные!$G154), 1, 0) -> 1 | P25: =IF( AND(P$3 >= Вводные!$F154, P$3 <= Вводные!$G154), 1, 0) -> 1 | Q25: =IF( AND(Q$3 >= Вводные!$F154, Q$3 <= Вводные!$G154), 1, 0) -> 1 | ... BJ25: =IF( AND(BJ$3 >= Вводные!$F154, BJ$3 <= Вводные!$G154), 1, 0) -> 1
D26: =Вводные!$D$83 -> Ежемесячный расход 14 | E26: флаг | J26: =IF( AND(J$3 >= Вводные!$F155, J$3 <= Вводные!$G155), 1, 0) -> 1 | K26: =IF( AND(K$3 >= Вводные!$F155, K$3 <= Вводные!$G155), 1, 0) -> 1 | L26: =IF( AND(L$3 >= Вводные!$F155, L$3 <= Вводные!$G155), 1, 0) -> 1 | M26: =IF( AND(M$3 >= Вводные!$F155, M$3 <= Вводные!$G155), 1, 0) -> 1 | N26: =IF( AND(N$3 >= Вводные!$F155, N$3 <= Вводные!$G155), 1, 0) -> 1 | O26: =IF( AND(O$3 >= Вводные!$F155, O$3 <= Вводные!$G155), 1, 0) -> 1 | P26: =IF( AND(P$3 >= Вводные!$F155, P$3 <= Вводные!$G155), 1, 0) -> 1 | Q26: =IF( AND(Q$3 >= Вводные!$F155, Q$3 <= Вводные!$G155), 1, 0) -> 1 | ... BJ26: =IF( AND(BJ$3 >= Вводные!$F155, BJ$3 <= Вводные!$G155), 1, 0) -> 1
D27: =Вводные!$D$84 -> Ежемесячный расход 15 | E27: флаг | J27: =IF( AND(J$3 >= Вводные!$F156, J$3 <= Вводные!$G156), 1, 0) -> 1 | K27: =IF( AND(K$3 >= Вводные!$F156, K$3 <= Вводные!$G156), 1, 0) -> 1 | L27: =IF( AND(L$3 >= Вводные!$F156, L$3 <= Вводные!$G156), 1, 0) -> 1 | M27: =IF( AND(M$3 >= Вводные!$F156, M$3 <= Вводные!$G156), 1, 0) -> 1 | N27: =IF( AND(N$3 >= Вводные!$F156, N$3 <= Вводные!$G156), 1, 0) -> 1 | O27: =IF( AND(O$3 >= Вводные!$F156, O$3 <= Вводные!$G156), 1, 0) -> 1 | P27: =IF( AND(P$3 >= Вводные!$F156, P$3 <= Вводные!$G156), 1, 0) -> 1 | Q27: =IF( AND(Q$3 >= Вводные!$F156, Q$3 <= Вводные!$G156), 1, 0) -> 1 | ... BJ27: =IF( AND(BJ$3 >= Вводные!$F156, BJ$3 <= Вводные!$G156), 1, 0) -> 1
D28: =Вводные!$D$85 -> Ежемесячный расход 16 | E28: флаг | J28: =IF( AND(J$3 >= Вводные!$F157, J$3 <= Вводные!$G157), 1, 0) -> 1 | K28: =IF( AND(K$3 >= Вводные!$F157, K$3 <= Вводные!$G157), 1, 0) -> 1 | L28: =IF( AND(L$3 >= Вводные!$F157, L$3 <= Вводные!$G157), 1, 0) -> 1 | M28: =IF( AND(M$3 >= Вводные!$F157, M$3 <= Вводные!$G157), 1, 0) -> 1 | N28: =IF( AND(N$3 >= Вводные!$F157, N$3 <= Вводные!$G157), 1, 0) -> 1 | O28: =IF( AND(O$3 >= Вводные!$F157, O$3 <= Вводные!$G157), 1, 0) -> 1 | P28: =IF( AND(P$3 >= Вводные!$F157, P$3 <= Вводные!$G157), 1, 0) -> 1 | Q28: =IF( AND(Q$3 >= Вводные!$F157, Q$3 <= Вводные!$G157), 1, 0) -> 1 | ... BJ28: =IF( AND(BJ$3 >= Вводные!$F157, BJ$3 <= Вводные!$G157), 1, 0) -> 1
D29: =Вводные!$D$86 -> Ежемесячный расход 17 | E29: флаг | J29: =IF( AND(J$3 >= Вводные!$F158, J$3 <= Вводные!$G158), 1, 0) -> 1 | K29: =IF( AND(K$3 >= Вводные!$F158, K$3 <= Вводные!$G158), 1, 0) -> 1 | L29: =IF( AND(L$3 >= Вводные!$F158, L$3 <= Вводные!$G158), 1, 0) -> 1 | M29: =IF( AND(M$3 >= Вводные!$F158, M$3 <= Вводные!$G158), 1, 0) -> 1 | N29: =IF( AND(N$3 >= Вводные!$F158, N$3 <= Вводные!$G158), 1, 0) -> 1 | O29: =IF( AND(O$3 >= Вводные!$F158, O$3 <= Вводные!$G158), 1, 0) -> 1 | P29: =IF( AND(P$3 >= Вводные!$F158, P$3 <= Вводные!$G158), 1, 0) -> 1 | Q29: =IF( AND(Q$3 >= Вводные!$F158, Q$3 <= Вводные!$G158), 1, 0) -> 1 | ... BJ29: =IF( AND(BJ$3 >= Вводные!$F158, BJ$3 <= Вводные!$G158), 1, 0) -> 1
D30: =Вводные!$D$87 -> Ежемесячный расход 18 | E30: флаг | J30: =IF( AND(J$3 >= Вводные!$F159, J$3 <= Вводные!$G159), 1, 0) -> 1 | K30: =IF( AND(K$3 >= Вводные!$F159, K$3 <= Вводные!$G159), 1, 0) -> 1 | L30: =IF( AND(L$3 >= Вводные!$F159, L$3 <= Вводные!$G159), 1, 0) -> 1 | M30: =IF( AND(M$3 >= Вводные!$F159, M$3 <= Вводные!$G159), 1, 0) -> 1 | N30: =IF( AND(N$3 >= Вводные!$F159, N$3 <= Вводные!$G159), 1, 0) -> 1 | O30: =IF( AND(O$3 >= Вводные!$F159, O$3 <= Вводные!$G159), 1, 0) -> 1 | P30: =IF( AND(P$3 >= Вводные!$F159, P$3 <= Вводные!$G159), 1, 0) -> 1 | Q30: =IF( AND(Q$3 >= Вводные!$F159, Q$3 <= Вводные!$G159), 1, 0) -> 1 | ... BJ30: =IF( AND(BJ$3 >= Вводные!$F159, BJ$3 <= Вводные!$G159), 1, 0) -> 1
D31: =Вводные!$D$88 -> Ежемесячный расход 19 | E31: флаг | J31: =IF( AND(J$3 >= Вводные!$F160, J$3 <= Вводные!$G160), 1, 0) -> 1 | K31: =IF( AND(K$3 >= Вводные!$F160, K$3 <= Вводные!$G160), 1, 0) -> 1 | L31: =IF( AND(L$3 >= Вводные!$F160, L$3 <= Вводные!$G160), 1, 0) -> 1 | M31: =IF( AND(M$3 >= Вводные!$F160, M$3 <= Вводные!$G160), 1, 0) -> 1 | N31: =IF( AND(N$3 >= Вводные!$F160, N$3 <= Вводные!$G160), 1, 0) -> 1 | O31: =IF( AND(O$3 >= Вводные!$F160, O$3 <= Вводные!$G160), 1, 0) -> 1 | P31: =IF( AND(P$3 >= Вводные!$F160, P$3 <= Вводные!$G160), 1, 0) -> 1 | Q31: =IF( AND(Q$3 >= Вводные!$F160, Q$3 <= Вводные!$G160), 1, 0) -> 1 | ... BJ31: =IF( AND(BJ$3 >= Вводные!$F160, BJ$3 <= Вводные!$G160), 1, 0) -> 1
D32: =Вводные!$D$89 -> Ежемесячный расход 20 | E32: флаг | J32: =IF( AND(J$3 >= Вводные!$F161, J$3 <= Вводные!$G161), 1, 0) -> 1 | K32: =IF( AND(K$3 >= Вводные!$F161, K$3 <= Вводные!$G161), 1, 0) -> 1 | L32: =IF( AND(L$3 >= Вводные!$F161, L$3 <= Вводные!$G161), 1, 0) -> 1 | M32: =IF( AND(M$3 >= Вводные!$F161, M$3 <= Вводные!$G161), 1, 0) -> 1 | N32: =IF( AND(N$3 >= Вводные!$F161, N$3 <= Вводные!$G161), 1, 0) -> 1 | O32: =IF( AND(O$3 >= Вводные!$F161, O$3 <= Вводные!$G161), 1, 0) -> 1 | P32: =IF( AND(P$3 >= Вводные!$F161, P$3 <= Вводные!$G161), 1, 0) -> 1 | Q32: =IF( AND(Q$3 >= Вводные!$F161, Q$3 <= Вводные!$G161), 1, 0) -> 1 | ... BJ32: =IF( AND(BJ$3 >= Вводные!$F161, BJ$3 <= Вводные!$G161), 1, 0) -> 1
D34: Ежегодные расходы
D35: =Вводные!$D$116 -> Страховка | E35: флаг | J35: =IF( AND(J$3 >= Вводные!$F164, J$3 <= Вводные!$G164), 1, 0) -> 1 | K35: =IF( AND(K$3 >= Вводные!$F164, K$3 <= Вводные!$G164), 1, 0) -> 1 | L35: =IF( AND(L$3 >= Вводные!$F164, L$3 <= Вводные!$G164), 1, 0) -> 1 | M35: =IF( AND(M$3 >= Вводные!$F164, M$3 <= Вводные!$G164), 1, 0) -> 1 | N35: =IF( AND(N$3 >= Вводные!$F164, N$3 <= Вводные!$G164), 1, 0) -> 1 | O35: =IF( AND(O$3 >= Вводные!$F164, O$3 <= Вводные!$G164), 1, 0) -> 1 | P35: =IF( AND(P$3 >= Вводные!$F164, P$3 <= Вводные!$G164), 1, 0) -> 1 | Q35: =IF( AND(Q$3 >= Вводные!$F164, Q$3 <= Вводные!$G164), 1, 0) -> 1 | ... BJ35: =IF( AND(BJ$3 >= Вводные!$F164, BJ$3 <= Вводные!$G164), 1, 0) -> 1
D36: =Вводные!$D$117 -> Детский сад / школа | E36: флаг | J36: =IF( AND(J$3 >= Вводные!$F165, J$3 <= Вводные!$G165), 1, 0) -> 1 | K36: =IF( AND(K$3 >= Вводные!$F165, K$3 <= Вводные!$G165), 1, 0) -> 1 | L36: =IF( AND(L$3 >= Вводные!$F165, L$3 <= Вводные!$G165), 1, 0) -> 1 | M36: =IF( AND(M$3 >= Вводные!$F165, M$3 <= Вводные!$G165), 1, 0) -> 1 | N36: =IF( AND(N$3 >= Вводные!$F165, N$3 <= Вводные!$G165), 1, 0) -> 1 | O36: =IF( AND(O$3 >= Вводные!$F165, O$3 <= Вводные!$G165), 1, 0) -> 1 | P36: =IF( AND(P$3 >= Вводные!$F165, P$3 <= Вводные!$G165), 1, 0) -> 1 | Q36: =IF( AND(Q$3 >= Вводные!$F165, Q$3 <= Вводные!$G165), 1, 0) -> 1 | ... BJ36: =IF( AND(BJ$3 >= Вводные!$F165, BJ$3 <= Вводные!$G165), 1, 0) -> 0
D37: =Вводные!$D$118 -> Страховка по ипотеке | E37: флаг | J37: =IF( AND(J$3 >= Вводные!$F166, J$3 <= Вводные!$G166), 1, 0) -> 1 | K37: =IF( AND(K$3 >= Вводные!$F166, K$3 <= Вводные!$G166), 1, 0) -> 1 | L37: =IF( AND(L$3 >= Вводные!$F166, L$3 <= Вводные!$G166), 1, 0) -> 1 | M37: =IF( AND(M$3 >= Вводные!$F166, M$3 <= Вводные!$G166), 1, 0) -> 1 | N37: =IF( AND(N$3 >= Вводные!$F166, N$3 <= Вводные!$G166), 1, 0) -> 1 | O37: =IF( AND(O$3 >= Вводные!$F166, O$3 <= Вводные!$G166), 1, 0) -> 1 | P37: =IF( AND(P$3 >= Вводные!$F166, P$3 <= Вводные!$G166), 1, 0) -> 1 | Q37: =IF( AND(Q$3 >= Вводные!$F166, Q$3 <= Вводные!$G166), 1, 0) -> 1 | ... BJ37: =IF( AND(BJ$3 >= Вводные!$F166, BJ$3 <= Вводные!$G166), 1, 0) -> 0
D38: =Вводные!$D$119 -> Отпуск | E38: флаг | J38: =IF( AND(J$3 >= Вводные!$F167, J$3 <= Вводные!$G167), 1, 0) -> 1 | K38: =IF( AND(K$3 >= Вводные!$F167, K$3 <= Вводные!$G167), 1, 0) -> 1 | L38: =IF( AND(L$3 >= Вводные!$F167, L$3 <= Вводные!$G167), 1, 0) -> 1 | M38: =IF( AND(M$3 >= Вводные!$F167, M$3 <= Вводные!$G167), 1, 0) -> 1 | N38: =IF( AND(N$3 >= Вводные!$F167, N$3 <= Вводные!$G167), 1, 0) -> 1 | O38: =IF( AND(O$3 >= Вводные!$F167, O$3 <= Вводные!$G167), 1, 0) -> 1 | P38: =IF( AND(P$3 >= Вводные!$F167, P$3 <= Вводные!$G167), 1, 0) -> 1 | Q38: =IF( AND(Q$3 >= Вводные!$F167, Q$3 <= Вводные!$G167), 1, 0) -> 1 | ... BJ38: =IF( AND(BJ$3 >= Вводные!$F167, BJ$3 <= Вводные!$G167), 1, 0) -> 1
D39: =Вводные!$D$120 -> Долг 2 млн | E39: флаг | J39: =IF( AND(J$3 >= Вводные!$F168, J$3 <= Вводные!$G168), 1, 0) -> 1 | K39: =IF( AND(K$3 >= Вводные!$F168, K$3 <= Вводные!$G168), 1, 0) -> 1 | L39: =IF( AND(L$3 >= Вводные!$F168, L$3 <= Вводные!$G168), 1, 0) -> 0 | M39: =IF( AND(M$3 >= Вводные!$F168, M$3 <= Вводные!$G168), 1, 0) -> 0 | N39: =IF( AND(N$3 >= Вводные!$F168, N$3 <= Вводные!$G168), 1, 0) -> 0 | O39: =IF( AND(O$3 >= Вводные!$F168, O$3 <= Вводные!$G168), 1, 0) -> 0 | P39: =IF( AND(P$3 >= Вводные!$F168, P$3 <= Вводные!$G168), 1, 0) -> 0 | Q39: =IF( AND(Q$3 >= Вводные!$F168, Q$3 <= Вводные!$G168), 1, 0) -> 0 | ... BJ39: =IF( AND(BJ$3 >= Вводные!$F168, BJ$3 <= Вводные!$G168), 1, 0) -> 0
D40: =Вводные!$D$121 -> Долг за квартиру | E40: флаг | J40: =IF( AND(J$3 >= Вводные!$F169, J$3 <= Вводные!$G169), 1, 0) -> 1 | K40: =IF( AND(K$3 >= Вводные!$F169, K$3 <= Вводные!$G169), 1, 0) -> 1 | L40: =IF( AND(L$3 >= Вводные!$F169, L$3 <= Вводные!$G169), 1, 0) -> 1 | M40: =IF( AND(M$3 >= Вводные!$F169, M$3 <= Вводные!$G169), 1, 0) -> 1 | N40: =IF( AND(N$3 >= Вводные!$F169, N$3 <= Вводные!$G169), 1, 0) -> 1 | O40: =IF( AND(O$3 >= Вводные!$F169, O$3 <= Вводные!$G169), 1, 0) -> 0 | P40: =IF( AND(P$3 >= Вводные!$F169, P$3 <= Вводные!$G169), 1, 0) -> 0 | Q40: =IF( AND(Q$3 >= Вводные!$F169, Q$3 <= Вводные!$G169), 1, 0) -> 0 | ... BJ40: =IF( AND(BJ$3 >= Вводные!$F169, BJ$3 <= Вводные!$G169), 1, 0) -> 0
D41: =Вводные!$D$122 -> Подарки | E41: флаг | J41: =IF( AND(J$3 >= Вводные!$F170, J$3 <= Вводные!$G170), 1, 0) -> 1 | K41: =IF( AND(K$3 >= Вводные!$F170, K$3 <= Вводные!$G170), 1, 0) -> 1 | L41: =IF( AND(L$3 >= Вводные!$F170, L$3 <= Вводные!$G170), 1, 0) -> 1 | M41: =IF( AND(M$3 >= Вводные!$F170, M$3 <= Вводные!$G170), 1, 0) -> 1 | N41: =IF( AND(N$3 >= Вводные!$F170, N$3 <= Вводные!$G170), 1, 0) -> 1 | O41: =IF( AND(O$3 >= Вводные!$F170, O$3 <= Вводные!$G170), 1, 0) -> 1 | P41: =IF( AND(P$3 >= Вводные!$F170, P$3 <= Вводные!$G170), 1, 0) -> 1 | Q41: =IF( AND(Q$3 >= Вводные!$F170, Q$3 <= Вводные!$G170), 1, 0) -> 1 | ... BJ41: =IF( AND(BJ$3 >= Вводные!$F170, BJ$3 <= Вводные!$G170), 1, 0) -> 1
D42: =Вводные!$D$123 -> Ежегодный расход 8 | E42: флаг | J42: =IF( AND(J$3 >= Вводные!$F171, J$3 <= Вводные!$G171), 1, 0) -> 1 | K42: =IF( AND(K$3 >= Вводные!$F171, K$3 <= Вводные!$G171), 1, 0) -> 1 | L42: =IF( AND(L$3 >= Вводные!$F171, L$3 <= Вводные!$G171), 1, 0) -> 1 | M42: =IF( AND(M$3 >= Вводные!$F171, M$3 <= Вводные!$G171), 1, 0) -> 1 | N42: =IF( AND(N$3 >= Вводные!$F171, N$3 <= Вводные!$G171), 1, 0) -> 1 | O42: =IF( AND(O$3 >= Вводные!$F171, O$3 <= Вводные!$G171), 1, 0) -> 1 | P42: =IF( AND(P$3 >= Вводные!$F171, P$3 <= Вводные!$G171), 1, 0) -> 1 | Q42: =IF( AND(Q$3 >= Вводные!$F171, Q$3 <= Вводные!$G171), 1, 0) -> 1 | ... BJ42: =IF( AND(BJ$3 >= Вводные!$F171, BJ$3 <= Вводные!$G171), 1, 0) -> 1
D43: =Вводные!$D$124 -> Ежегодный расход 9 | E43: флаг | J43: =IF( AND(J$3 >= Вводные!$F172, J$3 <= Вводные!$G172), 1, 0) -> 1 | K43: =IF( AND(K$3 >= Вводные!$F172, K$3 <= Вводные!$G172), 1, 0) -> 1 | L43: =IF( AND(L$3 >= Вводные!$F172, L$3 <= Вводные!$G172), 1, 0) -> 1 | M43: =IF( AND(M$3 >= Вводные!$F172, M$3 <= Вводные!$G172), 1, 0) -> 1 | N43: =IF( AND(N$3 >= Вводные!$F172, N$3 <= Вводные!$G172), 1, 0) -> 1 | O43: =IF( AND(O$3 >= Вводные!$F172, O$3 <= Вводные!$G172), 1, 0) -> 1 | P43: =IF( AND(P$3 >= Вводные!$F172, P$3 <= Вводные!$G172), 1, 0) -> 1 | Q43: =IF( AND(Q$3 >= Вводные!$F172, Q$3 <= Вводные!$G172), 1, 0) -> 1 | ... BJ43: =IF( AND(BJ$3 >= Вводные!$F172, BJ$3 <= Вводные!$G172), 1, 0) -> 1
D44: =Вводные!$D$125 -> Ежегодный расход 10 | E44: флаг | J44: =IF( AND(J$3 >= Вводные!$F173, J$3 <= Вводные!$G173), 1, 0) -> 1 | K44: =IF( AND(K$3 >= Вводные!$F173, K$3 <= Вводные!$G173), 1, 0) -> 1 | L44: =IF( AND(L$3 >= Вводные!$F173, L$3 <= Вводные!$G173), 1, 0) -> 1 | M44: =IF( AND(M$3 >= Вводные!$F173, M$3 <= Вводные!$G173), 1, 0) -> 1 | N44: =IF( AND(N$3 >= Вводные!$F173, N$3 <= Вводные!$G173), 1, 0) -> 1 | O44: =IF( AND(O$3 >= Вводные!$F173, O$3 <= Вводные!$G173), 1, 0) -> 1 | P44: =IF( AND(P$3 >= Вводные!$F173, P$3 <= Вводные!$G173), 1, 0) -> 1 | Q44: =IF( AND(Q$3 >= Вводные!$F173, Q$3 <= Вводные!$G173), 1, 0) -> 1 | ... BJ44: =IF( AND(BJ$3 >= Вводные!$F173, BJ$3 <= Вводные!$G173), 1, 0) -> 1
B46: =MAX( $B$7:B43 ) + 1 -> 2 | D46: Расходы
D48: Всего расходы | E48: USD / год | I48: =SUM(I52,I98) -> -117000 | J48: =SUM(J52,J98) -> -117000 | K48: =SUM(K52,K98) -> -119880 | L48: =SUM(L52,L98) -> -119846.4 | M48: =SUM(M52,M98) -> -122901.79 | N48: =SUM(N52,N98) -> -126048.85 | O48: =SUM(O52,O98) -> -126290.31 | P48: =SUM(P52,P98) -> -129629.02 | ... BJ48: =SUM(BJ52,BJ98) -> -432532.39
C50: =MAX( $B$7:C47 ) + 0.1 -> 2.1 | D50: Ежемесячные расходы
D52: Ежемесячные расходы | E52: USD / год | I52: =SUM(I53:I72) -> -96000 | J52: =SUM(J53:J72) -> -96000 | K52: =SUM(K53:K72) -> -98520 | L52: =SUM(L53:L72) -> -101115.6 | M52: =SUM(M53:M72) -> -103789.07 | N52: =SUM(N53:N72) -> -106542.74 | O52: =SUM(O53:O72) -> -109379.02 | P52: =SUM(P53:P72) -> -112300.39 | ... BJ52: =SUM(BJ53:BJ72) -> -390674.42
D53: =Вводные!$D$70 -> Еда | E53: USD / год | I53: =Вводные!F70 * Вводные!$F$12 -> -12000 | J53: =$I53 * J75 * J13 -> -12000 | K53: =$I53 * K75 * K13 -> -12360 | L53: =$I53 * L75 * L13 -> -12730.8 | M53: =$I53 * M75 * M13 -> -13112.724 | N53: =$I53 * N75 * N13 -> -13506.106 | O53: =$I53 * O75 * O13 -> -13911.289 | P53: =$I53 * P75 * P13 -> -14328.628 | Q53: =$I53 * Q75 * Q13 -> -14758.486 | ... BJ53: =$I53 * BJ75 * BJ13 -> -55810.631
D54: =Вводные!$D$71 -> Садик | E54: USD / год | I54: =Вводные!F71 * Вводные!$F$12 -> -12000 | J54: =$I54 * J76 * J14 -> -12000 | K54: =$I54 * K76 * K14 -> -12360 | L54: =$I54 * L76 * L14 -> -12730.8 | M54: =$I54 * M76 * M14 -> -13112.724 | N54: =$I54 * N76 * N14 -> -13506.106 | O54: =$I54 * O76 * O14 -> -13911.289 | P54: =$I54 * P76 * P14 -> -14328.628 | Q54: =$I54 * Q76 * Q14 -> -14758.486 | ... BJ54: =$I54 * BJ76 * BJ14 -> -55810.631
D55: =Вводные!$D$72 -> Няня | E55: USD / год | I55: =Вводные!F72 * Вводные!$F$12 -> -12000 | J55: =$I55 * J77 * J15 -> -12000 | K55: =$I55 * K77 * K15 -> -12360 | L55: =$I55 * L77 * L15 -> -12730.8 | M55: =$I55 * M77 * M15 -> -13112.724 | N55: =$I55 * N77 * N15 -> -13506.106 | O55: =$I55 * O77 * O15 -> -13911.289 | P55: =$I55 * P77 * P15 -> -14328.628 | Q55: =$I55 * Q77 * Q15 -> -14758.486 | ... BJ55: =$I55 * BJ77 * BJ15 -> -55810.631
D56: =Вводные!$D$73 -> Ипотека | E56: USD / год | I56: =Вводные!F73 * Вводные!$F$12 -> -12000 | J56: =$I56 * J78 * J16 -> -12000 | K56: =$I56 * K78 * K16 -> -12000 | L56: =$I56 * L78 * L16 -> -12000 | M56: =$I56 * M78 * M16 -> -12000 | N56: =$I56 * N78 * N16 -> -12000 | O56: =$I56 * O78 * O16 -> -12000 | P56: =$I56 * P78 * P16 -> -12000 | Q56: =$I56 * Q78 * Q16 -> -12000 | ... BJ56: =$I56 * BJ78 * BJ16 -> 0
D57: =Вводные!$D$74 -> Аренда квартиры + коммуналка | E57: USD / год | I57: =Вводные!F74 * Вводные!$F$12 -> -12000 | J57: =$I57 * J79 * J17 -> -12000 | K57: =$I57 * K79 * K17 -> -12360 | L57: =$I57 * L79 * L17 -> -12730.8 | M57: =$I57 * M79 * M17 -> -13112.724 | N57: =$I57 * N79 * N17 -> -13506.106 | O57: =$I57 * O79 * O17 -> -13911.289 | P57: =$I57 * P79 * P17 -> -14328.628 | Q57: =$I57 * Q79 * Q17 -> -14758.486 | ... BJ57: =$I57 * BJ79 * BJ17 -> -55810.631
D58: =Вводные!$D$75 -> Связь + интернет | E58: USD / год | I58: =Вводные!F75 * Вводные!$F$12 -> -12000 | J58: =$I58 * J80 * J18 -> -12000 | K58: =$I58 * K80 * K18 -> -12360 | L58: =$I58 * L80 * L18 -> -12730.8 | M58: =$I58 * M80 * M18 -> -13112.724 | N58: =$I58 * N80 * N18 -> -13506.106 | O58: =$I58 * O80 * O18 -> -13911.289 | P58: =$I58 * P80 * P18 -> -14328.628 | Q58: =$I58 * Q80 * Q18 -> -14758.486 | ... BJ58: =$I58 * BJ80 * BJ18 -> -55810.631
D59: =Вводные!$D$76 -> Командировки | E59: USD / год | I59: =Вводные!F76 * Вводные!$F$12 -> -12000 | J59: =$I59 * J81 * J19 -> -12000 | K59: =$I59 * K81 * K19 -> -12360 | L59: =$I59 * L81 * L19 -> -12730.8 | M59: =$I59 * M81 * M19 -> -13112.724 | N59: =$I59 * N81 * N19 -> -13506.106 | O59: =$I59 * O81 * O19 -> -13911.289 | P59: =$I59 * P81 * P19 -> -14328.628 | Q59: =$I59 * Q81 * Q19 -> -14758.486 | ... BJ59: =$I59 * BJ81 * BJ19 -> -55810.631
D60: =Вводные!$D$77 -> Прочее | E60: USD / год | I60: =Вводные!F77 * Вводные!$F$12 -> -12000 | J60: =$I60 * J82 * J20 -> -12000 | K60: =$I60 * K82 * K20 -> -12360 | L60: =$I60 * L82 * L20 -> -12730.8 | M60: =$I60 * M82 * M20 -> -13112.724 | N60: =$I60 * N82 * N20 -> -13506.106 | O60: =$I60 * O82 * O20 -> -13911.289 | P60: =$I60 * P82 * P20 -> -14328.628 | Q60: =$I60 * Q82 * Q20 -> -14758.486 | ... BJ60: =$I60 * BJ82 * BJ20 -> -55810.631
D61: =Вводные!$D$78 -> Ежемесячный расход 9 | E61: USD / год | I61: =Вводные!F78 * Вводные!$F$12 -> 0 | J61: =$I61 * J83 * J21 -> 0 | K61: =$I61 * K83 * K21 -> 0 | L61: =$I61 * L83 * L21 -> 0 | M61: =$I61 * M83 * M21 -> 0 | N61: =$I61 * N83 * N21 -> 0 | O61: =$I61 * O83 * O21 -> 0 | P61: =$I61 * P83 * P21 -> 0 | Q61: =$I61 * Q83 * Q21 -> 0 | ... BJ61: =$I61 * BJ83 * BJ21 -> 0
D62: =Вводные!$D$79 -> Ежемесячный расход 10 | E62: USD / год | I62: =Вводные!F79 * Вводные!$F$12 -> 0 | J62: =$I62 * J84 * J22 -> 0 | K62: =$I62 * K84 * K22 -> 0 | L62: =$I62 * L84 * L22 -> 0 | M62: =$I62 * M84 * M22 -> 0 | N62: =$I62 * N84 * N22 -> 0 | O62: =$I62 * O84 * O22 -> 0 | P62: =$I62 * P84 * P22 -> 0 | Q62: =$I62 * Q84 * Q22 -> 0 | ... BJ62: =$I62 * BJ84 * BJ22 -> 0
D63: =Вводные!$D$80 -> Ежемесячный расход 11 | E63: USD / год | I63: =Вводные!F80 * Вводные!$F$12 -> 0 | J63: =$I63 * J85 * J23 -> 0 | K63: =$I63 * K85 * K23 -> 0 | L63: =$I63 * L85 * L23 -> 0 | M63: =$I63 * M85 * M23 -> 0 | N63: =$I63 * N85 * N23 -> 0 | O63: =$I63 * O85 * O23 -> 0 | P63: =$I63 * P85 * P23 -> 0 | Q63: =$I63 * Q85 * Q23 -> 0 | ... BJ63: =$I63 * BJ85 * BJ23 -> 0
D64: =Вводные!$D$81 -> Ежемесячный расход 12 | E64: USD / год | I64: =Вводные!F81 * Вводные!$F$12 -> 0 | J64: =$I64 * J86 * J24 -> 0 | K64: =$I64 * K86 * K24 -> 0 | L64: =$I64 * L86 * L24 -> 0 | M64: =$I64 * M86 * M24 -> 0 | N64: =$I64 * N86 * N24 -> 0 | O64: =$I64 * O86 * O24 -> 0 | P64: =$I64 * P86 * P24 -> 0 | Q64: =$I64 * Q86 * Q24 -> 0 | ... BJ64: =$I64 * BJ86 * BJ24 -> 0
D65: =Вводные!$D$82 -> Ежемесячный расход 13 | E65: USD / год | I65: =Вводные!F82 * Вводные!$F$12 -> 0 | J65: =$I65 * J87 * J25 -> 0 | K65: =$I65 * K87 * K25 -> 0 | L65: =$I65 * L87 * L25 -> 0 | M65: =$I65 * M87 * M25 -> 0 | N65: =$I65 * N87 * N25 -> 0 | O65: =$I65 * O87 * O25 -> 0 | P65: =$I65 * P87 * P25 -> 0 | Q65: =$I65 * Q87 * Q25 -> 0 | ... BJ65: =$I65 * BJ87 * BJ25 -> 0
D66: =Вводные!$D$83 -> Ежемесячный расход 14 | E66: USD / год | I66: =Вводные!F83 * Вводные!$F$12 -> 0 | J66: =$I66 * J88 * J26 -> 0 | K66: =$I66 * K88 * K26 -> 0 | L66: =$I66 * L88 * L26 -> 0 | M66: =$I66 * M88 * M26 -> 0 | N66: =$I66 * N88 * N26 -> 0 | O66: =$I66 * O88 * O26 -> 0 | P66: =$I66 * P88 * P26 -> 0 | Q66: =$I66 * Q88 * Q26 -> 0 | ... BJ66: =$I66 * BJ88 * BJ26 -> 0
D67: =Вводные!$D$84 -> Ежемесячный расход 15 | E67: USD / год | I67: =Вводные!F84 * Вводные!$F$12 -> 0 | J67: =$I67 * J89 * J27 -> 0 | K67: =$I67 * K89 * K27 -> 0 | L67: =$I67 * L89 * L27 -> 0 | M67: =$I67 * M89 * M27 -> 0 | N67: =$I67 * N89 * N27 -> 0 | O67: =$I67 * O89 * O27 -> 0 | P67: =$I67 * P89 * P27 -> 0 | Q67: =$I67 * Q89 * Q27 -> 0 | ... BJ67: =$I67 * BJ89 * BJ27 -> 0
D68: =Вводные!$D$85 -> Ежемесячный расход 16 | E68: USD / год | I68: =Вводные!F85 * Вводные!$F$12 -> 0 | J68: =$I68 * J90 * J28 -> 0 | K68: =$I68 * K90 * K28 -> 0 | L68: =$I68 * L90 * L28 -> 0 | M68: =$I68 * M90 * M28 -> 0 | N68: =$I68 * N90 * N28 -> 0 | O68: =$I68 * O90 * O28 -> 0 | P68: =$I68 * P90 * P28 -> 0 | Q68: =$I68 * Q90 * Q28 -> 0 | ... BJ68: =$I68 * BJ90 * BJ28 -> 0
D69: =Вводные!$D$86 -> Ежемесячный расход 17 | E69: USD / год | I69: =Вводные!F86 * Вводные!$F$12 -> 0 | J69: =$I69 * J91 * J29 -> 0 | K69: =$I69 * K91 * K29 -> 0 | L69: =$I69 * L91 * L29 -> 0 | M69: =$I69 * M91 * M29 -> 0 | N69: =$I69 * N91 * N29 -> 0 | O69: =$I69 * O91 * O29 -> 0 | P69: =$I69 * P91 * P29 -> 0 | Q69: =$I69 * Q91 * Q29 -> 0 | ... BJ69: =$I69 * BJ91 * BJ29 -> 0
D70: =Вводные!$D$87 -> Ежемесячный расход 18 | E70: USD / год | I70: =Вводные!F87 * Вводные!$F$12 -> 0 | J70: =$I70 * J92 * J30 -> 0 | K70: =$I70 * K92 * K30 -> 0 | L70: =$I70 * L92 * L30 -> 0 | M70: =$I70 * M92 * M30 -> 0 | N70: =$I70 * N92 * N30 -> 0 | O70: =$I70 * O92 * O30 -> 0 | P70: =$I70 * P92 * P30 -> 0 | Q70: =$I70 * Q92 * Q30 -> 0 | ... BJ70: =$I70 * BJ92 * BJ30 -> 0
D71: =Вводные!$D$88 -> Ежемесячный расход 19 | E71: USD / год | I71: =Вводные!F88 * Вводные!$F$12 -> 0 | J71: =$I71 * J93 * J31 -> 0 | K71: =$I71 * K93 * K31 -> 0 | L71: =$I71 * L93 * L31 -> 0 | M71: =$I71 * M93 * M31 -> 0 | N71: =$I71 * N93 * N31 -> 0 | O71: =$I71 * O93 * O31 -> 0 | P71: =$I71 * P93 * P31 -> 0 | Q71: =$I71 * Q93 * Q31 -> 0 | ... BJ71: =$I71 * BJ93 * BJ31 -> 0
D72: =Вводные!$D$89 -> Ежемесячный расход 20 | E72: USD / год | I72: =Вводные!F89 * Вводные!$F$12 -> 0 | J72: =$I72 * J94 * J32 -> 0 | K72: =$I72 * K94 * K32 -> 0 | L72: =$I72 * L94 * L32 -> 0 | M72: =$I72 * M94 * M32 -> 0 | N72: =$I72 * N94 * N32 -> 0 | O72: =$I72 * O94 * O32 -> 0 | P72: =$I72 * P94 * P32 -> 0 | Q72: =$I72 * Q94 * Q32 -> 0 | ... BJ72: =$I72 * BJ94 * BJ32 -> 0
D74: Темп роста ежемесячных расходов | E74: %
D75: =Вводные!$D$92 -> Темп роста Еда | E75: % | I75: 1 | J75: =I75 * (1+Вводные!J92) -> 1 | K75: =J75 * (1+Вводные!K92) -> 1.03 | L75: =K75 * (1+Вводные!L92) -> 1.0609 | M75: =L75 * (1+Вводные!M92) -> 1.092727 | N75: =M75 * (1+Вводные!N92) -> 1.1255088 | O75: =N75 * (1+Вводные!O92) -> 1.1592741 | P75: =O75 * (1+Вводные!P92) -> 1.1940523 | Q75: =P75 * (1+Вводные!Q92) -> 1.2298739 | ... BJ75: =BI75 * (1+Вводные!BJ92) -> 4.6508859
D76: =Вводные!$D$93 -> Темп роста Садик | E76: % | I76: 1 | J76: =I76 * (1+Вводные!J93) -> 1 | K76: =J76 * (1+Вводные!K93) -> 1.03 | L76: =K76 * (1+Вводные!L93) -> 1.0609 | M76: =L76 * (1+Вводные!M93) -> 1.092727 | N76: =M76 * (1+Вводные!N93) -> 1.1255088 | O76: =N76 * (1+Вводные!O93) -> 1.1592741 | P76: =O76 * (1+Вводные!P93) -> 1.1940523 | Q76: =P76 * (1+Вводные!Q93) -> 1.2298739 | ... BJ76: =BI76 * (1+Вводные!BJ93) -> 4.6508859
D77: =Вводные!$D$94 -> Темп роста Няня | E77: % | I77: 1 | J77: =I77 * (1+Вводные!J94) -> 1 | K77: =J77 * (1+Вводные!K94) -> 1.03 | L77: =K77 * (1+Вводные!L94) -> 1.0609 | M77: =L77 * (1+Вводные!M94) -> 1.092727 | N77: =M77 * (1+Вводные!N94) -> 1.1255088 | O77: =N77 * (1+Вводные!O94) -> 1.1592741 | P77: =O77 * (1+Вводные!P94) -> 1.1940523 | Q77: =P77 * (1+Вводные!Q94) -> 1.2298739 | ... BJ77: =BI77 * (1+Вводные!BJ94) -> 4.6508859
D78: =Вводные!$D$95 -> Темп роста Ипотека | E78: % | I78: 1 | J78: =I78 * (1+Вводные!J95) -> 1 | K78: =J78 * (1+Вводные!K95) -> 1 | L78: =K78 * (1+Вводные!L95) -> 1 | M78: =L78 * (1+Вводные!M95) -> 1 | N78: =M78 * (1+Вводные!N95) -> 1 | O78: =N78 * (1+Вводные!O95) -> 1 | P78: =O78 * (1+Вводные!P95) -> 1 | Q78: =P78 * (1+Вводные!Q95) -> 1 | ... BJ78: =BI78 * (1+Вводные!BJ95) -> 1
D79: =Вводные!$D$96 -> Темп роста Аренда квартиры + коммуналка | E79: % | I79: 1 | J79: =I79 * (1+Вводные!J96) -> 1 | K79: =J79 * (1+Вводные!K96) -> 1.03 | L79: =K79 * (1+Вводные!L96) -> 1.0609 | M79: =L79 * (1+Вводные!M96) -> 1.092727 | N79: =M79 * (1+Вводные!N96) -> 1.1255088 | O79: =N79 * (1+Вводные!O96) -> 1.1592741 | P79: =O79 * (1+Вводные!P96) -> 1.1940523 | Q79: =P79 * (1+Вводные!Q96) -> 1.2298739 | ... BJ79: =BI79 * (1+Вводные!BJ96) -> 4.6508859
D80: =Вводные!$D$97 -> Темп роста Связь + интернет | E80: % | I80: 1 | J80: =I80 * (1+Вводные!J97) -> 1 | K80: =J80 * (1+Вводные!K97) -> 1.03 | L80: =K80 * (1+Вводные!L97) -> 1.0609 | M80: =L80 * (1+Вводные!M97) -> 1.092727 | N80: =M80 * (1+Вводные!N97) -> 1.1255088 | O80: =N80 * (1+Вводные!O97) -> 1.1592741 | P80: =O80 * (1+Вводные!P97) -> 1.1940523 | Q80: =P80 * (1+Вводные!Q97) -> 1.2298739 | ... BJ80: =BI80 * (1+Вводные!BJ97) -> 4.6508859
D81: =Вводные!$D$98 -> Темп роста Командировки | E81: % | I81: 1 | J81: =I81 * (1+Вводные!J98) -> 1 | K81: =J81 * (1+Вводные!K98) -> 1.03 | L81: =K81 * (1+Вводные!L98) -> 1.0609 | M81: =L81 * (1+Вводные!M98) -> 1.092727 | N81: =M81 * (1+Вводные!N98) -> 1.1255088 | O81: =N81 * (1+Вводные!O98) -> 1.1592741 | P81: =O81 * (1+Вводные!P98) -> 1.1940523 | Q81: =P81 * (1+Вводные!Q98) -> 1.2298739 | ... BJ81: =BI81 * (1+Вводные!BJ98) -> 4.6508859
D82: =Вводные!$D$99 -> Темп роста Прочее | E82: % | I82: 1 | J82: =I82 * (1+Вводные!J99) -> 1 | K82: =J82 * (1+Вводные!K99) -> 1.03 | L82: =K82 * (1+Вводные!L99) -> 1.0609 | M82: =L82 * (1+Вводные!M99) -> 1.092727 | N82: =M82 * (1+Вводные!N99) -> 1.1255088 | O82: =N82 * (1+Вводные!O99) -> 1.1592741 | P82: =O82 * (1+Вводные!P99) -> 1.1940523 | Q82: =P82 * (1+Вводные!Q99) -> 1.2298739 | ... BJ82: =BI82 * (1+Вводные!BJ99) -> 4.6508859
D83: =Вводные!$D$100 -> Темп роста Ежемесячный расход 9 | E83: % | I83: 1 | J83: =I83 * (1+Вводные!J100) -> 1 | K83: =J83 * (1+Вводные!K100) -> 1.03 | L83: =K83 * (1+Вводные!L100) -> 1.0609 | M83: =L83 * (1+Вводные!M100) -> 1.092727 | N83: =M83 * (1+Вводные!N100) -> 1.1255088 | O83: =N83 * (1+Вводные!O100) -> 1.1592741 | P83: =O83 * (1+Вводные!P100) -> 1.1940523 | Q83: =P83 * (1+Вводные!Q100) -> 1.2298739 | ... BJ83: =BI83 * (1+Вводные!BJ100) -> 4.6508859
D84: =Вводные!$D$101 -> Темп роста Ежемесячный расход 10 | E84: % | I84: 1 | J84: =I84 * (1+Вводные!J101) -> 1 | K84: =J84 * (1+Вводные!K101) -> 1.03 | L84: =K84 * (1+Вводные!L101) -> 1.0609 | M84: =L84 * (1+Вводные!M101) -> 1.092727 | N84: =M84 * (1+Вводные!N101) -> 1.1255088 | O84: =N84 * (1+Вводные!O101) -> 1.1592741 | P84: =O84 * (1+Вводные!P101) -> 1.1940523 | Q84: =P84 * (1+Вводные!Q101) -> 1.2298739 | ... BJ84: =BI84 * (1+Вводные!BJ101) -> 4.6508859
D85: =Вводные!$D$102 -> Темп роста Ежемесячный расход 11 | E85: % | I85: 1 | J85: =I85 * (1+Вводные!J102) -> 1 | K85: =J85 * (1+Вводные!K102) -> 1.03 | L85: =K85 * (1+Вводные!L102) -> 1.0609 | M85: =L85 * (1+Вводные!M102) -> 1.092727 | N85: =M85 * (1+Вводные!N102) -> 1.1255088 | O85: =N85 * (1+Вводные!O102) -> 1.1592741 | P85: =O85 * (1+Вводные!P102) -> 1.1940523 | Q85: =P85 * (1+Вводные!Q102) -> 1.2298739 | ... BJ85: =BI85 * (1+Вводные!BJ102) -> 4.6508859
D86: =Вводные!$D$103 -> Темп роста Ежемесячный расход 12 | E86: % | I86: 1 | J86: =I86 * (1+Вводные!J103) -> 1 | K86: =J86 * (1+Вводные!K103) -> 1.03 | L86: =K86 * (1+Вводные!L103) -> 1.0609 | M86: =L86 * (1+Вводные!M103) -> 1.092727 | N86: =M86 * (1+Вводные!N103) -> 1.1255088 | O86: =N86 * (1+Вводные!O103) -> 1.1592741 | P86: =O86 * (1+Вводные!P103) -> 1.1940523 | Q86: =P86 * (1+Вводные!Q103) -> 1.2298739 | ... BJ86: =BI86 * (1+Вводные!BJ103) -> 4.6508859
D87: =Вводные!$D$104 -> Темп роста Ежемесячный расход 13 | E87: % | I87: 1 | J87: =I87 * (1+Вводные!J104) -> 1 | K87: =J87 * (1+Вводные!K104) -> 1.03 | L87: =K87 * (1+Вводные!L104) -> 1.0609 | M87: =L87 * (1+Вводные!M104) -> 1.092727 | N87: =M87 * (1+Вводные!N104) -> 1.1255088 | O87: =N87 * (1+Вводные!O104) -> 1.1592741 | P87: =O87 * (1+Вводные!P104) -> 1.1940523 | Q87: =P87 * (1+Вводные!Q104) -> 1.2298739 | ... BJ87: =BI87 * (1+Вводные!BJ104) -> 4.6508859
D88: =Вводные!$D$105 -> Темп роста Ежемесячный расход 14 | E88: % | I88: 1 | J88: =I88 * (1+Вводные!J105) -> 1 | K88: =J88 * (1+Вводные!K105) -> 1.03 | L88: =K88 * (1+Вводные!L105) -> 1.0609 | M88: =L88 * (1+Вводные!M105) -> 1.092727 | N88: =M88 * (1+Вводные!N105) -> 1.1255088 | O88: =N88 * (1+Вводные!O105) -> 1.1592741 | P88: =O88 * (1+Вводные!P105) -> 1.1940523 | Q88: =P88 * (1+Вводные!Q105) -> 1.2298739 | ... BJ88: =BI88 * (1+Вводные!BJ105) -> 4.6508859
D89: =Вводные!$D$106 -> Темп роста Ежемесячный расход 15 | E89: % | I89: 1 | J89: =I89 * (1+Вводные!J106) -> 1 | K89: =J89 * (1+Вводные!K106) -> 1.03 | L89: =K89 * (1+Вводные!L106) -> 1.0609 | M89: =L89 * (1+Вводные!M106) -> 1.092727 | N89: =M89 * (1+Вводные!N106) -> 1.1255088 | O89: =N89 * (1+Вводные!O106) -> 1.1592741 | P89: =O89 * (1+Вводные!P106) -> 1.1940523 | Q89: =P89 * (1+Вводные!Q106) -> 1.2298739 | ... BJ89: =BI89 * (1+Вводные!BJ106) -> 4.6508859
D90: =Вводные!$D$107 -> Темп роста Ежемесячный расход 16 | E90: % | I90: 1 | J90: =I90 * (1+Вводные!J107) -> 1 | K90: =J90 * (1+Вводные!K107) -> 1.03 | L90: =K90 * (1+Вводные!L107) -> 1.0609 | M90: =L90 * (1+Вводные!M107) -> 1.092727 | N90: =M90 * (1+Вводные!N107) -> 1.1255088 | O90: =N90 * (1+Вводные!O107) -> 1.1592741 | P90: =O90 * (1+Вводные!P107) -> 1.1940523 | Q90: =P90 * (1+Вводные!Q107) -> 1.2298739 | ... BJ90: =BI90 * (1+Вводные!BJ107) -> 4.6508859
D91: =Вводные!$D$108 -> Темп роста Ежемесячный расход 17 | E91: % | I91: 1 | J91: =I91 * (1+Вводные!J108) -> 1 | K91: =J91 * (1+Вводные!K108) -> 1.03 | L91: =K91 * (1+Вводные!L108) -> 1.0609 | M91: =L91 * (1+Вводные!M108) -> 1.092727 | N91: =M91 * (1+Вводные!N108) -> 1.1255088 | O91: =N91 * (1+Вводные!O108) -> 1.1592741 | P91: =O91 * (1+Вводные!P108) -> 1.1940523 | Q91: =P91 * (1+Вводные!Q108) -> 1.2298739 | ... BJ91: =BI91 * (1+Вводные!BJ108) -> 4.6508859
D92: =Вводные!$D$109 -> Темп роста Ежемесячный расход 18 | E92: % | I92: 1 | J92: =I92 * (1+Вводные!J109) -> 1 | K92: =J92 * (1+Вводные!K109) -> 1.03 | L92: =K92 * (1+Вводные!L109) -> 1.0609 | M92: =L92 * (1+Вводные!M109) -> 1.092727 | N92: =M92 * (1+Вводные!N109) -> 1.1255088 | O92: =N92 * (1+Вводные!O109) -> 1.1592741 | P92: =O92 * (1+Вводные!P109) -> 1.1940523 | Q92: =P92 * (1+Вводные!Q109) -> 1.2298739 | ... BJ92: =BI92 * (1+Вводные!BJ109) -> 4.6508859
D93: =Вводные!$D$110 -> Темп роста Ежемесячный расход 19 | E93: % | I93: 1 | J93: =I93 * (1+Вводные!J110) -> 1 | K93: =J93 * (1+Вводные!K110) -> 1.03 | L93: =K93 * (1+Вводные!L110) -> 1.0609 | M93: =L93 * (1+Вводные!M110) -> 1.092727 | N93: =M93 * (1+Вводные!N110) -> 1.1255088 | O93: =N93 * (1+Вводные!O110) -> 1.1592741 | P93: =O93 * (1+Вводные!P110) -> 1.1940523 | Q93: =P93 * (1+Вводные!Q110) -> 1.2298739 | ... BJ93: =BI93 * (1+Вводные!BJ110) -> 4.6508859
D94: =Вводные!$D$111 -> Темп роста Ежемесячный расход 20 | E94: % | I94: 1 | J94: =I94 * (1+Вводные!J111) -> 1 | K94: =J94 * (1+Вводные!K111) -> 1.03 | L94: =K94 * (1+Вводные!L111) -> 1.0609 | M94: =L94 * (1+Вводные!M111) -> 1.092727 | N94: =M94 * (1+Вводные!N111) -> 1.1255088 | O94: =N94 * (1+Вводные!O111) -> 1.1592741 | P94: =O94 * (1+Вводные!P111) -> 1.1940523 | Q94: =P94 * (1+Вводные!Q111) -> 1.2298739 | ... BJ94: =BI94 * (1+Вводные!BJ111) -> 4.6508859
C96: =MAX( $B$7:C95 ) + 0.1 -> 2.2 | D96: Ежегодные расходы
D98: Ежегодные расходы | E98: USD / год | I98: =SUM(I99:I108) -> -21000 | J98: =SUM(J99:J108) -> -21000 | K98: =SUM(K99:K108) -> -21360 | L98: =SUM(L99:L108) -> -18730.8 | M98: =SUM(M99:M108) -> -19112.724 | N98: =SUM(N99:N108) -> -19506.106 | O98: =SUM(O99:O108) -> -16911.289 | P98: =SUM(P99:P108) -> -17328.628 | ... BJ98: =SUM(BJ99:BJ108) -> -41857.973
D99: =Вводные!$D$116 -> Страховка | E99: USD / год | I99: =Вводные!F116 -> -3000 | J99: =$I99 * J111 * J35 -> -3000 | K99: =$I99 * K111 * K35 -> -3090 | L99: =$I99 * L111 * L35 -> -3182.7 | M99: =$I99 * M111 * M35 -> -3278.181 | N99: =$I99 * N111 * N35 -> -3376.5264 | O99: =$I99 * O111 * O35 -> -3477.8222 | P99: =$I99 * P111 * P35 -> -3582.1569 | Q99: =$I99 * Q111 * Q35 -> -3689.6216 | ... BJ99: =$I99 * BJ111 * BJ35 -> -13952.658
D100: =Вводные!$D$117 -> Детский сад / школа | E100: USD / год | I100: =Вводные!F117 -> -3000 | J100: =$I100 * J112 * J36 -> -3000 | K100: =$I100 * K112 * K36 -> -3090 | L100: =$I100 * L112 * L36 -> -3182.7 | M100: =$I100 * M112 * M36 -> -3278.181 | N100: =$I100 * N112 * N36 -> -3376.5264 | O100: =$I100 * O112 * O36 -> -3477.8222 | P100: =$I100 * P112 * P36 -> -3582.1569 | Q100: =$I100 * Q112 * Q36 -> -3689.6216 | ... BJ100: =$I100 * BJ112 * BJ36 -> 0
D101: =Вводные!$D$118 -> Страховка по ипотеке | E101: USD / год | I101: =Вводные!F118 -> -3000 | J101: =$I101 * J113 * J37 -> -3000 | K101: =$I101 * K113 * K37 -> -3000 | L101: =$I101 * L113 * L37 -> -3000 | M101: =$I101 * M113 * M37 -> -3000 | N101: =$I101 * N113 * N37 -> -3000 | O101: =$I101 * O113 * O37 -> -3000 | P101: =$I101 * P113 * P37 -> -3000 | Q101: =$I101 * Q113 * Q37 -> -3000 | ... BJ101: =$I101 * BJ113 * BJ37 -> 0
D102: =Вводные!$D$119 -> Отпуск | E102: USD / год | I102: =Вводные!F119 -> -3000 | J102: =$I102 * J114 * J38 -> -3000 | K102: =$I102 * K114 * K38 -> -3090 | L102: =$I102 * L114 * L38 -> -3182.7 | M102: =$I102 * M114 * M38 -> -3278.181 | N102: =$I102 * N114 * N38 -> -3376.5264 | O102: =$I102 * O114 * O38 -> -3477.8222 | P102: =$I102 * P114 * P38 -> -3582.1569 | Q102: =$I102 * Q114 * Q38 -> -3689.6216 | ... BJ102: =$I102 * BJ114 * BJ38 -> -13952.658
D103: =Вводные!$D$120 -> Долг 2 млн | E103: USD / год | I103: =Вводные!F120 -> -3000 | J103: =$I103 * J115 * J39 -> -3000 | K103: =$I103 * K115 * K39 -> -3000 | L103: =$I103 * L115 * L39 -> 0 | M103: =$I103 * M115 * M39 -> 0 | N103: =$I103 * N115 * N39 -> 0 | O103: =$I103 * O115 * O39 -> 0 | P103: =$I103 * P115 * P39 -> 0 | Q103: =$I103 * Q115 * Q39 -> 0 | ... BJ103: =$I103 * BJ115 * BJ39 -> 0
D104: =Вводные!$D$121 -> Долг за квартиру | E104: USD / год | I104: =Вводные!F121 -> -3000 | J104: =$I104 * J116 * J40 -> -3000 | K104: =$I104 * K116 * K40 -> -3000 | L104: =$I104 * L116 * L40 -> -3000 | M104: =$I104 * M116 * M40 -> -3000 | N104: =$I104 * N116 * N40 -> -3000 | O104: =$I104 * O116 * O40 -> 0 | P104: =$I104 * P116 * P40 -> 0 | Q104: =$I104 * Q116 * Q40 -> 0 | ... BJ104: =$I104 * BJ116 * BJ40 -> 0
D105: =Вводные!$D$122 -> Подарки | E105: USD / год | I105: =Вводные!F122 -> -3000 | J105: =$I105 * J117 * J41 -> -3000 | K105: =$I105 * K117 * K41 -> -3090 | L105: =$I105 * L117 * L41 -> -3182.7 | M105: =$I105 * M117 * M41 -> -3278.181 | N105: =$I105 * N117 * N41 -> -3376.5264 | O105: =$I105 * O117 * O41 -> -3477.8222 | P105: =$I105 * P117 * P41 -> -3582.1569 | Q105: =$I105 * Q117 * Q41 -> -3689.6216 | ... BJ105: =$I105 * BJ117 * BJ41 -> -13952.658
D106: =Вводные!$D$123 -> Ежегодный расход 8 | E106: USD / год | I106: =Вводные!F123 -> 0 | J106: =$I106 * J118 * J42 -> 0 | K106: =$I106 * K118 * K42 -> 0 | L106: =$I106 * L118 * L42 -> 0 | M106: =$I106 * M118 * M42 -> 0 | N106: =$I106 * N118 * N42 -> 0 | O106: =$I106 * O118 * O42 -> 0 | P106: =$I106 * P118 * P42 -> 0 | Q106: =$I106 * Q118 * Q42 -> 0 | ... BJ106: =$I106 * BJ118 * BJ42 -> 0
D107: =Вводные!$D$124 -> Ежегодный расход 9 | E107: USD / год | I107: =Вводные!F124 -> 0 | J107: =$I107 * J119 * J43 -> 0 | K107: =$I107 * K119 * K43 -> 0 | L107: =$I107 * L119 * L43 -> 0 | M107: =$I107 * M119 * M43 -> 0 | N107: =$I107 * N119 * N43 -> 0 | O107: =$I107 * O119 * O43 -> 0 | P107: =$I107 * P119 * P43 -> 0 | Q107: =$I107 * Q119 * Q43 -> 0 | ... BJ107: =$I107 * BJ119 * BJ43 -> 0
D108: =Вводные!$D$125 -> Ежегодный расход 10 | E108: USD / год | I108: =Вводные!F125 -> 0 | J108: =$I108 * J120 * J44 -> 0 | K108: =$I108 * K120 * K44 -> 0 | L108: =$I108 * L120 * L44 -> 0 | M108: =$I108 * M120 * M44 -> 0 | N108: =$I108 * N120 * N44 -> 0 | O108: =$I108 * O120 * O44 -> 0 | P108: =$I108 * P120 * P44 -> 0 | Q108: =$I108 * Q120 * Q44 -> 0 | ... BJ108: =$I108 * BJ120 * BJ44 -> 0
D110: Темп роста ежегодных расходов
D111: =Вводные!$D$128 -> Темп роста Страховка | E111: % | I111: 1 | J111: =I111 * (1+Вводные!J128) -> 1 | K111: =J111 * (1+Вводные!K128) -> 1.03 | L111: =K111 * (1+Вводные!L128) -> 1.0609 | M111: =L111 * (1+Вводные!M128) -> 1.092727 | N111: =M111 * (1+Вводные!N128) -> 1.1255088 | O111: =N111 * (1+Вводные!O128) -> 1.1592741 | P111: =O111 * (1+Вводные!P128) -> 1.1940523 | Q111: =P111 * (1+Вводные!Q128) -> 1.2298739 | ... BJ111: =BI111 * (1+Вводные!BJ128) -> 4.6508859
D112: =Вводные!$D$129 -> Темп роста Детский сад / школа | E112: % | I112: 1 | J112: =I112 * (1+Вводные!J129) -> 1 | K112: =J112 * (1+Вводные!K129) -> 1.03 | L112: =K112 * (1+Вводные!L129) -> 1.0609 | M112: =L112 * (1+Вводные!M129) -> 1.092727 | N112: =M112 * (1+Вводные!N129) -> 1.1255088 | O112: =N112 * (1+Вводные!O129) -> 1.1592741 | P112: =O112 * (1+Вводные!P129) -> 1.1940523 | Q112: =P112 * (1+Вводные!Q129) -> 1.2298739 | ... BJ112: =BI112 * (1+Вводные!BJ129) -> 4.6508859
D113: =Вводные!$D$130 -> Темп роста Страховка по ипотеке | E113: % | I113: 1 | J113: =I113 * (1+Вводные!J130) -> 1 | K113: =J113 * (1+Вводные!K130) -> 1 | L113: =K113 * (1+Вводные!L130) -> 1 | M113: =L113 * (1+Вводные!M130) -> 1 | N113: =M113 * (1+Вводные!N130) -> 1 | O113: =N113 * (1+Вводные!O130) -> 1 | P113: =O113 * (1+Вводные!P130) -> 1 | Q113: =P113 * (1+Вводные!Q130) -> 1 | ... BJ113: =BI113 * (1+Вводные!BJ130) -> 1
D114: =Вводные!$D$131 -> Темп роста Отпуск | E114: % | I114: 1 | J114: =I114 * (1+Вводные!J131) -> 1 | K114: =J114 * (1+Вводные!K131) -> 1.03 | L114: =K114 * (1+Вводные!L131) -> 1.0609 | M114: =L114 * (1+Вводные!M131) -> 1.092727 | N114: =M114 * (1+Вводные!N131) -> 1.1255088 | O114: =N114 * (1+Вводные!O131) -> 1.1592741 | P114: =O114 * (1+Вводные!P131) -> 1.1940523 | Q114: =P114 * (1+Вводные!Q131) -> 1.2298739 | ... BJ114: =BI114 * (1+Вводные!BJ131) -> 4.6508859
D115: =Вводные!$D$132 -> Темп роста Долг 2 млн | E115: % | I115: 1 | J115: =I115 * (1+Вводные!J132) -> 1 | K115: =J115 * (1+Вводные!K132) -> 1 | L115: =K115 * (1+Вводные!L132) -> 1 | M115: =L115 * (1+Вводные!M132) -> 1 | N115: =M115 * (1+Вводные!N132) -> 1 | O115: =N115 * (1+Вводные!O132) -> 1 | P115: =O115 * (1+Вводные!P132) -> 1 | Q115: =P115 * (1+Вводные!Q132) -> 1 | ... BJ115: =BI115 * (1+Вводные!BJ132) -> 1
...

Sheet Цели
D3: =Вводные!D3 -> Год | J3: =Вводные!J3 -> 2024 | K3: =Вводные!K3 -> 2025 | L3: =Вводные!L3 -> 2026 | M3: =Вводные!M3 -> 2027 | N3: =Вводные!N3 -> 2028 | O3: =Вводные!O3 -> 2029 | P3: =Вводные!P3 -> 2030 | Q3: =Вводные!Q3 -> 2031 | ... BJ3: =Вводные!BJ3 -> 2076
D4: =Вводные!D4 -> Возраст | J4: =Вводные!J4 -> 31 | K4: =Вводные!K4 -> 32 | L4: =Вводные!L4 -> 33 | M4: =Вводные!M4 -> 34 | N4: =Вводные!N4 -> 35 | O4: =Вводные!O4 -> 36 | P4: =Вводные!P4 -> 37 | Q4: =Вводные!Q4 -> 38 | ... BJ4: =Вводные!BJ4 -> 83
D5: =Вводные!D5 -> № периода | J5: =Вводные!J5 -> 1 | K5: =Вводные!K5 -> 2 | L5: =Вводные!L5 -> 3 | M5: =Вводные!M5 -> 4 | N5: =Вводные!N5 -> 5 | O5: =Вводные!O5 -> 6 | P5: =Вводные!P5 -> 7 | Q5: =Вводные!Q5 -> 8 | ... BJ5: =Вводные!BJ5 -> 53
B8: =MAX( $B5:B$7 ) + 1 -> 1 | D8: Флаги
C10: =MAX( $B$7:C9 ) + 0.1 -> 1.1 | D10: Флаги понесения расходов
D12: Ежемесячные расходы на цели
D13: =Вводные!$D$180 -> Ежемесячный расход на цели 1 | E13: флаг | J13: =IF( AND(J$3 >= Вводные!$F232, J$3 <= Вводные!$G232), 1, 0) -> 1 | K13: =IF( AND(K$3 >= Вводные!$F232, K$3 <= Вводные!$G232), 1, 0) -> 1 | L13: =IF( AND(L$3 >= Вводные!$F232, L$3 <= Вводные!$G232), 1, 0) -> 1 | M13: =IF( AND(M$3 >= Вводные!$F232, M$3 <= Вводные!$G232), 1, 0) -> 1 | N13: =IF( AND(N$3 >= Вводные!$F232, N$3 <= Вводные!$G232), 1, 0) -> 1 | O13: =IF( AND(O$3 >= Вводные!$F232, O$3 <= Вводные!$G232), 1, 0) -> 1 | P13: =IF( AND(P$3 >= Вводные!$F232, P$3 <= Вводные!$G232), 1, 0) -> 1 | Q13: =IF( AND(Q$3 >= Вводные!$F232, Q$3 <= Вводные!$G232), 1, 0) -> 1 | ... BJ13: =IF( AND(BJ$3 >= Вводные!$F232, BJ$3 <= Вводные!$G232), 1, 0) -> 0
D14: =Вводные!$D$181 -> Ежемесячный расход на цели 2 | E14: флаг | J14: =IF( AND(J$3 >= Вводные!$F233, J$3 <= Вводные!$G233), 1, 0) -> 1 | K14: =IF( AND(K$3 >= Вводные!$F233, K$3 <= Вводные!$G233), 1, 0) -> 1 | L14: =IF( AND(L$3 >= Вводные!$F233, L$3 <= Вводные!$G233), 1, 0) -> 1 | M14: =IF( AND(M$3 >= Вводные!$F233, M$3 <= Вводные!$G233), 1, 0) -> 1 | N14: =IF( AND(N$3 >= Вводные!$F233, N$3 <= Вводные!$G233), 1, 0) -> 1 | O14: =IF( AND(O$3 >= Вводные!$F233, O$3 <= Вводные!$G233), 1, 0) -> 1 | P14: =IF( AND(P$3 >= Вводные!$F233, P$3 <= Вводные!$G233), 1, 0) -> 1 | Q14: =IF( AND(Q$3 >= Вводные!$F233, Q$3 <= Вводные!$G233), 1, 0) -> 1 | ... BJ14: =IF( AND(BJ$3 >= Вводные!$F233, BJ$3 <= Вводные!$G233), 1, 0) -> 0
D15: =Вводные!$D$182 -> Ежемесячный расход на цели 3 | E15: флаг | J15: =IF( AND(J$3 >= Вводные!$F234, J$3 <= Вводные!$G234), 1, 0) -> 1 | K15: =IF( AND(K$3 >= Вводные!$F234, K$3 <= Вводные!$G234), 1, 0) -> 1 | L15: =IF( AND(L$3 >= Вводные!$F234, L$3 <= Вводные!$G234), 1, 0) -> 1 | M15: =IF( AND(M$3 >= Вводные!$F234, M$3 <= Вводные!$G234), 1, 0) -> 1 | N15: =IF( AND(N$3 >= Вводные!$F234, N$3 <= Вводные!$G234), 1, 0) -> 1 | O15: =IF( AND(O$3 >= Вводные!$F234, O$3 <= Вводные!$G234), 1, 0) -> 1 | P15: =IF( AND(P$3 >= Вводные!$F234, P$3 <= Вводные!$G234), 1, 0) -> 1 | Q15: =IF( AND(Q$3 >= Вводные!$F234, Q$3 <= Вводные!$G234), 1, 0) -> 1 | ... BJ15: =IF( AND(BJ$3 >= Вводные!$F234, BJ$3 <= Вводные!$G234), 1, 0) -> 0
D16: =Вводные!$D$183 -> Ежемесячный расход на цели 4 | E16: флаг | J16: =IF( AND(J$3 >= Вводные!$F235, J$3 <= Вводные!$G235), 1, 0) -> 1 | K16: =IF( AND(K$3 >= Вводные!$F235, K$3 <= Вводные!$G235), 1, 0) -> 1 | L16: =IF( AND(L$3 >= Вводные!$F235, L$3 <= Вводные!$G235), 1, 0) -> 1 | M16: =IF( AND(M$3 >= Вводные!$F235, M$3 <= Вводные!$G235), 1, 0) -> 1 | N16: =IF( AND(N$3 >= Вводные!$F235, N$3 <= Вводные!$G235), 1, 0) -> 1 | O16: =IF( AND(O$3 >= Вводные!$F235, O$3 <= Вводные!$G235), 1, 0) -> 1 | P16: =IF( AND(P$3 >= Вводные!$F235, P$3 <= Вводные!$G235), 1, 0) -> 1 | Q16: =IF( AND(Q$3 >= Вводные!$F235, Q$3 <= Вводные!$G235), 1, 0) -> 1 | ... BJ16: =IF( AND(BJ$3 >= Вводные!$F235, BJ$3 <= Вводные!$G235), 1, 0) -> 0
D17: =Вводные!$D$184 -> Ежемесячный расход на цели 5 | E17: флаг | J17: =IF( AND(J$3 >= Вводные!$F236, J$3 <= Вводные!$G236), 1, 0) -> 1 | K17: =IF( AND(K$3 >= Вводные!$F236, K$3 <= Вводные!$G236), 1, 0) -> 1 | L17: =IF( AND(L$3 >= Вводные!$F236, L$3 <= Вводные!$G236), 1, 0) -> 1 | M17: =IF( AND(M$3 >= Вводные!$F236, M$3 <= Вводные!$G236), 1, 0) -> 1 | N17: =IF( AND(N$3 >= Вводные!$F236, N$3 <= Вводные!$G236), 1, 0) -> 1 | O17: =IF( AND(O$3 >= Вводные!$F236, O$3 <= Вводные!$G236), 1, 0) -> 1 | P17: =IF( AND(P$3 >= Вводные!$F236, P$3 <= Вводные!$G236), 1, 0) -> 1 | Q17: =IF( AND(Q$3 >= Вводные!$F236, Q$3 <= Вводные!$G236), 1, 0) -> 1 | ... BJ17: =IF( AND(BJ$3 >= Вводные!$F236, BJ$3 <= Вводные!$G236), 1, 0) -> 0
D18: =Вводные!$D$185 -> Ежемесячный расход на цели 6 | E18: флаг | J18: =IF( AND(J$3 >= Вводные!$F237, J$3 <= Вводные!$G237), 1, 0) -> 1 | K18: =IF( AND(K$3 >= Вводные!$F237, K$3 <= Вводные!$G237), 1, 0) -> 1 | L18: =IF( AND(L$3 >= Вводные!$F237, L$3 <= Вводные!$G237), 1, 0) -> 1 | M18: =IF( AND(M$3 >= Вводные!$F237, M$3 <= Вводные!$G237), 1, 0) -> 1 | N18: =IF( AND(N$3 >= Вводные!$F237, N$3 <= Вводные!$G237), 1, 0) -> 1 | O18: =IF( AND(O$3 >= Вводные!$F237, O$3 <= Вводные!$G237), 1, 0) -> 1 | P18: =IF( AND(P$3 >= Вводные!$F237, P$3 <= Вводные!$G237), 1, 0) -> 1 | Q18: =IF( AND(Q$3 >= Вводные!$F237, Q$3 <= Вводные!$G237), 1, 0) -> 1 | ... BJ18: =IF( AND(BJ$3 >= Вводные!$F237, BJ$3 <= Вводные!$G237), 1, 0) -> 0
D19: =Вводные!$D$186 -> Ежемесячный расход на цели 7 | E19: флаг | J19: =IF( AND(J$3 >= Вводные!$F238, J$3 <= Вводные!$G238), 1, 0) -> 1 | K19: =IF( AND(K$3 >= Вводные!$F238, K$3 <= Вводные!$G238), 1, 0) -> 1 | L19: =IF( AND(L$3 >= Вводные!$F238, L$3 <= Вводные!$G238), 1, 0) -> 1 | M19: =IF( AND(M$3 >= Вводные!$F238, M$3 <= Вводные!$G238), 1, 0) -> 1 | N19: =IF( AND(N$3 >= Вводные!$F238, N$3 <= Вводные!$G238), 1, 0) -> 1 | O19: =IF( AND(O$3 >= Вводные!$F238, O$3 <= Вводные!$G238), 1, 0) -> 1 | P19: =IF( AND(P$3 >= Вводные!$F238, P$3 <= Вводные!$G238), 1, 0) -> 1 | Q19: =IF( AND(Q$3 >= Вводные!$F238, Q$3 <= Вводные!$G238), 1, 0) -> 1 | ... BJ19: =IF( AND(BJ$3 >= Вводные!$F238, BJ$3 <= Вводные!$G238), 1, 0) -> 0
D20: =Вводные!$D$187 -> Ежемесячный расход на цели 8 | E20: флаг | J20: =IF( AND(J$3 >= Вводные!$F239, J$3 <= Вводные!$G239), 1, 0) -> 1 | K20: =IF( AND(K$3 >= Вводные!$F239, K$3 <= Вводные!$G239), 1, 0) -> 1 | L20: =IF( AND(L$3 >= Вводные!$F239, L$3 <= Вводные!$G239), 1, 0) -> 1 | M20: =IF( AND(M$3 >= Вводные!$F239, M$3 <= Вводные!$G239), 1, 0) -> 1 | N20: =IF( AND(N$3 >= Вводные!$F239, N$3 <= Вводные!$G239), 1, 0) -> 1 | O20: =IF( AND(O$3 >= Вводные!$F239, O$3 <= Вводные!$G239), 1, 0) -> 1 | P20: =IF( AND(P$3 >= Вводные!$F239, P$3 <= Вводные!$G239), 1, 0) -> 1 | Q20: =IF( AND(Q$3 >= Вводные!$F239, Q$3 <= Вводные!$G239), 1, 0) -> 1 | ... BJ20: =IF( AND(BJ$3 >= Вводные!$F239, BJ$3 <= Вводные!$G239), 1, 0) -> 0
D21: =Вводные!$D$188 -> Ежемесячный расход на цели 9 | E21: флаг | J21: =IF( AND(J$3 >= Вводные!$F240, J$3 <= Вводные!$G240), 1, 0) -> 1 | K21: =IF( AND(K$3 >= Вводные!$F240, K$3 <= Вводные!$G240), 1, 0) -> 1 | L21: =IF( AND(L$3 >= Вводные!$F240, L$3 <= Вводные!$G240), 1, 0) -> 1 | M21: =IF( AND(M$3 >= Вводные!$F240, M$3 <= Вводные!$G240), 1, 0) -> 1 | N21: =IF( AND(N$3 >= Вводные!$F240, N$3 <= Вводные!$G240), 1, 0) -> 1 | O21: =IF( AND(O$3 >= Вводные!$F240, O$3 <= Вводные!$G240), 1, 0) -> 1 | P21: =IF( AND(P$3 >= Вводные!$F240, P$3 <= Вводные!$G240), 1, 0) -> 1 | Q21: =IF( AND(Q$3 >= Вводные!$F240, Q$3 <= Вводные!$G240), 1, 0) -> 1 | ... BJ21: =IF( AND(BJ$3 >= Вводные!$F240, BJ$3 <= Вводные!$G240), 1, 0) -> 0
D22: =Вводные!$D$189 -> Ежемесячный расход на цели 10 | E22: флаг | J22: =IF( AND(J$3 >= Вводные!$F241, J$3 <= Вводные!$G241), 1, 0) -> 1 | K22: =IF( AND(K$3 >= Вводные!$F241, K$3 <= Вводные!$G241), 1, 0) -> 1 | L22: =IF( AND(L$3 >= Вводные!$F241, L$3 <= Вводные!$G241), 1, 0) -> 1 | M22: =IF( AND(M$3 >= Вводные!$F241, M$3 <= Вводные!$G241), 1, 0) -> 1 | N22: =IF( AND(N$3 >= Вводные!$F241, N$3 <= Вводные!$G241), 1, 0) -> 1 | O22: =IF( AND(O$3 >= Вводные!$F241, O$3 <= Вводные!$G241), 1, 0) -> 1 | P22: =IF( AND(P$3 >= Вводные!$F241, P$3 <= Вводные!$G241), 1, 0) -> 1 | Q22: =IF( AND(Q$3 >= Вводные!$F241, Q$3 <= Вводные!$G241), 1, 0) -> 1 | ... BJ22: =IF( AND(BJ$3 >= Вводные!$F241, BJ$3 <= Вводные!$G241), 1, 0) -> 0
D24: Ежегодные расходы на цели
D25: =Вводные!$D$180 -> Ежемесячный расход на цели 1 | E25: флаг | J25: =IF( AND(J$3 >= Вводные!$F244, J$3 <= Вводные!$G244), 1, 0) -> 1 | K25: =IF( AND(K$3 >= Вводные!$F244, K$3 <= Вводные!$G244), 1, 0) -> 1 | L25: =IF( AND(L$3 >= Вводные!$F244, L$3 <= Вводные!$G244), 1, 0) -> 1 | M25: =IF( AND(M$3 >= Вводные!$F244, M$3 <= Вводные!$G244), 1, 0) -> 1 | N25: =IF( AND(N$3 >= Вводные!$F244, N$3 <= Вводные!$G244), 1, 0) -> 1 | O25: =IF( AND(O$3 >= Вводные!$F244, O$3 <= Вводные!$G244), 1, 0) -> 1 | P25: =IF( AND(P$3 >= Вводные!$F244, P$3 <= Вводные!$G244), 1, 0) -> 1 | Q25: =IF( AND(Q$3 >= Вводные!$F244, Q$3 <= Вводные!$G244), 1, 0) -> 1 | ... BJ25: =IF( AND(BJ$3 >= Вводные!$F244, BJ$3 <= Вводные!$G244), 1, 0) -> 0
D26: =Вводные!$D$181 -> Ежемесячный расход на цели 2 | E26: флаг | J26: =IF( AND(J$3 >= Вводные!$F245, J$3 <= Вводные!$G245), 1, 0) -> 1 | K26: =IF( AND(K$3 >= Вводные!$F245, K$3 <= Вводные!$G245), 1, 0) -> 1 | L26: =IF( AND(L$3 >= Вводные!$F245, L$3 <= Вводные!$G245), 1, 0) -> 1 | M26: =IF( AND(M$3 >= Вводные!$F245, M$3 <= Вводные!$G245), 1, 0) -> 1 | N26: =IF( AND(N$3 >= Вводные!$F245, N$3 <= Вводные!$G245), 1, 0) -> 1 | O26: =IF( AND(O$3 >= Вводные!$F245, O$3 <= Вводные!$G245), 1, 0) -> 1 | P26: =IF( AND(P$3 >= Вводные!$F245, P$3 <= Вводные!$G245), 1, 0) -> 1 | Q26: =IF( AND(Q$3 >= Вводные!$F245, Q$3 <= Вводные!$G245), 1, 0) -> 1 | ... BJ26: =IF( AND(BJ$3 >= Вводные!$F245, BJ$3 <= Вводные!$G245), 1, 0) -> 0
D27: =Вводные!$D$182 -> Ежемесячный расход на цели 3 | E27: флаг | J27: =IF( AND(J$3 >= Вводные!$F246, J$3 <= Вводные!$G246), 1, 0) -> 1 | K27: =IF( AND(K$3 >= Вводные!$F246, K$3 <= Вводные!$G246), 1, 0) -> 1 | L27: =IF( AND(L$3 >= Вводные!$F246, L$3 <= Вводные!$G246), 1, 0) -> 1 | M27: =IF( AND(M$3 >= Вводные!$F246, M$3 <= Вводные!$G246), 1, 0) -> 1 | N27: =IF( AND(N$3 >= Вводные!$F246, N$3 <= Вводные!$G246), 1, 0) -> 1 | O27: =IF( AND(O$3 >= Вводные!$F246, O$3 <= Вводные!$G246), 1, 0) -> 1 | P27: =IF( AND(P$3 >= Вводные!$F246, P$3 <= Вводные!$G246), 1, 0) -> 1 | Q27: =IF( AND(Q$3 >= Вводные!$F246, Q$3 <= Вводные!$G246), 1, 0) -> 1 | ... BJ27: =IF( AND(BJ$3 >= Вводные!$F246, BJ$3 <= Вводные!$G246), 1, 0) -> 0
D28: =Вводные!$D$183 -> Ежемесячный расход на цели 4 | E28: флаг | J28: =IF( AND(J$3 >= Вводные!$F247, J$3 <= Вводные!$G247), 1, 0) -> 1 | K28: =IF( AND(K$3 >= Вводные!$F247, K$3 <= Вводные!$G247), 1, 0) -> 1 | L28: =IF( AND(L$3 >= Вводные!$F247, L$3 <= Вводные!$G247), 1, 0) -> 1 | M28: =IF( AND(M$3 >= Вводные!$F247, M$3 <= Вводные!$G247), 1, 0) -> 1 | N28: =IF( AND(N$3 >= Вводные!$F247, N$3 <= Вводные!$G247), 1, 0) -> 1 | O28: =IF( AND(O$3 >= Вводные!$F247, O$3 <= Вводные!$G247), 1, 0) -> 1 | P28: =IF( AND(P$3 >= Вводные!$F247, P$3 <= Вводные!$G247), 1, 0) -> 1 | Q28: =IF( AND(Q$3 >= Вводные!$F247, Q$3 <= Вводные!$G247), 1, 0) -> 1 | ... BJ28: =IF( AND(BJ$3 >= Вводные!$F247, BJ$3 <= Вводные!$G247), 1, 0) -> 0
D29: =Вводные!$D$184 -> Ежемесячный расход на цели 5 | E29: флаг | J29: =IF( AND(J$3 >= Вводные!$F248, J$3 <= Вводные!$G248), 1, 0) -> 1 | K29: =IF( AND(K$3 >= Вводные!$F248, K$3 <= Вводные!$G248), 1, 0) -> 1 | L29: =IF( AND(L$3 >= Вводные!$F248, L$3 <= Вводные!$G248), 1, 0) -> 1 | M29: =IF( AND(M$3 >= Вводные!$F248, M$3 <= Вводные!$G248), 1, 0) -> 1 | N29: =IF( AND(N$3 >= Вводные!$F248, N$3 <= Вводные!$G248), 1, 0) -> 1 | O29: =IF( AND(O$3 >= Вводные!$F248, O$3 <= Вводные!$G248), 1, 0) -> 1 | P29: =IF( AND(P$3 >= Вводные!$F248, P$3 <= Вводные!$G248), 1, 0) -> 1 | Q29: =IF( AND(Q$3 >= Вводные!$F248, Q$3 <= Вводные!$G248), 1, 0) -> 1 | ... BJ29: =IF( AND(BJ$3 >= Вводные!$F248, BJ$3 <= Вводные!$G248), 1, 0) -> 0
D30: =Вводные!$D$185 -> Ежемесячный расход на цели 6 | E30: флаг | J30: =IF( AND(J$3 >= Вводные!$F249, J$3 <= Вводные!$G249), 1, 0) -> 1 | K30: =IF( AND(K$3 >= Вводные!$F249, K$3 <= Вводные!$G249), 1, 0) -> 1 | L30: =IF( AND(L$3 >= Вводные!$F249, L$3 <= Вводные!$G249), 1, 0) -> 1 | M30: =IF( AND(M$3 >= Вводные!$F249, M$3 <= Вводные!$G249), 1, 0) -> 1 | N30: =IF( AND(N$3 >= Вводные!$F249, N$3 <= Вводные!$G249), 1, 0) -> 1 | O30: =IF( AND(O$3 >= Вводные!$F249, O$3 <= Вводные!$G249), 1, 0) -> 1 | P30: =IF( AND(P$3 >= Вводные!$F249, P$3 <= Вводные!$G249), 1, 0) -> 1 | Q30: =IF( AND(Q$3 >= Вводные!$F249, Q$3 <= Вводные!$G249), 1, 0) -> 1 | ... BJ30: =IF( AND(BJ$3 >= Вводные!$F249, BJ$3 <= Вводные!$G249), 1, 0) -> 0
D31: =Вводные!$D$186 -> Ежемесячный расход на цели 7 | E31: флаг | J31: =IF( AND(J$3 >= Вводные!$F250, J$3 <= Вводные!$G250), 1, 0) -> 1 | K31: =IF( AND(K$3 >= Вводные!$F250, K$3 <= Вводные!$G250), 1, 0) -> 1 | L31: =IF( AND(L$3 >= Вводные!$F250, L$3 <= Вводные!$G250), 1, 0) -> 1 | M31: =IF( AND(M$3 >= Вводные!$F250, M$3 <= Вводные!$G250), 1, 0) -> 1 | N31: =IF( AND(N$3 >= Вводные!$F250, N$3 <= Вводные!$G250), 1, 0) -> 1 | O31: =IF( AND(O$3 >= Вводные!$F250, O$3 <= Вводные!$G250), 1, 0) -> 1 | P31: =IF( AND(P$3 >= Вводные!$F250, P$3 <= Вводные!$G250), 1, 0) -> 1 | Q31: =IF( AND(Q$3 >= Вводные!$F250, Q$3 <= Вводные!$G250), 1, 0) -> 1 | ... BJ31: =IF( AND(BJ$3 >= Вводные!$F250, BJ$3 <= Вводные!$G250), 1, 0) -> 0
D32: =Вводные!$D$187 -> Ежемесячный расход на цели 8 | E32: флаг | J32: =IF( AND(J$3 >= Вводные!$F251, J$3 <= Вводные!$G251), 1, 0) -> 1 | K32: =IF( AND(K$3 >= Вводные!$F251, K$3 <= Вводные!$G251), 1, 0) -> 1 | L32: =IF( AND(L$3 >= Вводные!$F251, L$3 <= Вводные!$G251), 1, 0) -> 1 | M32: =IF( AND(M$3 >= Вводные!$F251, M$3 <= Вводные!$G251), 1, 0) -> 1 | N32: =IF( AND(N$3 >= Вводные!$F251, N$3 <= Вводные!$G251), 1, 0) -> 1 | O32: =IF( AND(O$3 >= Вводные!$F251, O$3 <= Вводные!$G251), 1, 0) -> 1 | P32: =IF( AND(P$3 >= Вводные!$F251, P$3 <= Вводные!$G251), 1, 0) -> 1 | Q32: =IF( AND(Q$3 >= Вводные!$F251, Q$3 <= Вводные!$G251), 1, 0) -> 1 | ... BJ32: =IF( AND(BJ$3 >= Вводные!$F251, BJ$3 <= Вводные!$G251), 1, 0) -> 0
D33: =Вводные!$D$188 -> Ежемесячный расход на цели 9 | E33: флаг | J33: =IF( AND(J$3 >= Вводные!$F252, J$3 <= Вводные!$G252), 1, 0) -> 1 | K33: =IF( AND(K$3 >= Вводные!$F252, K$3 <= Вводные!$G252), 1, 0) -> 1 | L33: =IF( AND(L$3 >= Вводные!$F252, L$3 <= Вводные!$G252), 1, 0) -> 1 | M33: =IF( AND(M$3 >= Вводные!$F252, M$3 <= Вводные!$G252), 1, 0) -> 1 | N33: =IF( AND(N$3 >= Вводные!$F252, N$3 <= Вводные!$G252), 1, 0) -> 1 | O33: =IF( AND(O$3 >= Вводные!$F252, O$3 <= Вводные!$G252), 1, 0) -> 1 | P33: =IF( AND(P$3 >= Вводные!$F252, P$3 <= Вводные!$G252), 1, 0) -> 1 | Q33: =IF( AND(Q$3 >= Вводные!$F252, Q$3 <= Вводные!$G252), 1, 0) -> 1 | ... BJ33: =IF( AND(BJ$3 >= Вводные!$F252, BJ$3 <= Вводные!$G252), 1, 0) -> 0
D34: =Вводные!$D$189 -> Ежемесячный расход на цели 10 | E34: флаг | J34: =IF( AND(J$3 >= Вводные!$F253, J$3 <= Вводные!$G253), 1, 0) -> 1 | K34: =IF( AND(K$3 >= Вводные!$F253, K$3 <= Вводные!$G253), 1, 0) -> 1 | L34: =IF( AND(L$3 >= Вводные!$F253, L$3 <= Вводные!$G253), 1, 0) -> 1 | M34: =IF( AND(M$3 >= Вводные!$F253, M$3 <= Вводные!$G253), 1, 0) -> 1 | N34: =IF( AND(N$3 >= Вводные!$F253, N$3 <= Вводные!$G253), 1, 0) -> 1 | O34: =IF( AND(O$3 >= Вводные!$F253, O$3 <= Вводные!$G253), 1, 0) -> 1 | P34: =IF( AND(P$3 >= Вводные!$F253, P$3 <= Вводные!$G253), 1, 0) -> 1 | Q34: =IF( AND(Q$3 >= Вводные!$F253, Q$3 <= Вводные!$G253), 1, 0) -> 1 | ... BJ34: =IF( AND(BJ$3 >= Вводные!$F253, BJ$3 <= Вводные!$G253), 1, 0) -> 0
B36: =MAX( $B$7:B33 ) + 1 -> 2 | D36: Расходы на цели
D38: Всего расходы на цели | E38: USD / год | I38: =SUM(I42,I68) -> -20000 | J38: =SUM(J42,J68) -> -20000 | K38: =SUM(K42,K68) -> -20600 | L38: =SUM(L42,L68) -> -21218 | M38: =SUM(M42,M68) -> -21854.54 | N38: =SUM(N42,N68) -> -22510.176 | O38: =SUM(O42,O68) -> -23185.481 | P38: =SUM(P42,P68) -> -23881.046 | ... BJ38: =SUM(BJ42,BJ68) -> 0
C40: =MAX( $B$36:C37 ) + 0.1 -> 2.1 | D40: Ежемесячные расходы на цели
D42: Ежемесячные расходы на цели | E42: USD / год | I42: =SUM(I43:I52) -> 0 | J42: =SUM(J43:J52) -> 0 | K42: =SUM(K43:K52) -> 0 | L42: =SUM(L43:L52) -> 0 | M42: =SUM(M43:M52) -> 0 | N42: =SUM(N43:N52) -> 0 | O42: =SUM(O43:O52) -> 0 | P42: =SUM(P43:P52) -> 0 | ... BJ42: =SUM(BJ43:BJ52) -> 0
D43: =Вводные!$D$180 -> Ежемесячный расход на цели 1 | E43: USD / год | I43: =Вводные!F180 * Вводные!$F$12 -> 0 | J43: =$I43 * J55 * J13 -> 0 | K43: =$I43 * K55 * K13 -> 0 | L43: =$I43 * L55 * L13 -> 0 | M43: =$I43 * M55 * M13 -> 0 | N43: =$I43 * N55 * N13 -> 0 | O43: =$I43 * O55 * O13 -> 0 | P43: =$I43 * P55 * P13 -> 0 | Q43: =$I43 * Q55 * Q13 -> 0 | ... BJ43: =$I43 * BJ55 * BJ13 -> 0
D44: =Вводные!$D$181 -> Ежемесячный расход на цели 2 | E44: USD / год | I44: =Вводные!F181 * Вводные!$F$12 -> 0 | J44: =$I44 * J56 * J14 -> 0 | K44: =$I44 * K56 * K14 -> 0 | L44: =$I44 * L56 * L14 -> 0 | M44: =$I44 * M56 * M14 -> 0 | N44: =$I44 * N56 * N14 -> 0 | O44: =$I44 * O56 * O14 -> 0 | P44: =$I44 * P56 * P14 -> 0 | Q44: =$I44 * Q56 * Q14 -> 0 | ... BJ44: =$I44 * BJ56 * BJ14 -> 0
D45: =Вводные!$D$182 -> Ежемесячный расход на цели 3 | E45: USD / год | I45: =Вводные!F182 * Вводные!$F$12 -> 0 | J45: =$I45 * J57 * J15 -> 0 | K45: =$I45 * K57 * K15 -> 0 | L45: =$I45 * L57 * L15 -> 0 | M45: =$I45 * M57 * M15 -> 0 | N45: =$I45 * N57 * N15 -> 0 | O45: =$I45 * O57 * O15 -> 0 | P45: =$I45 * P57 * P15 -> 0 | Q45: =$I45 * Q57 * Q15 -> 0 | ... BJ45: =$I45 * BJ57 * BJ15 -> 0
D46: =Вводные!$D$183 -> Ежемесячный расход на цели 4 | E46: USD / год | I46: =Вводные!F183 * Вводные!$F$12 -> 0 | J46: =$I46 * J58 * J16 -> 0 | K46: =$I46 * K58 * K16 -> 0 | L46: =$I46 * L58 * L16 -> 0 | M46: =$I46 * M58 * M16 -> 0 | N46: =$I46 * N58 * N16 -> 0 | O46: =$I46 * O58 * O16 -> 0 | P46: =$I46 * P58 * P16 -> 0 | Q46: =$I46 * Q58 * Q16 -> 0 | ... BJ46: =$I46 * BJ58 * BJ16 -> 0
D47: =Вводные!$D$184 -> Ежемесячный расход на цели 5 | E47: USD / год | I47: =Вводные!F184 * Вводные!$F$12 -> 0 | J47: =$I47 * J59 * J17 -> 0 | K47: =$I47 * K59 * K17 -> 0 | L47: =$I47 * L59 * L17 -> 0 | M47: =$I47 * M59 * M17 -> 0 | N47: =$I47 * N59 * N17 -> 0 | O47: =$I47 * O59 * O17 -> 0 | P47: =$I47 * P59 * P17 -> 0 | Q47: =$I47 * Q59 * Q17 -> 0 | ... BJ47: =$I47 * BJ59 * BJ17 -> 0
D48: =Вводные!$D$185 -> Ежемесячный расход на цели 6 | E48: USD / год | I48: =Вводные!F185 * Вводные!$F$12 -> 0 | J48: =$I48 * J60 * J18 -> 0 | K48: =$I48 * K60 * K18 -> 0 | L48: =$I48 * L60 * L18 -> 0 | M48: =$I48 * M60 * M18 -> 0 | N48: =$I48 * N60 * N18 -> 0 | O48: =$I48 * O60 * O18 -> 0 | P48: =$I48 * P60 * P18 -> 0 | Q48: =$I48 * Q60 * Q18 -> 0 | ... BJ48: =$I48 * BJ60 * BJ18 -> 0
D49: =Вводные!$D$186 -> Ежемесячный расход на цели 7 | E49: USD / год | I49: =Вводные!F186 * Вводные!$F$12 -> 0 | J49: =$I49 * J61 * J19 -> 0 | K49: =$I49 * K61 * K19 -> 0 | L49: =$I49 * L61 * L19 -> 0 | M49: =$I49 * M61 * M19 -> 0 | N49: =$I49 * N61 * N19 -> 0 | O49: =$I49 * O61 * O19 -> 0 | P49: =$I49 * P61 * P19 -> 0 | Q49: =$I49 * Q61 * Q19 -> 0 | ... BJ49: =$I49 * BJ61 * BJ19 -> 0
D50: =Вводные!$D$187 -> Ежемесячный расход на цели 8 | E50: USD / год | I50: =Вводные!F187 * Вводные!$F$12 -> 0 | J50: =$I50 * J62 * J20 -> 0 | K50: =$I50 * K62 * K20 -> 0 | L50: =$I50 * L62 * L20 -> 0 | M50: =$I50 * M62 * M20 -> 0 | N50: =$I50 * N62 * N20 -> 0 | O50: =$I50 * O62 * O20 -> 0 | P50: =$I50 * P62 * P20 -> 0 | Q50: =$I50 * Q62 * Q20 -> 0 | ... BJ50: =$I50 * BJ62 * BJ20 -> 0
D51: =Вводные!$D$188 -> Ежемесячный расход на цели 9 | E51: USD / год | I51: =Вводные!F188 * Вводные!$F$12 -> 0 | J51: =$I51 * J63 * J21 -> 0 | K51: =$I51 * K63 * K21 -> 0 | L51: =$I51 * L63 * L21 -> 0 | M51: =$I51 * M63 * M21 -> 0 | N51: =$I51 * N63 * N21 -> 0 | O51: =$I51 * O63 * O21 -> 0 | P51: =$I51 * P63 * P21 -> 0 | Q51: =$I51 * Q63 * Q21 -> 0 | ... BJ51: =$I51 * BJ63 * BJ21 -> 0
D52: =Вводные!$D$189 -> Ежемесячный расход на цели 10 | E52: USD / год | I52: =Вводные!F189 * Вводные!$F$12 -> 0 | J52: =$I52 * J64 * J22 -> 0 | K52: =$I52 * K64 * K22 -> 0 | L52: =$I52 * L64 * L22 -> 0 | M52: =$I52 * M64 * M22 -> 0 | N52: =$I52 * N64 * N22 -> 0 | O52: =$I52 * O64 * O22 -> 0 | P52: =$I52 * P64 * P22 -> 0 | Q52: =$I52 * Q64 * Q22 -> 0 | ... BJ52: =$I52 * BJ64 * BJ22 -> 0
D54: Темп роста ежемесячных расходов
D55: =Вводные!$D$192 -> Темп роста Ежемесячный расход на цели 1 | E55: % | I55: 1 | J55: =I55*(1+Вводные!J192) -> 1 | K55: =J55*(1+Вводные!K192) -> 1.03 | L55: =K55*(1+Вводные!L192) -> 1.0609 | M55: =L55*(1+Вводные!M192) -> 1.092727 | N55: =M55*(1+Вводные!N192) -> 1.1255088 | O55: =N55*(1+Вводные!O192) -> 1.1592741 | P55: =O55*(1+Вводные!P192) -> 1.1940523 | Q55: =P55*(1+Вводные!Q192) -> 1.2298739 | ... BJ55: =BI55*(1+Вводные!BJ192) -> 4.6508859
D56: =Вводные!$D$193 -> Темп роста Ежемесячный расход на цели 2 | E56: % | I56: 1 | J56: =I56*(1+Вводные!J193) -> 1 | K56: =J56*(1+Вводные!K193) -> 1.03 | L56: =K56*(1+Вводные!L193) -> 1.0609 | M56: =L56*(1+Вводные!M193) -> 1.092727 | N56: =M56*(1+Вводные!N193) -> 1.1255088 | O56: =N56*(1+Вводные!O193) -> 1.1592741 | P56: =O56*(1+Вводные!P193) -> 1.1940523 | Q56: =P56*(1+Вводные!Q193) -> 1.2298739 | ... BJ56: =BI56*(1+Вводные!BJ193) -> 4.6508859
D57: =Вводные!$D$194 -> Темп роста Ежемесячный расход на цели 3 | E57: % | I57: 1 | J57: =I57*(1+Вводные!J194) -> 1 | K57: =J57*(1+Вводные!K194) -> 1.03 | L57: =K57*(1+Вводные!L194) -> 1.0609 | M57: =L57*(1+Вводные!M194) -> 1.092727 | N57: =M57*(1+Вводные!N194) -> 1.1255088 | O57: =N57*(1+Вводные!O194) -> 1.1592741 | P57: =O57*(1+Вводные!P194) -> 1.1940523 | Q57: =P57*(1+Вводные!Q194) -> 1.2298739 | ... BJ57: =BI57*(1+Вводные!BJ194) -> 4.6508859
D58: =Вводные!$D$195 -> Темп роста Ежемесячный расход на цели 4 | E58: % | I58: 1 | J58: =I58*(1+Вводные!J195) -> 1 | K58: =J58*(1+Вводные!K195) -> 1.03 | L58: =K58*(1+Вводные!L195) -> 1.0609 | M58: =L58*(1+Вводные!M195) -> 1.092727 | N58: =M58*(1+Вводные!N195) -> 1.1255088 | O58: =N58*(1+Вводные!O195) -> 1.1592741 | P58: =O58*(1+Вводные!P195) -> 1.1940523 | Q58: =P58*(1+Вводные!Q195) -> 1.2298739 | ... BJ58: =BI58*(1+Вводные!BJ195) -> 4.6508859
D59: =Вводные!$D$196 -> Темп роста Ежемесячный расход на цели 5 | E59: % | I59: 1 | J59: =I59*(1+Вводные!J196) -> 1 | K59: =J59*(1+Вводные!K196) -> 1.03 | L59: =K59*(1+Вводные!L196) -> 1.0609 | M59: =L59*(1+Вводные!M196) -> 1.092727 | N59: =M59*(1+Вводные!N196) -> 1.1255088 | O59: =N59*(1+Вводные!O196) -> 1.1592741 | P59: =O59*(1+Вводные!P196) -> 1.1940523 | Q59: =P59*(1+Вводные!Q196) -> 1.2298739 | ... BJ59: =BI59*(1+Вводные!BJ196) -> 4.6508859
D60: =Вводные!$D$197 -> Темп роста Ежемесячный расход на цели 6 | E60: % | I60: 1 | J60: =I60*(1+Вводные!J197) -> 1 | K60: =J60*(1+Вводные!K197) -> 1.03 | L60: =K60*(1+Вводные!L197) -> 1.0609 | M60: =L60*(1+Вводные!M197) -> 1.092727 | N60: =M60*(1+Вводные!N197) -> 1.1255088 | O60: =N60*(1+Вводные!O197) -> 1.1592741 | P60: =O60*(1+Вводные!P197) -> 1.1940523 | Q60: =P60*(1+Вводные!Q197) -> 1.2298739 | ... BJ60: =BI60*(1+Вводные!BJ197) -> 4.6508859
D61: =Вводные!$D$198 -> Темп роста Ежемесячный расход на цели 7 | E61: % | I61: 1 | J61: =I61*(1+Вводные!J198) -> 1 | K61: =J61*(1+Вводные!K198) -> 1.03 | L61: =K61*(1+Вводные!L198) -> 1.0609 | M61: =L61*(1+Вводные!M198) -> 1.092727 | N61: =M61*(1+Вводные!N198) -> 1.1255088 | O61: =N61*(1+Вводные!O198) -> 1.1592741 | P61: =O61*(1+Вводные!P198) -> 1.1940523 | Q61: =P61*(1+Вводные!Q198) -> 1.2298739 | ... BJ61: =BI61*(1+Вводные!BJ198) -> 4.6508859
D62: =Вводные!$D$199 -> Темп роста Ежемесячный расход на цели 8 | E62: % | I62: 1 | J62: =I62*(1+Вводные!J199) -> 1 | K62: =J62*(1+Вводные!K199) -> 1.03 | L62: =K62*(1+Вводные!L199) -> 1.0609 | M62: =L62*(1+Вводные!M199) -> 1.092727 | N62: =M62*(1+Вводные!N199) -> 1.1255088 | O62: =N62*(1+Вводные!O199) -> 1.1592741 | P62: =O62*(1+Вводные!P199) -> 1.1940523 | Q62: =P62*(1+Вводные!Q199) -> 1.2298739 | ... BJ62: =BI62*(1+Вводные!BJ199) -> 4.6508859
D63: =Вводные!$D$200 -> Темп роста Ежемесячный расход на цели 9 | E63: % | I63: 1 | J63: =I63*(1+Вводные!J200) -> 1 | K63: =J63*(1+Вводные!K200) -> 1.03 | L63: =K63*(1+Вводные!L200) -> 1.0609 | M63: =L63*(1+Вводные!M200) -> 1.092727 | N63: =M63*(1+Вводные!N200) -> 1.1255088 | O63: =N63*(1+Вводные!O200) -> 1.1592741 | P63: =O63*(1+Вводные!P200) -> 1.1940523 | Q63: =P63*(1+Вводные!Q200) -> 1.2298739 | ... BJ63: =BI63*(1+Вводные!BJ200) -> 4.6508859
D64: =Вводные!$D$201 -> Темп роста Ежемесячный расход на цели 10 | E64: % | I64: 1 | J64: =I64*(1+Вводные!J201) -> 1 | K64: =J64*(1+Вводные!K201) -> 1.03 | L64: =K64*(1+Вводные!L201) -> 1.0609 | M64: =L64*(1+Вводные!M201) -> 1.092727 | N64: =M64*(1+Вводные!N201) -> 1.1255088 | O64: =N64*(1+Вводные!O201) -> 1.1592741 | P64: =O64*(1+Вводные!P201) -> 1.1940523 | Q64: =P64*(1+Вводные!Q201) -> 1.2298739 | ... BJ64: =BI64*(1+Вводные!BJ201) -> 4.6508859
C66: =MAX( $B$36:C65 ) + 0.1 -> 2.2 | D66: Ежегодные расходы на цели
D68: Ежегодные расходы на цели | E68: USD / год | I68: =SUM(I69:I78) -> -20000 | J68: =SUM(J69:J78) -> -20000 | K68: =SUM(K69:K78) -> -20600 | L68: =SUM(L69:L78) -> -21218 | M68: =SUM(M69:M78) -> -21854.54 | N68: =SUM(N69:N78) -> -22510.176 | O68: =SUM(O69:O78) -> -23185.481 | P68: =SUM(P69:P78) -> -23881.046 | ... BJ68: =SUM(BJ69:BJ78) -> 0
D69: =Вводные!$D$206 -> Отдых | E69: USD / год | I69: =Вводные!F206 -> -20000 | J69: =$I69 * J81 * J25 -> -20000 | K69: =$I69 * K81 * K25 -> -20600 | L69: =$I69 * L81 * L25 -> -21218 | M69: =$I69 * M81 * M25 -> -21854.54 | N69: =$I69 * N81 * N25 -> -22510.176 | O69: =$I69 * O81 * O25 -> -23185.481 | P69: =$I69 * P81 * P25 -> -23881.046 | Q69: =$I69 * Q81 * Q25 -> -24597.477 | ... BJ69: =$I69 * BJ81 * BJ25 -> 0
D70: =Вводные!$D$207 -> Ежегодный расход на цели 2 | E70: USD / год | I70: =Вводные!F207 -> 0 | J70: =$I70 * J82 * J26 -> 0 | K70: =$I70 * K82 * K26 -> 0 | L70: =$I70 * L82 * L26 -> 0 | M70: =$I70 * M82 * M26 -> 0 | N70: =$I70 * N82 * N26 -> 0 | O70: =$I70 * O82 * O26 -> 0 | P70: =$I70 * P82 * P26 -> 0 | Q70: =$I70 * Q82 * Q26 -> 0 | ... BJ70: =$I70 * BJ82 * BJ26 -> 0
D71: =Вводные!$D$208 -> Ежегодный расход на цели 3 | E71: USD / год | I71: =Вводные!F208 -> 0 | J71: =$I71 * J83 * J27 -> 0 | K71: =$I71 * K83 * K27 -> 0 | L71: =$I71 * L83 * L27 -> 0 | M71: =$I71 * M83 * M27 -> 0 | N71: =$I71 * N83 * N27 -> 0 | O71: =$I71 * O83 * O27 -> 0 | P71: =$I71 * P83 * P27 -> 0 | Q71: =$I71 * Q83 * Q27 -> 0 | ... BJ71: =$I71 * BJ83 * BJ27 -> 0
D72: =Вводные!$D$209 -> Ежегодный расход на цели 4 | E72: USD / год | I72: =Вводные!F209 -> 0 | J72: =$I72 * J84 * J28 -> 0 | K72: =$I72 * K84 * K28 -> 0 | L72: =$I72 * L84 * L28 -> 0 | M72: =$I72 * M84 * M28 -> 0 | N72: =$I72 * N84 * N28 -> 0 | O72: =$I72 * O84 * O28 -> 0 | P72: =$I72 * P84 * P28 -> 0 | Q72: =$I72 * Q84 * Q28 -> 0 | ... BJ72: =$I72 * BJ84 * BJ28 -> 0
D73: =Вводные!$D$210 -> Ежегодный расход на цели 5 | E73: USD / год | I73: =Вводные!F210 -> 0 | J73: =$I73 * J85 * J29 -> 0 | K73: =$I73 * K85 * K29 -> 0 | L73: =$I73 * L85 * L29 -> 0 | M73: =$I73 * M85 * M29 -> 0 | N73: =$I73 * N85 * N29 -> 0 | O73: =$I73 * O85 * O29 -> 0 | P73: =$I73 * P85 * P29 -> 0 | Q73: =$I73 * Q85 * Q29 -> 0 | ... BJ73: =$I73 * BJ85 * BJ29 -> 0
D74: =Вводные!$D$211 -> Ежегодный расход на цели 6 | E74: USD / год | I74: =Вводные!F211 -> 0 | J74: =$I74 * J86 * J30 -> 0 | K74: =$I74 * K86 * K30 -> 0 | L74: =$I74 * L86 * L30 -> 0 | M74: =$I74 * M86 * M30 -> 0 | N74: =$I74 * N86 * N30 -> 0 | O74: =$I74 * O86 * O30 -> 0 | P74: =$I74 * P86 * P30 -> 0 | Q74: =$I74 * Q86 * Q30 -> 0 | ... BJ74: =$I74 * BJ86 * BJ30 -> 0
D75: =Вводные!$D$212 -> Ежегодный расход на цели 7 | E75: USD / год | I75: =Вводные!F212 -> 0 | J75: =$I75 * J87 * J31 -> 0 | K75: =$I75 * K87 * K31 -> 0 | L75: =$I75 * L87 * L31 -> 0 | M75: =$I75 * M87 * M31 -> 0 | N75: =$I75 * N87 * N31 -> 0 | O75: =$I75 * O87 * O31 -> 0 | P75: =$I75 * P87 * P31 -> 0 | Q75: =$I75 * Q87 * Q31 -> 0 | ... BJ75: =$I75 * BJ87 * BJ31 -> 0
D76: =Вводные!$D$213 -> Ежегодный расход на цели 8 | E76: USD / год | I76: =Вводные!F213 -> 0 | J76: =$I76 * J88 * J32 -> 0 | K76: =$I76 * K88 * K32 -> 0 | L76: =$I76 * L88 * L32 -> 0 | M76: =$I76 * M88 * M32 -> 0 | N76: =$I76 * N88 * N32 -> 0 | O76: =$I76 * O88 * O32 -> 0 | P76: =$I76 * P88 * P32 -> 0 | Q76: =$I76 * Q88 * Q32 -> 0 | ... BJ76: =$I76 * BJ88 * BJ32 -> 0
D77: =Вводные!$D$214 -> Ежегодный расход на цели 9 | E77: USD / год | I77: =Вводные!F214 -> 0 | J77: =$I77 * J89 * J33 -> 0 | K77: =$I77 * K89 * K33 -> 0 | L77: =$I77 * L89 * L33 -> 0 | M77: =$I77 * M89 * M33 -> 0 | N77: =$I77 * N89 * N33 -> 0 | O77: =$I77 * O89 * O33 -> 0 | P77: =$I77 * P89 * P33 -> 0 | Q77: =$I77 * Q89 * Q33 -> 0 | ... BJ77: =$I77 * BJ89 * BJ33 -> 0
D78: =Вводные!$D$215 -> Ежегодный расход на цели 10 | E78: USD / год | I78: =Вводные!F215 -> 0 | J78: =$I78 * J90 * J34 -> 0 | K78: =$I78 * K90 * K34 -> 0 | L78: =$I78 * L90 * L34 -> 0 | M78: =$I78 * M90 * M34 -> 0 | N78: =$I78 * N90 * N34 -> 0 | O78: =$I78 * O90 * O34 -> 0 | P78: =$I78 * P90 * P34 -> 0 | Q78: =$I78 * Q90 * Q34 -> 0 | ... BJ78: =$I78 * BJ90 * BJ34 -> 0
D80: Темп роста ежегодных расходов
D81: =Вводные!$D$192 -> Темп роста Ежемесячный расход на цели 1 | E81: % | I81: 1 | J81: =I81 * (1 + Вводные!J218) -> 1 | K81: =J81 * (1 + Вводные!K218) -> 1.03 | L81: =K81 * (1 + Вводные!L218) -> 1.0609 | M81: =L81 * (1 + Вводные!M218) -> 1.092727 | N81: =M81 * (1 + Вводные!N218) -> 1.1255088 | O81: =N81 * (1 + Вводные!O218) -> 1.1592741 | P81: =O81 * (1 + Вводные!P218) -> 1.1940523 | Q81: =P81 * (1 + Вводные!Q218) -> 1.2298739 | ... BJ81: =BI81 * (1 + Вводные!BJ218) -> 4.6508859
D82: =Вводные!$D$193 -> Темп роста Ежемесячный расход на цели 2 | E82: % | I82: 1 | J82: =I82 * (1 + Вводные!J219) -> 1 | K82: =J82 * (1 + Вводные!K219) -> 1.03 | L82: =K82 * (1 + Вводные!L219) -> 1.0609 | M82: =L82 * (1 + Вводные!M219) -> 1.092727 | N82: =M82 * (1 + Вводные!N219) -> 1.1255088 | O82: =N82 * (1 + Вводные!O219) -> 1.1592741 | P82: =O82 * (1 + Вводные!P219) -> 1.1940523 | Q82: =P82 * (1 + Вводные!Q219) -> 1.2298739 | ... BJ82: =BI82 * (1 + Вводные!BJ219) -> 4.6508859
D83: =Вводные!$D$194 -> Темп роста Ежемесячный расход на цели 3 | E83: % | I83: 1 | J83: =I83 * (1 + Вводные!J220) -> 1 | K83: =J83 * (1 + Вводные!K220) -> 1.03 | L83: =K83 * (1 + Вводные!L220) -> 1.0609 | M83: =L83 * (1 + Вводные!M220) -> 1.092727 | N83: =M83 * (1 + Вводные!N220) -> 1.1255088 | O83: =N83 * (1 + Вводные!O220) -> 1.1592741 | P83: =O83 * (1 + Вводные!P220) -> 1.1940523 | Q83: =P83 * (1 + Вводные!Q220) -> 1.2298739 | ... BJ83: =BI83 * (1 + Вводные!BJ220) -> 4.6508859
D84: =Вводные!$D$195 -> Темп роста Ежемесячный расход на цели 4 | E84: % | I84: 1 | J84: =I84 * (1 + Вводные!J221) -> 1 | K84: =J84 * (1 + Вводные!K221) -> 1.03 | L84: =K84 * (1 + Вводные!L221) -> 1.0609 | M84: =L84 * (1 + Вводные!M221) -> 1.092727 | N84: =M84 * (1 + Вводные!N221) -> 1.1255088 | O84: =N84 * (1 + Вводные!O221) -> 1.1592741 | P84: =O84 * (1 + Вводные!P221) -> 1.1940523 | Q84: =P84 * (1 + Вводные!Q221) -> 1.2298739 | ... BJ84: =BI84 * (1 + Вводные!BJ221) -> 4.6508859
D85: =Вводные!$D$196 -> Темп роста Ежемесячный расход на цели 5 | E85: % | I85: 1 | J85: =I85 * (1 + Вводные!J222) -> 1 | K85: =J85 * (1 + Вводные!K222) -> 1.03 | L85: =K85 * (1 + Вводные!L222) -> 1.0609 | M85: =L85 * (1 + Вводные!M222) -> 1.092727 | N85: =M85 * (1 + Вводные!N222) -> 1.1255088 | O85: =N85 * (1 + Вводные!O222) -> 1.1592741 | P85: =O85 * (1 + Вводные!P222) -> 1.1940523 | Q85: =P85 * (1 + Вводные!Q222) -> 1.2298739 | ... BJ85: =BI85 * (1 + Вводные!BJ222) -> 4.6508859
D86: =Вводные!$D$197 -> Темп роста Ежемесячный расход на цели 6 | E86: % | I86: 1 | J86: =I86 * (1 + Вводные!J223) -> 1 | K86: =J86 * (1 + Вводные!K223) -> 1.03 | L86: =K86 * (1 + Вводные!L223) -> 1.0609 | M86: =L86 * (1 + Вводные!M223) -> 1.092727 | N86: =M86 * (1 + Вводные!N223) -> 1.1255088 | O86: =N86 * (1 + Вводные!O223) -> 1.1592741 | P86: =O86 * (1 + Вводные!P223) -> 1.1940523 | Q86: =P86 * (1 + Вводные!Q223) -> 1.2298739 | ... BJ86: =BI86 * (1 + Вводные!BJ223) -> 4.6508859
D87: =Вводные!$D$198 -> Темп роста Ежемесячный расход на цели 7 | E87: % | I87: 1 | J87: =I87 * (1 + Вводные!J224) -> 1 | K87: =J87 * (1 + Вводные!K224) -> 1.03 | L87: =K87 * (1 + Вводные!L224) -> 1.0609 | M87: =L87 * (1 + Вводные!M224) -> 1.092727 | N87: =M87 * (1 + Вводные!N224) -> 1.1255088 | O87: =N87 * (1 + Вводные!O224) -> 1.1592741 | P87: =O87 * (1 + Вводные!P224) -> 1.1940523 | Q87: =P87 * (1 + Вводные!Q224) -> 1.2298739 | ... BJ87: =BI87 * (1 + Вводные!BJ224) -> 4.6508859
D88: =Вводные!$D$199 -> Темп роста Ежемесячный расход на цели 8 | E88: % | I88: 1 | J88: =I88 * (1 + Вводные!J225) -> 1 | K88: =J88 * (1 + Вводные!K225) -> 1.03 | L88: =K88 * (1 + Вводные!L225) -> 1.0609 | M88: =L88 * (1 + Вводные!M225) -> 1.092727 | N88: =M88 * (1 + Вводные!N225) -> 1.1255088 | O88: =N88 * (1 + Вводные!O225) -> 1.1592741 | P88: =O88 * (1 + Вводные!P225) -> 1.1940523 | Q88: =P88 * (1 + Вводные!Q225) -> 1.2298739 | ... BJ88: =BI88 * (1 + Вводные!BJ225) -> 4.6508859
D89: =Вводные!$D$200 -> Темп роста Ежемесячный расход на цели 9 | E89: % | I89: 1 | J89: =I89 * (1 + Вводные!J226) -> 1 | K89: =J89 * (1 + Вводные!K226) -> 1.03 | L89: =K89 * (1 + Вводные!L226) -> 1.0609 | M89: =L89 * (1 + Вводные!M226) -> 1.092727 | N89: =M89 * (1 + Вводные!N226) -> 1.1255088 | O89: =N89 * (1 + Вводные!O226) -> 1.1592741 | P89: =O89 * (1 + Вводные!P226) -> 1.1940523 | Q89: =P89 * (1 + Вводные!Q226) -> 1.2298739 | ... BJ89: =BI89 * (1 + Вводные!BJ226) -> 4.6508859
D90: =Вводные!$D$201 -> Темп роста Ежемесячный расход на цели 10 | E90: % | I90: 1 | J90: =I90 * (1 + Вводные!J227) -> 1 | K90: =J90 * (1 + Вводные!K227) -> 1.03 | L90: =K90 * (1 + Вводные!L227) -> 1.0609 | M90: =L90 * (1 + Вводные!M227) -> 1.092727 | N90: =M90 * (1 + Вводные!N227) -> 1.1255088 | O90: =N90 * (1 + Вводные!O227) -> 1.1592741 | P90: =O90 * (1 + Вводные!P227) -> 1.1940523 | Q90: =P90 * (1 + Вводные!Q227) -> 1.2298739 | ... BJ90: =BI90 * (1 + Вводные!BJ227) -> 4.6508859

Sheet Баланс
D2: Баланс на текущий год
D3: Доход | F3: Расход
D4: Ежемесячный
D5: =Доходы!I32 -> 156000 | F5: =SUM(Расходы!I52,Цели!I42) -> -96000
D6: Ежегодный
D7: =Доходы!I48 -> 0 | F7: =SUM(Расходы!I98,Цели!I68) -> -41000
D8: Всего
D9: =SUM(D5,D7) -> 156000 | E9: =SUM(D9,F9) -> 19000 | F9: =SUM(F5,F7) -> -137000

Sheet Сбережения
D3: =Вводные!D3 -> Год | I3: =Вводные!J3 -> 2024 | J3: =Вводные!K3 -> 2025 | K3: =Вводные!L3 -> 2026 | L3: =Вводные!M3 -> 2027 | M3: =Вводные!N3 -> 2028 | N3: =Вводные!O3 -> 2029 | O3: =Вводные!P3 -> 2030 | P3: =Вводные!Q3 -> 2031 | ... BI3: =Вводные!BJ3 -> 2076
D4: =Вводные!D4 -> Возраст | I4: =Вводные!J4 -> 31 | J4: =Вводные!K4 -> 32 | K4: =Вводные!L4 -> 33 | L4: =Вводные!M4 -> 34 | M4: =Вводные!N4 -> 35 | N4: =Вводные!O4 -> 36 | O4: =Вводные!P4 -> 37 | P4: =Вводные!Q4 -> 38 | ... BI4: =Вводные!BJ4 -> 83
D5: =Вводные!D5 -> № периода | I5: =Вводные!J5 -> 1 | J5: =Вводные!K5 -> 2 | K5: =Вводные!L5 -> 3 | L5: =Вводные!M5 -> 4 | M5: =Вводные!N5 -> 5 | N5: =Вводные!O5 -> 6 | O5: =Вводные!P5 -> 7 | P5: =Вводные!Q5 -> 8 | ... BI5: =Вводные!BJ5 -> 53
B8: =MAX( $B$7:B7 ) + 1 -> 1 | D8: Сбережения
D10: Сбережения | E10: USD / год | I10: =SUM(I11:I13) -> 19000 | J10: =SUM(J11:J13) -> 51880 | K10: =SUM(K11:K13) -> 57066.4 | L10: =SUM(L11:L13) -> 59318.392 | M10: =SUM(M11:M13) -> 61637.944 | N10: =SUM(N11:N13) -> 67027.082 | O10: =SUM(O11:O13) -> 69487.895 | P10: =SUM(P11:P13) -> 72022.531 | ... BI10: =SUM(BI11:BI13) -> 436054.42
D11: Доходы | E11: USD / год | I11: =Доходы!J28 -> 156000 | J11: =Доходы!K28 -> 192360 | K11: =Доходы!L28 -> 198130.8 | L11: =Доходы!M28 -> 204074.72 | M11: =Доходы!N28 -> 210196.97 | N11: =Доходы!O28 -> 216502.87 | O11: =Доходы!P28 -> 222997.96 | P11: =Доходы!Q28 -> 229687.9 | ... BI11: =Доходы!BJ28 -> 868586.81
D12: Расходы | E12: USD / год | I12: =Расходы!J48 -> -117000 | J12: =Расходы!K48 -> -119880 | K12: =Расходы!L48 -> -119846.4 | L12: =Расходы!M48 -> -122901.79 | M12: =Расходы!N48 -> -126048.85 | N12: =Расходы!O48 -> -126290.31 | O12: =Расходы!P48 -> -129629.02 | P12: =Расходы!Q48 -> -133067.89 | ... BI12: =Расходы!BJ48 -> -432532.39
D13: Расходы на цели | E13: USD / год | I13: =Цели!J38 -> -20000 | J13: =Цели!K38 -> -20600 | K13: =Цели!L38 -> -21218 | L13: =Цели!M38 -> -21854.54 | M13: =Цели!N38 -> -22510.176 | N13: =Цели!O38 -> -23185.481 | O13: =Цели!P38 -> -23881.046 | P13: =Цели!Q38 -> -24597.477 | ... BI13: =Цели!BJ38 -> 0
D15: Доходность на инвестированный капитал | E15: % | F15: =Вводные!F15 -> 0.06 | I15: 1 | J15: =1 + $F$15 -> 1.06 | K15: =1 + $F$15 -> 1.06 | L15: =1 + $F$15 -> 1.06 | M15: =1 + $F$15 -> 1.06 | N15: =1 + $F$15 -> 1.06 | O15: =1 + $F$15 -> 1.06 | P15: =1 + $F$15 -> 1.06 | Q15: =1 + $F$15 -> 1.06 | ... BI15: =1 + $F$15 -> 1.06
D17: Накопления | E17: USD / год | I17: =I10 + H17 * H15 -> 19000 | J17: =J10 + I17 * I15 -> 70880 | K17: =K10 + J17 * J15 -> 132199.2 | L17: =L10 + K17 * K15 -> 199449.54 | M17: =M10 + L17 * L15 -> 273054.46 | N17: =N10 + M17 * M15 -> 356464.81 | O17: =O10 + N17 * N15 -> 447340.59 | P17: =P10 + O17 * O15 -> 546203.56 | ... BI17: =BI10 + BH17 * BH15 -> 37771112

Sheet Пенсия
D3: =Вводные!D3 -> Год | J3: =Вводные!J3 -> 2024 | K3: =Вводные!K3 -> 2025 | L3: =Вводные!L3 -> 2026 | M3: =Вводные!M3 -> 2027 | N3: =Вводные!N3 -> 2028 | O3: =Вводные!O3 -> 2029 | P3: =Вводные!P3 -> 2030 | Q3: =Вводные!Q3 -> 2031 | ... BJ3: =Вводные!BJ3 -> 2076
D4: =Вводные!D4 -> Возраст | J4: =Вводные!J4 -> 31 | K4: =Вводные!K4 -> 32 | L4: =Вводные!L4 -> 33 | M4: =Вводные!M4 -> 34 | N4: =Вводные!N4 -> 35 | O4: =Вводные!O4 -> 36 | P4: =Вводные!P4 -> 37 | Q4: =Вводные!Q4 -> 38 | ... BJ4: =Вводные!BJ4 -> 83
D5: =Вводные!D5 -> № периода | J5: =Вводные!J5 -> 1 | K5: =Вводные!K5 -> 2 | L5: =Вводные!L5 -> 3 | M5: =Вводные!M5 -> 4 | N5: =Вводные!N5 -> 5 | O5: =Вводные!O5 -> 6 | P5: =Вводные!P5 -> 7 | Q5: =Вводные!Q5 -> 8 | ... BJ5: =Вводные!BJ5 -> 53
B8: =MAX( $B$7:B7 ) + 1 -> 1 | D8: Пенсия
C10: =MAX( $B$7:C9 ) + 0.1 -> 1.1 | D10: Вариант расходования процентов от накоплений
D12: Возрат выхода на пенсию | E12: лет | F12: =Вводные!F257 -> 50
D13: Текущий возраст | E13: лет | F13: =YEAR(TODAY()) - Вводные!F11 -> 33
D14: Год выхода на пенсию | E14: год | F14: =YEAR(TODAY()) + (F12 - F13) -> 2043
D15: Сумма накоплений в год выхода на пенсию | E15: USD | F15: =HLOOKUP($F$14,Сбережения!$I$3:$BI$17,15,0) -> 2614402.2
D16: Доходность | E16: % | F16: =Вводные!F15 -> 0.06
D17: Средняя инфляция | E17: % | F17: =AVERAGE(J23:INDEX(J23:BJ23,1,MATCH(F14,J3:BJ3,0))) -> 0.031
D18: Реальная доходность | E18: % | F18: =(1 + F16) / (1 + F17) -1 -> 0.028128031
D19: Доход доступный для трат | E19: USD / год | F19: =F15 * F18 -> 73537.986
D20: Доход доступный для трат в текущем выражении | E20: USD / год | F20: =F19*INDEX(J24:BJ24,1,MATCH(F14,J3:BJ3,0)) -> 39940.653
D21: Доход доступный для трат в текущем выражении в месяц | E21: USD / мес. | F21: =F20 / Вводные!F12 -> 3328.3877
D23: Инфляция | E23: % | J23: =Вводные!J14 -> 0.05 | K23: =Вводные!K14 -> 0.03 | L23: =Вводные!L14 -> 0.03 | M23: =Вводные!M14 -> 0.03 | N23: =Вводные!N14 -> 0.03 | O23: =Вводные!O14 -> 0.03 | P23: =Вводные!P14 -> 0.03 | Q23: =Вводные!Q14 -> 0.03 | ... BJ23: =Вводные!BJ14 -> 0.03
D24: Коэффициент приведения | E24: x | I24: 1 | J24: =I24 / (1+J23) -> 0.95238095 | K24: =J24 / (1+K23) -> 0.9246417 | L24: =K24 / (1+L23) -> 0.89771039 | M24: =L24 / (1+M23) -> 0.87156349 | N24: =M24 / (1+N23) -> 0.84617814 | O24: =N24 / (1+O23) -> 0.82153218 | P24: =O24 / (1+P23) -> 0.79760405 | Q24: =P24 / (1+Q23) -> 0.77437287 | ... BJ24: =BI24 / (1+BJ23) -> 0.2047741
C26: =MAX( $B$7:C25 ) + 0.1 -> 1.2 | D26: Вариант расходования всей суммы накоплений
D28: Возрат выхода на пенсию | E28: лет | F28: =F12 -> 50
D29: Текущий возраст | E29: лет | F29: =F13 -> 33
D30: Год выхода на пенсию | E30: год | F30: =F14 -> 2043
D31: Сумма накоплений в год выхода на пенсию | E31: USD | F31: =F15 -> 2614402.2
D32: Доходность | E32: % | F32: =F16 -> 0.06
D33: Средняя инфляция | E33: % | F33: =F17 -> 0.031
D34: Реальная доходность | E34: % | F34: =F18 -> 0.028128031
D35: Желаемый уровень расхода | E35: USD / год | F35: =Вводные!F258 * Вводные!F12 -> -120000
D36: Желаемый уровень расхода в выражении года выхода на пенсию | E36: USD / год | F36: =F35/INDEX(J24:BJ24,1,MATCH(F30,J3:BJ3,0)) -> -220941.76
D37: Количество пенсионных лет | E37: год | F37: =COUNTIF(J45:BJ45, ">=0") -> 13
D38: Возраст полного израсходования накоплений | E38: лет | F38: =SUM(F28,F37) -> 63
D40: Год | I40: =F14 -> 2043 | J40: =I40+1 -> 2044 | K40: =J40+1 -> 2045 | L40: =K40+1 -> 2046 | M40: =L40+1 -> 2047 | N40: =M40+1 -> 2048 | O40: =N40+1 -> 2049 | P40: =O40+1 -> 2050 | Q40: =P40+1 -> 2051 | ... BJ40: =BI40+1 -> 2096
D41: Накопления н.п. | J41: =I45 -> 2614402.2 | K41: =J45 -> 2529807.9 | L41: =K45 -> 2432652.7 | M41: =L45 -> 2321951 | N41: =M45 -> 2196650.7 | O41: =N45 -> 2055629.3 | P41: =O45 -> 1897689.1 | Q41: =P45 -> 1721552.9 | ... BJ41: =BI45 -> -77487262
D42: Расходы | I42: =F36 -> -220941.76 | J42: =I42 * (1 + J43) -> -227790.96 | K42: =J42 * (1 + K43) -> -234852.48 | L42: =K42 * (1 + L43) -> -242132.9 | M42: =L42 * (1 + M43) -> -249639.02 | N42: =M42 * (1 + N43) -> -257377.83 | O42: =N42 * (1 + O43) -> -265356.55 | P42: =O42 * (1 + P43) -> -273582.6 | Q42: =P42 * (1 + Q43) -> -282063.66 | ... BJ42: =BI42 * (1 + BJ43) -> -1114261.4
D43: Средняя инфляция | I43: =F33 -> 0.031 | J43: =$I$43 -> 0.031 | K43: =$I$43 -> 0.031 | L43: =$I$43 -> 0.031 | M43: =$I$43 -> 0.031 | N43: =$I$43 -> 0.031 | O43: =$I$43 -> 0.031 | P43: =$I$43 -> 0.031 | Q43: =$I$43 -> 0.031 | ... BJ43: =$I$43 -> 0.031
D44: Доходность | I44: =F32 -> 0.06 | J44: =$I$44 -> 0.06 | K44: =$I$44 -> 0.06 | L44: =$I$44 -> 0.06 | M44: =$I$44 -> 0.06 | N44: =$I$44 -> 0.06 | O44: =$I$44 -> 0.06 | P44: =$I$44 -> 0.06 | Q44: =$I$44 -> 0.06 | ... BJ44: =$I$44 -> 0.06
D45: Накопления к.п. | I45: =F31 -> 2614402.2 | J45: =SUM(J41,J42) * ( 1 + J44 ) -> 2529807.9 | K45: =SUM(K41,K42) * ( 1 + K44 ) -> 2432652.7 | L45: =SUM(L41,L42) * ( 1 + L44 ) -> 2321951 | M45: =SUM(M41,M42) * ( 1 + M44 ) -> 2196650.7 | N45: =SUM(N41,N42) * ( 1 + N44 ) -> 2055629.3 | O45: =SUM(O41,O42) * ( 1 + O44 ) -> 1897689.1 | P45: =SUM(P41,P42) * ( 1 + P44 ) -> 1721552.9 | Q45: =SUM(Q41,Q42) * ( 1 + Q44 ) -> 1525858.6 | ... BJ45: =SUM(BJ41,BJ42) * ( 1 + BJ44 ) -> -83317615
